Workbook
Name Slicer_Category: #N/A
Name Slicer_Date_Year: #N/A

Sheet Sales_Table
A1: Date | B1: Order_id | C1: Product_id | D1: Cost Price | E1: Selling Price | F1: Quantity_Sold | G1: Total_Sale | H1: Mode of Payment | I1: Profit | J1: Date(Year) | K1: Date(Month)
A2: 10/02/2023 | B2: O2001 | C2: P101 | D2: =IF(C2="P101",271,IF(C2="P102",408,IF(C2="P103",735,IF(C2="P104",749,IF(C2="P105",807,IF(C2="P106",365,IF(C2="P107",213,IF(C2="P108",117,IF(C2="P109",399,IF(C2="P110",520,IF(C2="P111",505,IF(C2="P112",380,IF(C2="P113",392,IF(C2="P114",164,IF(C2="P115",282,IF(C2="P116",386,IF(C2="P117",217,IF(C2="P118",518,IF(C2="P119",321,IF(C2="P120",593,IF(C2="P121",104,0))))))))))))))))))))) -> 271 | E2: 476 | F2: 3 | G2: =Sales_Table!$E2*F2 -> 1428 | H2: COD | I2: =G2-(D2*F2) -> 615 | J2: =YEAR(Table16[[#This Row],[Date]]) -> 2023 | K2: =TEXT(Table16[[#This Row],[Date]],"MMMM") -> February
A3: 18/09/2024 | B3: O2002 | C3: P101 | D3: =IF(C3="P101",271,IF(C3="P102",408,IF(C3="P103",735,IF(C3="P104",749,IF(C3="P105",807,IF(C3="P106",365,IF(C3="P107",213,IF(C3="P108",117,IF(C3="P109",399,IF(C3="P110",520,IF(C3="P111",505,IF(C3="P112",380,IF(C3="P113",392,IF(C3="P114",164,IF(C3="P115",282,IF(C3="P116",386,IF(C3="P117",217,IF(C3="P118",518,IF(C3="P119",321,IF(C3="P120",593,IF(C3="P121",104,0))))))))))))))))))))) -> 271 | E3: 476 | F3: 3 | G3: =Sales_Table!$E3*F3 -> 1428 | H3: COD | I3: =G3-(D3*F3) -> 615 | J3: =YEAR(Table16[[#This Row],[Date]]) -> 2024 | K3: =TEXT(Table16[[#This Row],[Date]],"MMMM") -> September
A4: 09/07/2020 | B4: O2003 | C4: P101 | D4: =IF(C4="P101",271,IF(C4="P102",408,IF(C4="P103",735,IF(C4="P104",749,IF(C4="P105",807,IF(C4="P106",365,IF(C4="P107",213,IF(C4="P108",117,IF(C4="P109",399,IF(C4="P110",520,IF(C4="P111",505,IF(C4="P112",380,IF(C4="P113",392,IF(C4="P114",164,IF(C4="P115",282,IF(C4="P116",386,IF(C4="P117",217,IF(C4="P118",518,IF(C4="P119",321,IF(C4="P120",593,IF(C4="P121",104,0))))))))))))))))))))) -> 271 | E4: 476 | F4: 7 | G4: =Sales_Table!$E4*F4 -> 3332 | H4: COD | I4: =G4-(D4*F4) -> 1435 | J4: =YEAR(Table16[[#This Row],[Date]]) -> 2020 | K4: =TEXT(Table16[[#This Row],[Date]],"MMMM") -> July
A5: 30/07/2022 | B5: O2004 | C5: P101 | D5: =IF(C5="P101",271,IF(C5="P102",408,IF(C5="P103",735,IF(C5="P104",749,IF(C5="P105",807,IF(C5="P106",365,IF(C5="P107",213,IF(C5="P108",117,IF(C5="P109",399,IF(C5="P110",520,IF(C5="P111",505,IF(C5="P112",380,IF(C5="P113",392,IF(C5="P114",164,IF(C5="P115",282,IF(C5="P116",386,IF(C5="P117",217,IF(C5="P118",518,IF(C5="P119",321,IF(C5="P120",593,IF(C5="P121",104,0))))))))))))))))))))) -> 271 | E5: 476 | F5: 8 | G5: =Sales_Table!$E5*F5 -> 3808 | H5: COD | I5: =G5-(D5*F5) -> 1640 | J5: =YEAR(Table16[[#This Row],[Date]]) -> 2022 | K5: =TEXT(Table16[[#This Row],[Date]],"MMMM") -> July
A6: 10/01/2020 | B6: O2005 | C6: P101 | D6: =IF(C6="P101",271,IF(C6="P102",408,IF(C6="P103",735,IF(C6="P104",749,IF(C6="P105",807,IF(C6="P106",365,IF(C6="P107",213,IF(C6="P108",117,IF(C6="P109",399,IF(C6="P110",520,IF(C6="P111",505,IF(C6="P112",380,IF(C6="P113",392,IF(C6="P114",164,IF(C6="P115",282,IF(C6="P116",386,IF(C6="P117",217,IF(C6="P118",518,IF(C6="P119",321,IF(C6="P120",593,IF(C6="P121",104,0))))))))))))))))))))) -> 271 | E6: 476 | F6: 5 | G6: =Sales_Table!$E6*F6 -> 2380 | H6: Credit | I6: =G6-(D6*F6) -> 1025 | J6: =YEAR(Table16[[#This Row],[Date]]) -> 2020 | K6: =TEXT(Table16[[#This Row],[Date]],"MMMM") -> January
A7: 29/03/2021 | B7: O2006 | C7: P101 | D7: =IF(C7="P101",271,IF(C7="P102",408,IF(C7="P103",735,IF(C7="P104",749,IF(C7="P105",807,IF(C7="P106",365,IF(C7="P107",213,IF(C7="P108",117,IF(C7="P109",399,IF(C7="P110",520,IF(C7="P111",505,IF(C7="P112",380,IF(C7="P113",392,IF(C7="P114",164,IF(C7="P115",282,IF(C7="P116",386,IF(C7="P117",217,IF(C7="P118",518,IF(C7="P119",321,IF(C7="P120",593,IF(C7="P121",104,0))))))))))))))))))))) -> 271 | E7: 476 | F7: 1 | G7: =Sales_Table!$E7*F7 -> 476 | H7: EMI | I7: =G7-(D7*F7) -> 205 | J7: =YEAR(Table16[[#This Row],[Date]]) -> 2021 | K7: =TEXT(Table16[[#This Row],[Date]],"MMMM") -> March
A8: 21/10/2023 | B8: O2007 | C8: P101 | D8: =IF(C8="P101",271,IF(C8="P102",408,IF(C8="P103",735,IF(C8="P104",749,IF(C8="P105",807,IF(C8="P106",365,IF(C8="P107",213,IF(C8="P108",117,IF(C8="P109",399,IF(C8="P110",520,IF(C8="P111",505,IF(C8="P112",380,IF(C8="P113",392,IF(C8="P114",164,IF(C8="P115",282,IF(C8="P116",386,IF(C8="P117",217,IF(C8="P118",518,IF(C8="P119",321,IF(C8="P120",593,IF(C8="P121",104,0))))))))))))))))))))) -> 271 | E8: 476 | F8: 7 | G8: =Sales_Table!$E8*F8 -> 3332 | H8: COD | I8: =G8-(D8*F8) -> 1435 | J8: =YEAR(Table16[[#This Row],[Date]]) -> 2023 | K8: =TEXT(Table16[[#This Row],[Date]],"MMMM") -> October
A9: 25/05/2025 | B9: O2008 | C9: P101 | D9: =IF(C9="P101",271,IF(C9="P102",408,IF(C9="P103",735,IF(C9="P104",749,IF(C9="P105",807,IF(C9="P106",365,IF(C9="P107",213,IF(C9="P108",117,IF(C9="P109",399,IF(C9="P110",520,IF(C9="P111",505,IF(C9="P112",380,IF(C9="P113",392,IF(C9="P114",164,IF(C9="P115",282,IF(C9="P116",386,IF(C9="P117",217,IF(C9="P118",518,IF(C9="P119",321,IF(C9="P120",593,IF(C9="P121",104,0))))))))))))))))))))) -> 271 | E9: 476 | F9: 2 | G9: =Sales_Table!$E9*F9 -> 952 | H9: Debit | I9: =G9-(D9*F9) -> 410 | J9: =YEAR(Table16[[#This Row],[Date]]) -> 2025 | K9: =TEXT(Table16[[#This Row],[Date]],"MMMM") -> May
A10: 13/12/2020 | B10: O2009 | C10: P101 | D10: =IF(C10="P101",271,IF(C10="P102",408,IF(C10="P103",735,IF(C10="P104",749,IF(C10="P105",807,IF(C10="P106",365,IF(C10="P107",213,IF(C10="P108",117,IF(C10="P109",399,IF(C10="P110",520,IF(C10="P111",505,IF(C10="P112",380,IF(C10="P113",392,IF(C10="P114",164,IF(C10="P115",282,IF(C10="P116",386,IF(C10="P117",217,IF(C10="P118",518,IF(C10="P119",321,IF(C10="P120",593,IF(C10="P121",104,0))))))))))))))))))))) -> 271 | E10: 476 | F10: 1 | G10: =Sales_Table!$E10*F10 -> 476 | H10: EMI | I10: =G10-(D10*F10) -> 205 | J10: =YEAR(Table16[[#This Row],[Date]]) -> 2020 | K10: =TEXT(Table16[[#This Row],[Date]],"MMMM") -> December
A11: 15/04/2023 | B11: O2010 | C11: P101 | D11: =IF(C11="P101",271,IF(C11="P102",408,IF(C11="P103",735,IF(C11="P104",749,IF(C11="P105",807,IF(C11="P106",365,IF(C11="P107",213,IF(C11="P108",117,IF(C11="P109",399,IF(C11="P110",520,IF(C11="P111",505,IF(C11="P112",380,IF(C11="P113",392,IF(C11="P114",164,IF(C11="P115",282,IF(C11="P116",386,IF(C11="P117",217,IF(C11="P118",518,IF(C11="P119",321,IF(C11="P120",593,IF(C11="P121",104,0))))))))))))))))))))) -> 271 | E11: 476 | F11: 1 | G11: =Sales_Table!$E11*F11 -> 476 | H11: COD | I11: =G11-(D11*F11) -> 205 | J11: =YEAR(Table16[[#This Row],[Date]]) -> 2023 | K11: =TEXT(Table16[[#This Row],[Date]],"MMMM") -> April
A12: 23/05/2020 | B12: O2011 | C12: P101 | D12: =IF(C12="P101",271,IF(C12="P102",408,IF(C12="P103",735,IF(C12="P104",749,IF(C12="P105",807,IF(C12="P106",365,IF(C12="P107",213,IF(C12="P108",117,IF(C12="P109",399,IF(C12="P110",520,IF(C12="P111",505,IF(C12="P112",380,IF(C12="P113",392,IF(C12="P114",164,IF(C12="P115",282,IF(C12="P116",386,IF(C12="P117",217,IF(C12="P118",518,IF(C12="P119",321,IF(C12="P120",593,IF(C12="P121",104,0))))))))))))))))))))) -> 271 | E12: 476 | F12: 3 | G12: =Sales_Table!$E12*F12 -> 1428 | H12: COD | I12: =G12-(D12*F12) -> 615 | J12: =YEAR(Table16[[#This Row],[Date]]) -> 2020 | K12: =TEXT(Table16[[#This Row],[Date]],"MMMM") -> May
A13: 09/06/2021 | B13: O2012 | C13: P101 | D13: =IF(C13="P101",271,IF(C13="P102",408,IF(C13="P103",735,IF(C13="P104",749,IF(C13="P105",807,IF(C13="P106",365,IF(C13="P107",213,IF(C13="P108",117,IF(C13="P109",399,IF(C13="P110",520,IF(C13="P111",505,IF(C13="P112",380,IF(C13="P113",392,IF(C13="P114",164,IF(C13="P115",282,IF(C13="P116",386,IF(C13="P117",217,IF(C13="P118",518,IF(C13="P119",321,IF(C13="P120",593,IF(C13="P121",104,0))))))))))))))))))))) -> 271 | E13: 476 | F13: 4 | G13: =Sales_Table!$E13*F13 -> 1904 | H13: Credit | I13: =G13-(D13*F13) -> 820 | J13: =YEAR(Table16[[#This Row],[Date]]) -> 2021 | K13: =TEXT(Table16[[#This Row],[Date]],"MMMM") -> June
... A399: 02/10/2022 | B399: O2398 | C399: P121 | D399: =IF(C399="P101",271,IF(C399="P102",408,IF(C399="P103",735,IF(C399="P104",749,IF(C399="P105",807,IF(C399="P106",365,IF(C399="P107",213,IF(C399="P108",117,IF(C399="P109",399,IF(C399="P110",520,IF(C399="P111",505,IF(C399="P112",380,IF(C399="P113",392,IF(C399="P114",164,IF(C399="P115",282,IF(C399="P116",386,IF(C399="P117",217,IF(C399="P118",518,IF(C399="P119",321,IF(C399="P120",593,IF(C399="P121",104,0))))))))))))))))))))) -> 104 | E399: 130 | F399: 8 | G399: =Sales_Table!$E399*F399 -> 1040 | H399: EMI | I399: =G399-(D399*F399) -> 208 | J399: =YEAR(Table16[[#This Row],[Date]]) -> 2022 | K399: =TEXT(Table16[[#This Row],[Date]],"MMMM") -> October
A400: 19/08/2022 | B400: O2399 | C400: P122 | D400: =IF(C401="P122",183,IF(C401="P123",371,IF(C401="P124",415,IF(C401="P125",508,IF(C401="P126",358,IF(C401="P127",712,IF(C401="P128",126,IF(C401="P129",280,IF(C401="P130",695,IF(C401="P131",216,IF(C401="P132",540,IF(C401="P133",181,IF(C401="P134",353,IF(C401="P135",226,IF(C401="P136",604,IF(C401="P137",97,IF(C401="P138",465,IF(C401="P139",637,IF(C401="P140",307,0))))))))))))))))))) -> 183 | E400: 155 | F400: 3 | G400: =Sales_Table!$E400*F400 -> 465 | H400: EMI | I400: =G400-(D400*F400) -> -84 | J400: =YEAR(Table16[[#This Row],[Date]]) -> 2022 | K400: =TEXT(Table16[[#This Row],[Date]],"MMMM") -> August
A401: 01/07/2020 | B401: O2400 | C401: P122 | D401: =IF(C401="P122",183,IF(C401="P123",371,IF(C401="P124",415,IF(C401="P125",508,IF(C401="P126",358,IF(C401="P127",712,IF(C401="P128",126,IF(C401="P129",280,IF(C401="P130",695,IF(C401="P131",216,IF(C401="P132",540,IF(C401="P133",181,IF(C401="P134",353,IF(C401="P135",226,IF(C401="P136",604,IF(C401="P137",97,IF(C401="P138",465,IF(C401="P139",637,IF(C401="P140",307,0))))))))))))))))))) -> 183 | E401: 155 | F401: 10 | G401: =Sales_Table!$E401*F401 -> 1550 | H401: COD | I401: =G401-(D401*F401) -> -280 | J401: =YEAR(Table16[[#This Row],[Date]]) -> 2020 | K401: =TEXT(Table16[[#This Row],[Date]],"MMMM") -> July
A402: 25/02/2025 | B402: O2401 | C402: P122 | D402: =IF(C402="P122",183,IF(C402="P123",371,IF(C402="P124",415,IF(C402="P125",508,IF(C402="P126",358,IF(C402="P127",712,IF(C402="P128",126,IF(C402="P129",280,IF(C402="P130",695,IF(C402="P131",216,IF(C402="P132",540,IF(C402="P133",181,IF(C402="P134",353,IF(C402="P135",226,IF(C402="P136",604,IF(C402="P137",97,IF(C402="P138",465,IF(C402="P139",637,IF(C402="P140",307,0))))))))))))))))))) -> 183 | E402: 155 | F402: 4 | G402: =Sales_Table!$E402*F402 -> 620 | H402: Debit | I402: =G402-(D402*F402) -> -112 | J402: =YEAR(Table16[[#This Row],[Date]]) -> 2025 | K402: =TEXT(Table16[[#This Row],[Date]],"MMMM") -> February
A403: 20/04/2022 | B403: O2402 | C403: P122 | D403: =IF(C403="P122",183,IF(C403="P123",371,IF(C403="P124",415,IF(C403="P125",508,IF(C403="P126",358,IF(C403="P127",712,IF(C403="P128",126,IF(C403="P129",280,IF(C403="P130",695,IF(C403="P131",216,IF(C403="P132",540,IF(C403="P133",181,IF(C403="P134",353,IF(C403="P135",226,IF(C403="P136",604,IF(C403="P137",97,IF(C403="P138",465,IF(C403="P139",637,IF(C403="P140",307,0))))))))))))))))))) -> 183 | E403: 155 | F403: 9 | G403: =Sales_Table!$E403*F403 -> 1395 | H403: Debit | I403: =G403-(D403*F403) -> -252 | J403: =YEAR(Table16[[#This Row],[Date]]) -> 2022 | K403: =TEXT(Table16[[#This Row],[Date]],"MMMM") -> April
A404: 21/09/2020 | B404: O2403 | C404: P122 | D404: =IF(C404="P122",183,IF(C404="P123",371,IF(C404="P124",415,IF(C404="P125",508,IF(C404="P126",358,IF(C404="P127",712,IF(C404="P128",126,IF(C404="P129",280,IF(C404="P130",695,IF(C404="P131",216,IF(C404="P132",540,IF(C404="P133",181,IF(C404="P134",353,IF(C404="P135",226,IF(C404="P136",604,IF(C404="P137",97,IF(C404="P138",465,IF(C404="P139",637,IF(C404="P140",307,0))))))))))))))))))) -> 183 | E404: 155 | F404: 5 | G404: =Sales_Table!$E404*F404 -> 775 | H404: EMI | I404: =G404-(D404*F404) -> -140 | J404: =YEAR(Table16[[#This Row],[Date]]) -> 2020 | K404: =TEXT(Table16[[#This Row],[Date]],"MMMM") -> September
A405: 21/05/2021 | B405: O2404 | C405: P122 | D405: =IF(C405="P122",183,IF(C405="P123",371,IF(C405="P124",415,IF(C405="P125",508,IF(C405="P126",358,IF(C405="P127",712,IF(C405="P128",126,IF(C405="P129",280,IF(C405="P130",695,IF(C405="P131",216,IF(C405="P132",540,IF(C405="P133",181,IF(C405="P134",353,IF(C405="P135",226,IF(C405="P136",604,IF(C405="P137",97,IF(C405="P138",465,IF(C405="P139",637,IF(C405="P140",307,0))))))))))))))))))) -> 183 | E405: 155 | F405: 7 | G405: =Sales_Table!$E405*F405 -> 1085 | H405: Debit | I405: =G405-(D405*F405) -> -196 | J405: =YEAR(Table16[[#This Row],[Date]]) -> 2021 | K405: =TEXT(Table16[[#This Row],[Date]],"MMMM") -> May
A406: 06/09/2024 | B406: O2405 | C406: P122 | D406: =IF(C406="P122",183,IF(C406="P123",371,IF(C406="P124",415,IF(C406="P125",508,IF(C406="P126",358,IF(C406="P127",712,IF(C406="P128",126,IF(C406="P129",280,IF(C406="P130",695,IF(C406="P131",216,IF(C406="P132",540,IF(C406="P133",181,IF(C406="P134",353,IF(C406="P135",226,IF(C406="P136",604,IF(C406="P137",97,IF(C406="P138",465,IF(C406="P139",637,IF(C406="P140",307,0))))))))))))))))))) -> 183 | E406: 155 | F406: 2 | G406: =Sales_Table!$E406*F406 -> 310 | H406: COD | I406: =G406-(D406*F406) -> -56 | J406: =YEAR(Table16[[#This Row],[Date]]) -> 2024 | K406: =TEXT(Table16[[#This Row],[Date]],"MMMM") -> September
A407: 24/12/2020 | B407: O2406 | C407: P122 | D407: =IF(C407="P122",183,IF(C407="P123",371,IF(C407="P124",415,IF(C407="P125",508,IF(C407="P126",358,IF(C407="P127",712,IF(C407="P128",126,IF(C407="P129",280,IF(C407="P130",695,IF(C407="P131",216,IF(C407="P132",540,IF(C407="P133",181,IF(C407="P134",353,IF(C407="P135",226,IF(C407="P136",604,IF(C407="P137",97,IF(C407="P138",465,IF(C407="P139",637,IF(C407="P140",307,0))))))))))))))))))) -> 183 | E407: 155 | F407: 5 | G407: =Sales_Table!$E407*F407 -> 775 | H407: Credit | I407: =G407-(D407*F407) -> -140 | J407: =YEAR(Table16[[#This Row],[Date]]) -> 2020 | K407: =TEXT(Table16[[#This Row],[Date]],"MMMM") -> December
A408: 18/04/2020 | B408: O2407 | C408: P122 | D408: =IF(C408="P122",183,IF(C408="P123",371,IF(C408="P124",415,IF(C408="P125",508,IF(C408="P126",358,IF(C408="P127",712,IF(C408="P128",126,IF(C408="P129",280,IF(C408="P130",695,IF(C408="P131",216,IF(C408="P132",540,IF(C408="P133",181,IF(C408="P134",353,IF(C408="P135",226,IF(C408="P136",604,IF(C408="P137",97,IF(C408="P138",465,IF(C408="P139",637,IF(C408="P140",307,0))))))))))))))))))) -> 183 | E408: 155 | F408: 1 | G408: =Sales_Table!$E408*F408 -> 155 | H408: COD | I408: =G408-(D408*F408) -> -28 | J408: =YEAR(Table16[[#This Row],[Date]]) -> 2020 | K408: =TEXT(Table16[[#This Row],[Date]],"MMMM") -> April
A409: 13/03/2023 | B409: O2408 | C409: P122 | D409: =IF(C409="P122",183,IF(C409="P123",371,IF(C409="P124",415,IF(C409="P125",508,IF(C409="P126",358,IF(C409="P127",712,IF(C409="P128",126,IF(C409="P129",280,IF(C409="P130",695,IF(C409="P131",216,IF(C409="P132",540,IF(C409="P133",181,IF(C409="P134",353,IF(C409="P135",226,IF(C409="P136",604,IF(C409="P137",97,IF(C409="P138",465,IF(C409="P139",637,IF(C409="P140",307,0))))))))))))))))))) -> 183 | E409: 155 | F409: 6 | G409: =Sales_Table!$E409*F409 -> 930 | H409: Credit | I409: =G409-(D409*F409) -> -168 | J409: =YEAR(Table16[[#This Row],[Date]]) -> 2023 | K409: =TEXT(Table16[[#This Row],[Date]],"MMMM") -> March
A410: 15/06/2021 | B410: O2409 | C410: P122 | D410: =IF(C410="P122",183,IF(C410="P123",371,IF(C410="P124",415,IF(C410="P125",508,IF(C410="P126",358,IF(C410="P127",712,IF(C410="P128",126,IF(C410="P129",280,IF(C410="P130",695,IF(C410="P131",216,IF(C410="P132",540,IF(C410="P133",181,IF(C410="P134",353,IF(C410="P135",226,IF(C410="P136",604,IF(C410="P137",97,IF(C410="P138",465,IF(C410="P139",637,IF(C410="P140",307,0))))))))))))))))))) -> 183 | E410: 155 | F410: 2 | G410: =Sales_Table!$E410*F410 -> 310 | H410: EMI | I410: =G410-(D410*F410) -> -56 | J410: =YEAR(Table16[[#This Row],[Date]]) -> 2021 | K410: =TEXT(Table16[[#This Row],[Date]],"MMMM") -> June
A411: 13/12/2021 | B411: O2410 | C411: P122 | D411: =IF(C411="P122",183,IF(C411="P123",371,IF(C411="P124",415,IF(C411="P125",508,IF(C411="P126",358,IF(C411="P127",712,IF(C411="P128",126,IF(C411="P129",280,IF(C411="P130",695,IF(C411="P131",216,IF(C411="P132",540,IF(C411="P133",181,IF(C411="P134",353,IF(C411="P135",226,IF(C411="P136",604,IF(C411="P137",97,IF(C411="P138",465,IF(C411="P139",637,IF(C411="P140",307,0))))))))))))))))))) -> 183 | E411: 155 | F411: 6 | G411: =Sales_Table!$E411*F411 -> 930 | H411: Credit | I411: =G411-(D411*F411) -> -168 | J411: =YEAR(Table16[[#This Row],[Date]]) -> 2021 | K411: =TEXT(Table16[[#This Row],[Date]],"MMMM") -> December
A412: 15/09/2020 | B412: O2411 | C412: P122 | D412: =IF(C412="P122",183,IF(C412="P123",371,IF(C412="P124",415,IF(C412="P125",508,IF(C412="P126",358,IF(C412="P127",712,IF(C412="P128",126,IF(C412="P129",280,IF(C412="P130",695,IF(C412="P131",216,IF(C412="P132",540,IF(C412="P133",181,IF(C412="P134",353,IF(C412="P135",226,IF(C412="P136",604,IF(C412="P137",97,IF(C412="P138",465,IF(C412="P139",637,IF(C412="P140",307,0))))))))))))))))))) -> 183 | E412: 155 | F412: 5 | G412: =Sales_Table!$E412*F412 -> 775 | H412: COD | I412: =G412-(D412*F412) -> -140 | J412: =YEAR(Table16[[#This Row],[Date]]) -> 2020 | K412: =TEXT(Table16[[#This Row],[Date]],"MMMM") -> September
... A502: 21/03/2020 | B502: O2501 | C502: P126 | D502: =IF(C502="P122",183,IF(C502="P123",371,IF(C502="P124",415,IF(C502="P125",508,IF(C502="P126",358,IF(C502="P127",712,IF(C502="P128",126,IF(C502="P129",280,IF(C502="P130",695,IF(C502="P131",216,IF(C502="P132",540,IF(C502="P133",181,IF(C502="P134",353,IF(C502="P135",226,IF(C502="P136",604,IF(C502="P137",97,IF(C502="P138",465,IF(C502="P139",637,IF(C502="P140",307,0))))))))))))))))))) -> 358 | E502: 480 | F502: 4 | G502: =Sales_Table!$E502*F502 -> 1920 | H502: Credit | I502: =G502-(D502*F502) -> 488 | J502: =YEAR(Table16[[#This Row],[Date]]) -> 2020 | K502: =TEXT(Table16[[#This Row],[Date]],"MMMM") -> March
A503: 01/07/2022 | B503: O2502 | C503: P127 | D503: =IF(C503="P122",183,IF(C503="P123",371,IF(C503="P124",415,IF(C503="P125",508,IF(C503="P126",358,IF(C503="P127",712,IF(C503="P128",126,IF(C503="P129",280,IF(C503="P130",695,IF(C503="P131",216,IF(C503="P132",540,IF(C503="P133",181,IF(C503="P134",353,IF(C503="P135",226,IF(C503="P136",604,IF(C503="P137",97,IF(C503="P138",465,IF(C503="P139",637,IF(C503="P140",307,0))))))))))))))))))) -> 712 | E503: =IF(C503="P127",800,IF(C503="P128",180,IF(C503="P129",220,0))) -> 800 | F503: 9 | G503: =Sales_Table!$E503*F503 -> 7200 | H503: Debit | I503: =G503-(D503*F503) -> 792 | J503: =YEAR(Table16[[#This Row],[Date]]) -> 2022 | K503: =TEXT(Table16[[#This Row],[Date]],"MMMM") -> July
A504: 29/12/2024 | B504: O2503 | C504: P127 | D504: =IF(C504="P122",183,IF(C504="P123",371,IF(C504="P124",415,IF(C504="P125",508,IF(C504="P126",358,IF(C504="P127",712,IF(C504="P128",126,IF(C504="P129",280,IF(C504="P130",695,IF(C504="P131",216,IF(C504="P132",540,IF(C504="P133",181,IF(C504="P134",353,IF(C504="P135",226,IF(C504="P136",604,IF(C504="P137",97,IF(C504="P138",465,IF(C504="P139",637,IF(C504="P140",307,0))))))))))))))))))) -> 712 | E504: =IF(C504="P127",800,IF(C504="P128",180,IF(C504="P129",220,0))) -> 800 | F504: 2 | G504: =Sales_Table!$E504*F504 -> 1600 | H504: Credit | I504: =G504-(D504*F504) -> 176 | J504: =YEAR(Table16[[#This Row],[Date]]) -> 2024 | K504: =TEXT(Table16[[#This Row],[Date]],"MMMM") -> December
A505: 08/11/2024 | B505: O2504 | C505: P127 | D505: =IF(C505="P122",183,IF(C505="P123",371,IF(C505="P124",415,IF(C505="P125",508,IF(C505="P126",358,IF(C505="P127",712,IF(C505="P128",126,IF(C505="P129",280,IF(C505="P130",695,IF(C505="P131",216,IF(C505="P132",540,IF(C505="P133",181,IF(C505="P134",353,IF(C505="P135",226,IF(C505="P136",604,IF(C505="P137",97,IF(C505="P138",465,IF(C505="P139",637,IF(C505="P140",307,0))))))))))))))))))) -> 712 | E505: =IF(C505="P127",800,IF(C505="P128",180,IF(C505="P129",220,0))) -> 800 | F505: 10 | G505: =Sales_Table!$E505*F505 -> 8000 | H505: COD | I505: =G505-(D505*F505) -> 880 | J505: =YEAR(Table16[[#This Row],[Date]]) -> 2024 | K505: =TEXT(Table16[[#This Row],[Date]],"MMMM") -> November
A506: 13/08/2022 | B506: O2505 | C506: P127 | D506: =IF(C506="P122",183,IF(C506="P123",371,IF(C506="P124",415,IF(C506="P125",508,IF(C506="P126",358,IF(C506="P127",712,IF(C506="P128",126,IF(C506="P129",280,IF(C506="P130",695,IF(C506="P131",216,IF(C506="P132",540,IF(C506="P133",181,IF(C506="P134",353,IF(C506="P135",226,IF(C506="P136",604,IF(C506="P137",97,IF(C506="P138",465,IF(C506="P139",637,IF(C506="P140",307,0))))))))))))))))))) -> 712 | E506: =IF(C506="P127",800,IF(C506="P128",180,IF(C506="P129",220,0))) -> 800 | F506: 5 | G506: =Sales_Table!$E506*F506 -> 4000 | H506: Credit | I506: =G506-(D506*F506) -> 440 | J506: =YEAR(Table16[[#This Row],[Date]]) -> 2022 | K506: =TEXT(Table16[[#This Row],[Date]],"MMMM") -> August
A507: 11/03/2024 | B507: O2506 | C507: P127 | D507: =IF(C507="P122",183,IF(C507="P123",371,IF(C507="P124",415,IF(C507="P125",508,IF(C507="P126",358,IF(C507="P127",712,IF(C507="P128",126,IF(C507="P129",280,IF(C507="P130",695,IF(C507="P131",216,IF(C507="P132",540,IF(C507="P133",181,IF(C507="P134",353,IF(C507="P135",226,IF(C507="P136",604,IF(C507="P137",97,IF(C507="P138",465,IF(C507="P139",637,IF(C507="P140",307,0))))))))))))))))))) -> 712 | E507: =IF(C507="P127",800,IF(C507="P128",180,IF(C507="P129",220,0))) -> 800 | F507: 9 | G507: =Sales_Table!$E507*F507 -> 7200 | H507: COD | I507: =G507-(D507*F507) -> 792 | J507: =YEAR(Table16[[#This Row],[Date]]) -> 2024 | K507: =TEXT(Table16[[#This Row],[Date]],"MMMM") -> March
A508: 18/11/2020 | B508: O2507 | C508: P127 | D508: =IF(C508="P122",183,IF(C508="P123",371,IF(C508="P124",415,IF(C508="P125",508,IF(C508="P126",358,IF(C508="P127",712,IF(C508="P128",126,IF(C508="P129",280,IF(C508="P130",695,IF(C508="P131",216,IF(C508="P132",540,IF(C508="P133",181,IF(C508="P134",353,IF(C508="P135",226,IF(C508="P136",604,IF(C508="P137",97,IF(C508="P138",465,IF(C508="P139",637,IF(C508="P140",307,0))))))))))))))))))) -> 712 | E508: =IF(C508="P127",800,IF(C508="P128",180,IF(C508="P129",220,0))) -> 800 | F508: 6 | G508: =Sales_Table!$E508*F508 -> 4800 | H508: EMI | I508: =G508-(D508*F508) -> 528 | J508: =YEAR(Table16[[#This Row],[Date]]) -> 2020 | K508: =TEXT(Table16[[#This Row],[Date]],"MMMM") -> November
A509: 11/04/2020 | B509: O2508 | C509: P127 | D509: =IF(C509="P122",183,IF(C509="P123",371,IF(C509="P124",415,IF(C509="P125",508,IF(C509="P126",358,IF(C509="P127",712,IF(C509="P128",126,IF(C509="P129",280,IF(C509="P130",695,IF(C509="P131",216,IF(C509="P132",540,IF(C509="P133",181,IF(C509="P134",353,IF(C509="P135",226,IF(C509="P136",604,IF(C509="P137",97,IF(C509="P138",465,IF(C509="P139",637,IF(C509="P140",307,0))))))))))))))))))) -> 712 | E509: =IF(C509="P127",800,IF(C509="P128",180,IF(C509="P129",220,0))) -> 800 | F509: 2 | G509: =Sales_Table!$E509*F509 -> 1600 | H509: Debit | I509: =G509-(D509*F509) -> 176 | J509: =YEAR(Table16[[#This Row],[Date]]) -> 2020 | K509: =TEXT(Table16[[#This Row],[Date]],"MMMM") -> April
A510: 30/06/2021 | B510: O2509 | C510: P127 | D510: =IF(C510="P122",183,IF(C510="P123",371,IF(C510="P124",415,IF(C510="P125",508,IF(C510="P126",358,IF(C510="P127",712,IF(C510="P128",126,IF(C510="P129",280,IF(C510="P130",695,IF(C510="P131",216,IF(C510="P132",540,IF(C510="P133",181,IF(C510="P134",353,IF(C510="P135",226,IF(C510="P136",604,IF(C510="P137",97,IF(C510="P138",465,IF(C510="P139",637,IF(C510="P140",307,0))))))))))))))))))) -> 712 | E510: =IF(C510="P127",800,IF(C510="P128",180,IF(C510="P129",220,0))) -> 800 | F510: 7 | G510: =Sales_Table!$E510*F510 -> 5600 | H510: COD | I510: =G510-(D510*F510) -> 616 | J510: =YEAR(Table16[[#This Row],[Date]]) -> 2021 | K510: =TEXT(Table16[[#This Row],[Date]],"MMMM") -> June
A511: 06/06/2024 | B511: O2510 | C511: P127 | D511: =IF(C511="P122",183,IF(C511="P123",371,IF(C511="P124",415,IF(C511="P125",508,IF(C511="P126",358,IF(C511="P127",712,IF(C511="P128",126,IF(C511="P129",280,IF(C511="P130",695,IF(C511="P131",216,IF(C511="P132",540,IF(C511="P133",181,IF(C511="P134",353,IF(C511="P135",226,IF(C511="P136",604,IF(C511="P137",97,IF(C511="P138",465,IF(C511="P139",637,IF(C511="P140",307,0))))))))))))))))))) -> 712 | E511: =IF(C511="P127",800,IF(C511="P128",180,IF(C511="P129",220,0))) -> 800 | F511: 4 | G511: =Sales_Table!$E511*F511 -> 3200 | H511: Credit | I511: =G511-(D511*F511) -> 352 | J511: =YEAR(Table16[[#This Row],[Date]]) -> 2024 | K511: =TEXT(Table16[[#This Row],[Date]],"MMMM") -> June
A512: 01/02/2020 | B512: O2511 | C512: P127 | D512: =IF(C512="P122",183,IF(C512="P123",371,IF(C512="P124",415,IF(C512="P125",508,IF(C512="P126",358,IF(C512="P127",712,IF(C512="P128",126,IF(C512="P129",280,IF(C512="P130",695,IF(C512="P131",216,IF(C512="P132",540,IF(C512="P133",181,IF(C512="P134",353,IF(C512="P135",226,IF(C512="P136",604,IF(C512="P137",97,IF(C512="P138",465,IF(C512="P139",637,IF(C512="P140",307,0))))))))))))))))))) -> 712 | E512: =IF(C512="P127",800,IF(C512="P128",180,IF(C512="P129",220,0))) -> 800 | F512: 3 | G512: =Sales_Table!$E512*F512 -> 2400 | H512: COD | I512: =G512-(D512*F512) -> 264 | J512: =YEAR(Table16[[#This Row],[Date]]) -> 2020 | K512: =TEXT(Table16[[#This Row],[Date]],"MMMM") -> February
A513: 19/08/2021 | B513: O2512 | C513: P127 | D513: =IF(C513="P122",183,IF(C513="P123",371,IF(C513="P124",415,IF(C513="P125",508,IF(C513="P126",358,IF(C513="P127",712,IF(C513="P128",126,IF(C513="P129",280,IF(C513="P130",695,IF(C513="P131",216,IF(C513="P132",540,IF(C513="P133",181,IF(C513="P134",353,IF(C513="P135",226,IF(C513="P136",604,IF(C513="P137",97,IF(C513="P138",465,IF(C513="P139",637,IF(C513="P140",307,0))))))))))))))))))) -> 712 | E513: =IF(C513="P127",800,IF(C513="P128",180,IF(C513="P129",220,0))) -> 800 | F513: 3 | G513: =Sales_Table!$E513*F513 -> 2400 | H513: COD | I513: =G513-(D513*F513) -> 264 | J513: =YEAR(Table16[[#This Row],[Date]]) -> 2021 | K513: =TEXT(Table16[[#This Row],[Date]],"MMMM") -> August
A514: 28/03/2022 | B514: O2513 | C514: P127 | D514: =IF(C514="P122",183,IF(C514="P123",371,IF(C514="P124",415,IF(C514="P125",508,IF(C514="P126",358,IF(C514="P127",712,IF(C514="P128",126,IF(C514="P129",280,IF(C514="P130",695,IF(C514="P131",216,IF(C514="P132",540,IF(C514="P133",181,IF(C514="P134",353,IF(C514="P135",226,IF(C514="P136",604,IF(C514="P137",97,IF(C514="P138",465,IF(C514="P139",637,IF(C514="P140",307,0))))))))))))))))))) -> 712 | E514: =IF(C514="P127",800,IF(C514="P128",180,IF(C514="P129",220,0))) -> 800 | F514: 5 | G514: =Sales_Table!$E514*F514 -> 4000 | H514: COD | I514: =G514-(D514*F514) -> 440 | J514: =YEAR(Table16[[#This Row],[Date]]) -> 2022 | K514: =TEXT(Table16[[#This Row],[Date]],"MMMM") -> March
... A564: 09/03/2021 | B564: O2563 | C564: P129 | D564: =IF(C564="P122",183,IF(C564="P123",371,IF(C564="P124",415,IF(C564="P125",508,IF(C564="P126",358,IF(C564="P127",712,IF(C564="P128",126,IF(C564="P129",280,IF(C564="P130",695,IF(C564="P131",216,IF(C564="P132",540,IF(C564="P133",181,IF(C564="P134",353,IF(C564="P135",226,IF(C564="P136",604,IF(C564="P137",97,IF(C564="P138",465,IF(C564="P139",637,IF(C564="P140",307,0))))))))))))))))))) -> 280 | E564: =IF(C564="P127",800,IF(C564="P128",180,IF(C564="P129",220,0))) -> 220 | F564: 3 | G564: =Sales_Table!$E564*F564 -> 660 | H564: EMI | I564: =G564-(D564*F564) -> -180 | J564: =YEAR(Table16[[#This Row],[Date]]) -> 2021 | K564: =TEXT(Table16[[#This Row],[Date]],"MMMM") -> March
A565: 22/07/2023 | B565: O2564 | C565: P130 | D565: =IF(C565="P122",183,IF(C565="P123",371,IF(C565="P124",415,IF(C565="P125",508,IF(C565="P126",358,IF(C565="P127",712,IF(C565="P128",126,IF(C565="P129",280,IF(C565="P130",695,IF(C565="P131",216,IF(C565="P132",540,IF(C565="P133",181,IF(C565="P134",353,IF(C565="P135",226,IF(C565="P136",604,IF(C565="P137",97,IF(C565="P138",465,IF(C565="P139",637,IF(C565="P140",307,0))))))))))))))))))) -> 695 | E565: =IF(C565="P130",715,IF(C565="P131",225,IF(C565="P132",580,IF(C565="P133",205,IF(C565="P134",250,IF(C565="P135",312,IF(C565="P136",460,IF(C565="P137",140,IF(C565="P138",400,0))))))))) -> 715 | F565: 10 | G565: =Sales_Table!$E565*F565 -> 7150 | H565: Credit | I565: =G565-(D565*F565) -> 200 | J565: =YEAR(Table16[[#This Row],[Date]]) -> 2023 | K565: =TEXT(Table16[[#This Row],[Date]],"MMMM") -> July
A566: 11/06/2021 | B566: O2565 | C566: P130 | D566: =IF(C566="P122",183,IF(C566="P123",371,IF(C566="P124",415,IF(C566="P125",508,IF(C566="P126",358,IF(C566="P127",712,IF(C566="P128",126,IF(C566="P129",280,IF(C566="P130",695,IF(C566="P131",216,IF(C566="P132",540,IF(C566="P133",181,IF(C566="P134",353,IF(C566="P135",226,IF(C566="P136",604,IF(C566="P137",97,IF(C566="P138",465,IF(C566="P139",637,IF(C566="P140",307,0))))))))))))))))))) -> 695 | E566: =IF(C566="P130",715,IF(C566="P131",225,IF(C566="P132",580,IF(C566="P133",205,IF(C566="P134",250,IF(C566="P135",312,IF(C566="P136",460,IF(C566="P137",140,IF(C566="P138",400,0))))))))) -> 715 | F566: 4 | G566: =Sales_Table!$E566*F566 -> 2860 | H566: COD | I566: =G566-(D566*F566) -> 80 | J566: =YEAR(Table16[[#This Row],[Date]]) -> 2021 | K566: =TEXT(Table16[[#This Row],[Date]],"MMMM") -> June
A567: 30/04/2024 | B567: O2566 | C567: P130 | D567: =IF(C567="P122",183,IF(C567="P123",371,IF(C567="P124",415,IF(C567="P125",508,IF(C567="P126",358,IF(C567="P127",712,IF(C567="P128",126,IF(C567="P129",280,IF(C567="P130",695,IF(C567="P131",216,IF(C567="P132",540,IF(C567="P133",181,IF(C567="P134",353,IF(C567="P135",226,IF(C567="P136",604,IF(C567="P137",97,IF(C567="P138",465,IF(C567="P139",637,IF(C567="P140",307,0))))))))))))))))))) -> 695 | E567: =IF(C567="P130",715,IF(C567="P131",225,IF(C567="P132",580,IF(C567="P133",205,IF(C567="P134",250,IF(C567="P135",312,IF(C567="P136",460,IF(C567="P137",140,IF(C567="P138",400,0))))))))) -> 715 | F567: 9 | G567: =Sales_Table!$E567*F567 -> 6435 | H567: COD | I567: =G567-(D567*F567) -> 180 | J567: =YEAR(Table16[[#This Row],[Date]]) -> 2024 | K567: =TEXT(Table16[[#This Row],[Date]],"MMMM") -> April
A568: 20/08/2024 | B568: O2567 | C568: P130 | D568: =IF(C568="P122",183,IF(C568="P123",371,IF(C568="P124",415,IF(C568="P125",508,IF(C568="P126",358,IF(C568="P127",712,IF(C568="P128",126,IF(C568="P129",280,IF(C568="P130",695,IF(C568="P131",216,IF(C568="P132",540,IF(C568="P133",181,IF(C568="P134",353,IF(C568="P135",226,IF(C568="P136",604,IF(C568="P137",97,IF(C568="P138",465,IF(C568="P139",637,IF(C568="P140",307,0))))))))))))))))))) -> 695 | E568: =IF(C568="P130",715,IF(C568="P131",225,IF(C568="P132",580,IF(C568="P133",205,IF(C568="P134",250,IF(C568="P135",312,IF(C568="P136",460,IF(C568="P137",140,IF(C568="P138",400,0))))))))) -> 715 | F568: 2 | G568: =Sales_Table!$E568*F568 -> 1430 | H568: Credit | I568: =G568-(D568*F568) -> 40 | J568: =YEAR(Table16[[#This Row],[Date]]) -> 2024 | K568: =TEXT(Table16[[#This Row],[Date]],"MMMM") -> August
A569: 06/03/2023 | B569: O2568 | C569: P130 | D569: =IF(C569="P122",183,IF(C569="P123",371,IF(C569="P124",415,IF(C569="P125",508,IF(C569="P126",358,IF(C569="P127",712,IF(C569="P128",126,IF(C569="P129",280,IF(C569="P130",695,IF(C569="P131",216,IF(C569="P132",540,IF(C569="P133",181,IF(C569="P134",353,IF(C569="P135",226,IF(C569="P136",604,IF(C569="P137",97,IF(C569="P138",465,IF(C569="P139",637,IF(C569="P140",307,0))))))))))))))))))) -> 695 | E569: =IF(C569="P130",715,IF(C569="P131",225,IF(C569="P132",580,IF(C569="P133",205,IF(C569="P134",250,IF(C569="P135",312,IF(C569="P136",460,IF(C569="P137",140,IF(C569="P138",400,0))))))))) -> 715 | F569: 3 | G569: =Sales_Table!$E569*F569 -> 2145 | H569: EMI | I569: =G569-(D569*F569) -> 60 | J569: =YEAR(Table16[[#This Row],[Date]]) -> 2023 | K569: =TEXT(Table16[[#This Row],[Date]],"MMMM") -> March
A570: 27/05/2021 | B570: O2569 | C570: P130 | D570: =IF(C570="P122",183,IF(C570="P123",371,IF(C570="P124",415,IF(C570="P125",508,IF(C570="P126",358,IF(C570="P127",712,IF(C570="P128",126,IF(C570="P129",280,IF(C570="P130",695,IF(C570="P131",216,IF(C570="P132",540,IF(C570="P133",181,IF(C570="P134",353,IF(C570="P135",226,IF(C570="P136",604,IF(C570="P137",97,IF(C570="P138",465,IF(C570="P139",637,IF(C570="P140",307,0))))))))))))))))))) -> 695 | E570: =IF(C570="P130",715,IF(C570="P131",225,IF(C570="P132",580,IF(C570="P133",205,IF(C570="P134",250,IF(C570="P135",312,IF(C570="P136",460,IF(C570="P137",140,IF(C570="P138",400,0))))))))) -> 715 | F570: 7 | G570: =Sales_Table!$E570*F570 -> 5005 | H570: EMI | I570: =G570-(D570*F570) -> 140 | J570: =YEAR(Table16[[#This Row],[Date]]) -> 2021 | K570: =TEXT(Table16[[#This Row],[Date]],"MMMM") -> May
A571: 22/06/2023 | B571: O2570 | C571: P130 | D571: =IF(C571="P122",183,IF(C571="P123",371,IF(C571="P124",415,IF(C571="P125",508,IF(C571="P126",358,IF(C571="P127",712,IF(C571="P128",126,IF(C571="P129",280,IF(C571="P130",695,IF(C571="P131",216,IF(C571="P132",540,IF(C571="P133",181,IF(C571="P134",353,IF(C571="P135",226,IF(C571="P136",604,IF(C571="P137",97,IF(C571="P138",465,IF(C571="P139",637,IF(C571="P140",307,0))))))))))))))))))) -> 695 | E571: =IF(C571="P130",715,IF(C571="P131",225,IF(C571="P132",580,IF(C571="P133",205,IF(C571="P134",250,IF(C571="P135",312,IF(C571="P136",460,IF(C571="P137",140,IF(C571="P138",400,0))))))))) -> 715 | F571: 3 | G571: =Sales_Table!$E571*F571 -> 2145 | H571: Credit | I571: =G571-(D571*F571) -> 60 | J571: =YEAR(Table16[[#This Row],[Date]]) -> 2023 | K571: =TEXT(Table16[[#This Row],[Date]],"MMMM") -> June
A572: 21/10/2024 | B572: O2571 | C572: P130 | D572: =IF(C572="P122",183,IF(C572="P123",371,IF(C572="P124",415,IF(C572="P125",508,IF(C572="P126",358,IF(C572="P127",712,IF(C572="P128",126,IF(C572="P129",280,IF(C572="P130",695,IF(C572="P131",216,IF(C572="P132",540,IF(C572="P133",181,IF(C572="P134",353,IF(C572="P135",226,IF(C572="P136",604,IF(C572="P137",97,IF(C572="P138",465,IF(C572="P139",637,IF(C572="P140",307,0))))))))))))))))))) -> 695 | E572: =IF(C572="P130",715,IF(C572="P131",225,IF(C572="P132",580,IF(C572="P133",205,IF(C572="P134",250,IF(C572="P135",312,IF(C572="P136",460,IF(C572="P137",140,IF(C572="P138",400,0))))))))) -> 715 | F572: 4 | G572: =Sales_Table!$E572*F572 -> 2860 | H572: EMI | I572: =G572-(D572*F572) -> 80 | J572: =YEAR(Table16[[#This Row],[Date]]) -> 2024 | K572: =TEXT(Table16[[#This Row],[Date]],"MMMM") -> October
A573: 09/09/2020 | B573: O2572 | C573: P130 | D573: =IF(C573="P122",183,IF(C573="P123",371,IF(C573="P124",415,IF(C573="P125",508,IF(C573="P126",358,IF(C573="P127",712,IF(C573="P128",126,IF(C573="P129",280,IF(C573="P130",695,IF(C573="P131",216,IF(C573="P132",540,IF(C573="P133",181,IF(C573="P134",353,IF(C573="P135",226,IF(C573="P136",604,IF(C573="P137",97,IF(C573="P138",465,IF(C573="P139",637,IF(C573="P140",307,0))))))))))))))))))) -> 695 | E573: =IF(C573="P130",715,IF(C573="P131",225,IF(C573="P132",580,IF(C573="P133",205,IF(C573="P134",250,IF(C573="P135",312,IF(C573="P136",460,IF(C573="P137",140,IF(C573="P138",400,0))))))))) -> 715 | F573: 9 | G573: =Sales_Table!$E573*F573 -> 6435 | H573: EMI | I573: =G573-(D573*F573) -> 180 | J573: =YEAR(Table16[[#This Row],[Date]]) -> 2020 | K573: =TEXT(Table16[[#This Row],[Date]],"MMMM") -> September
A574: 31/03/2020 | B574: O2573 | C574: P130 | D574: =IF(C574="P122",183,IF(C574="P123",371,IF(C574="P124",415,IF(C574="P125",508,IF(C574="P126",358,IF(C574="P127",712,IF(C574="P128",126,IF(C574="P129",280,IF(C574="P130",695,IF(C574="P131",216,IF(C574="P132",540,IF(C574="P133",181,IF(C574="P134",353,IF(C574="P135",226,IF(C574="P136",604,IF(C574="P137",97,IF(C574="P138",465,IF(C574="P139",637,IF(C574="P140",307,0))))))))))))))))))) -> 695 | E574: =IF(C574="P130",715,IF(C574="P131",225,IF(C574="P132",580,IF(C574="P133",205,IF(C574="P134",250,IF(C574="P135",312,IF(C574="P136",460,IF(C574="P137",140,IF(C574="P138",400,0))))))))) -> 715 | F574: 6 | G574: =Sales_Table!$E574*F574 -> 4290 | H574: EMI | I574: =G574-(D574*F574) -> 120 | J574: =YEAR(Table16[[#This Row],[Date]]) -> 2020 | K574: =TEXT(Table16[[#This Row],[Date]],"MMMM") -> March
A575: 23/08/2021 | B575: O2574 | C575: P130 | D575: =IF(C575="P122",183,IF(C575="P123",371,IF(C575="P124",415,IF(C575="P125",508,IF(C575="P126",358,IF(C575="P127",712,IF(C575="P128",126,IF(C575="P129",280,IF(C575="P130",695,IF(C575="P131",216,IF(C575="P132",540,IF(C575="P133",181,IF(C575="P134",353,IF(C575="P135",226,IF(C575="P136",604,IF(C575="P137",97,IF(C575="P138",465,IF(C575="P139",637,IF(C575="P140",307,0))))))))))))))))))) -> 695 | E575: =IF(C575="P130",715,IF(C575="P131",225,IF(C575="P132",580,IF(C575="P133",205,IF(C575="P134",250,IF(C575="P135",312,IF(C575="P136",460,IF(C575="P137",140,IF(C575="P138",400,0))))))))) -> 715 | F575: 10 | G575: =Sales_Table!$E575*F575 -> 7150 | H575: Debit | I575: =G575-(D575*F575) -> 200 | J575: =YEAR(Table16[[#This Row],[Date]]) -> 2021 | K575: =TEXT(Table16[[#This Row],[Date]],"MMMM") -> August
A576: 30/08/2021 | B576: O2575 | C576: P130 | D576: =IF(C576="P122",183,IF(C576="P123",371,IF(C576="P124",415,IF(C576="P125",508,IF(C576="P126",358,IF(C576="P127",712,IF(C576="P128",126,IF(C576="P129",280,IF(C576="P130",695,IF(C576="P131",216,IF(C576="P132",540,IF(C576="P133",181,IF(C576="P134",353,IF(C576="P135",226,IF(C576="P136",604,IF(C576="P137",97,IF(C576="P138",465,IF(C576="P139",637,IF(C576="P140",307,0))))))))))))))))))) -> 695 | E576: =IF(C576="P130",715,IF(C576="P131",225,IF(C576="P132",580,IF(C576="P133",205,IF(C576="P134",250,IF(C576="P135",312,IF(C576="P136",460,IF(C576="P137",140,IF(C576="P138",400,0))))))))) -> 715 | F576: 5 | G576: =Sales_Table!$E576*F576 -> 3575 | H576: Debit | I576: =G576-(D576*F576) -> 100 | J576: =YEAR(Table16[[#This Row],[Date]]) -> 2021 | K576: =TEXT(Table16[[#This Row],[Date]],"MMMM") -> August
... A754: 16/05/2022 | B754: O2753 | C754: P138 | D754: =IF(C754="P122",183,IF(C754="P123",371,IF(C754="P124",415,IF(C754="P125",508,IF(C754="P126",358,IF(C754="P127",712,IF(C754="P128",126,IF(C754="P129",280,IF(C754="P130",695,IF(C754="P131",216,IF(C754="P132",540,IF(C754="P133",181,IF(C754="P134",353,IF(C754="P135",226,IF(C754="P136",604,IF(C754="P137",97,IF(C754="P138",465,IF(C754="P139",637,IF(C754="P140",307,0))))))))))))))))))) -> 465 | E754: =IF(C754="P130",715,IF(C754="P131",225,IF(C754="P132",580,IF(C754="P133",205,IF(C754="P134",250,IF(C754="P135",312,IF(C754="P136",460,IF(C754="P137",140,IF(C754="P138",400,0))))))))) -> 400 | F754: 2 | G754: =Sales_Table!$E754*F754 -> 800 | H754: Credit | I754: =G754-(D754*F754) -> -130 | J754: =YEAR(Table16[[#This Row],[Date]]) -> 2022 | K754: =TEXT(Table16[[#This Row],[Date]],"MMMM") -> May
A755: 04/03/2025 | B755: O2754 | C755: P139 | D755: =IF(C755="P122",183,IF(C755="P123",371,IF(C755="P124",415,IF(C755="P125",508,IF(C755="P126",358,IF(C755="P127",712,IF(C755="P128",126,IF(C755="P129",280,IF(C755="P130",695,IF(C755="P131",216,IF(C755="P132",540,IF(C755="P133",181,IF(C755="P134",353,IF(C755="P135",226,IF(C755="P136",604,IF(C755="P137",97,IF(C755="P138",465,IF(C755="P139",637,IF(C755="P140",307,0))))))))))))))))))) -> 637 | E755: =IF(C755="P139",575,IF(C755="P140",402,IF(C755="P141",400,IF(C755="P142",252,IF(C755="P143",800,IF(C755="P144",380,IF(C755="P145",800,IF(C755="P146",822,IF(C755="P147",175,0))))))))) -> 575 | F755: 6 | G755: =Sales_Table!$E755*F755 -> 3450 | H755: Credit | I755: =G755-(D755*F755) -> -372 | J755: =YEAR(Table16[[#This Row],[Date]]) -> 2025 | K755: =TEXT(Table16[[#This Row],[Date]],"MMMM") -> March
A756: 27/01/2022 | B756: O2755 | C756: P139 | D756: =IF(C756="P122",183,IF(C756="P123",371,IF(C756="P124",415,IF(C756="P125",508,IF(C756="P126",358,IF(C756="P127",712,IF(C756="P128",126,IF(C756="P129",280,IF(C756="P130",695,IF(C756="P131",216,IF(C756="P132",540,IF(C756="P133",181,IF(C756="P134",353,IF(C756="P135",226,IF(C756="P136",604,IF(C756="P137",97,IF(C756="P138",465,IF(C756="P139",637,IF(C756="P140",307,0))))))))))))))))))) -> 637 | E756: =IF(C756="P139",575,IF(C756="P140",402,IF(C756="P141",400,IF(C756="P142",252,IF(C756="P143",800,IF(C756="P144",380,IF(C756="P145",800,IF(C756="P146",822,IF(C756="P147",175,0))))))))) -> 575 | F756: 3 | G756: =Sales_Table!$E756*F756 -> 1725 | H756: COD | I756: =G756-(D756*F756) -> -186 | J756: =YEAR(Table16[[#This Row],[Date]]) -> 2022 | K756: =TEXT(Table16[[#This Row],[Date]],"MMMM") -> January
A757: 22/10/2021 | B757: O2756 | C757: P139 | D757: =IF(C757="P122",183,IF(C757="P123",371,IF(C757="P124",415,IF(C757="P125",508,IF(C757="P126",358,IF(C757="P127",712,IF(C757="P128",126,IF(C757="P129",280,IF(C757="P130",695,IF(C757="P131",216,IF(C757="P132",540,IF(C757="P133",181,IF(C757="P134",353,IF(C757="P135",226,IF(C757="P136",604,IF(C757="P137",97,IF(C757="P138",465,IF(C757="P139",637,IF(C757="P140",307,0))))))))))))))))))) -> 637 | E757: =IF(C757="P139",575,IF(C757="P140",402,IF(C757="P141",400,IF(C757="P142",252,IF(C757="P143",800,IF(C757="P144",380,IF(C757="P145",800,IF(C757="P146",822,IF(C757="P147",175,0))))))))) -> 575 | F757: 7 | G757: =Sales_Table!$E757*F757 -> 4025 | H757: EMI | I757: =G757-(D757*F757) -> -434 | J757: =YEAR(Table16[[#This Row],[Date]]) -> 2021 | K757: =TEXT(Table16[[#This Row],[Date]],"MMMM") -> October
A758: 13/02/2023 | B758: O2757 | C758: P139 | D758: =IF(C758="P122",183,IF(C758="P123",371,IF(C758="P124",415,IF(C758="P125",508,IF(C758="P126",358,IF(C758="P127",712,IF(C758="P128",126,IF(C758="P129",280,IF(C758="P130",695,IF(C758="P131",216,IF(C758="P132",540,IF(C758="P133",181,IF(C758="P134",353,IF(C758="P135",226,IF(C758="P136",604,IF(C758="P137",97,IF(C758="P138",465,IF(C758="P139",637,IF(C758="P140",307,0))))))))))))))))))) -> 637 | E758: =IF(C758="P139",575,IF(C758="P140",402,IF(C758="P141",400,IF(C758="P142",252,IF(C758="P143",800,IF(C758="P144",380,IF(C758="P145",800,IF(C758="P146",822,IF(C758="P147",175,0))))))))) -> 575 | F758: 6 | G758: =Sales_Table!$E758*F758 -> 3450 | H758: EMI | I758: =G758-(D758*F758) -> -372 | J758: =YEAR(Table16[[#This Row],[Date]]) -> 2023 | K758: =TEXT(Table16[[#This Row],[Date]],"MMMM") -> February
A759: 15/11/2021 | B759: O2758 | C759: P139 | D759: =IF(C759="P122",183,IF(C759="P123",371,IF(C759="P124",415,IF(C759="P125",508,IF(C759="P126",358,IF(C759="P127",712,IF(C759="P128",126,IF(C759="P129",280,IF(C759="P130",695,IF(C759="P131",216,IF(C759="P132",540,IF(C759="P133",181,IF(C759="P134",353,IF(C759="P135",226,IF(C759="P136",604,IF(C759="P137",97,IF(C759="P138",465,IF(C759="P139",637,IF(C759="P140",307,0))))))))))))))))))) -> 637 | E759: =IF(C759="P139",575,IF(C759="P140",402,IF(C759="P141",400,IF(C759="P142",252,IF(C759="P143",800,IF(C759="P144",380,IF(C759="P145",800,IF(C759="P146",822,IF(C759="P147",175,0))))))))) -> 575 | F759: 4 | G759: =Sales_Table!$E759*F759 -> 2300 | H759: EMI | I759: =G759-(D759*F759) -> -248 | J759: =YEAR(Table16[[#This Row],[Date]]) -> 2021 | K759: =TEXT(Table16[[#This Row],[Date]],"MMMM") -> November
A760: 28/02/2025 | B760: O2759 | C760: P139 | D760: =IF(C760="P122",183,IF(C760="P123",371,IF(C760="P124",415,IF(C760="P125",508,IF(C760="P126",358,IF(C760="P127",712,IF(C760="P128",126,IF(C760="P129",280,IF(C760="P130",695,IF(C760="P131",216,IF(C760="P132",540,IF(C760="P133",181,IF(C760="P134",353,IF(C760="P135",226,IF(C760="P136",604,IF(C760="P137",97,IF(C760="P138",465,IF(C760="P139",637,IF(C760="P140",307,0))))))))))))))))))) -> 637 | E760: =IF(C760="P139",575,IF(C760="P140",402,IF(C760="P141",400,IF(C760="P142",252,IF(C760="P143",800,IF(C760="P144",380,IF(C760="P145",800,IF(C760="P146",822,IF(C760="P147",175,0))))))))) -> 575 | F760: 1 | G760: =Sales_Table!$E760*F760 -> 575 | H760: COD | I760: =G760-(D760*F760) -> -62 | J760: =YEAR(Table16[[#This Row],[Date]]) -> 2025 | K760: =TEXT(Table16[[#This Row],[Date]],"MMMM") -> February
A761: 20/11/2023 | B761: O2760 | C761: P139 | D761: =IF(C761="P122",183,IF(C761="P123",371,IF(C761="P124",415,IF(C761="P125",508,IF(C761="P126",358,IF(C761="P127",712,IF(C761="P128",126,IF(C761="P129",280,IF(C761="P130",695,IF(C761="P131",216,IF(C761="P132",540,IF(C761="P133",181,IF(C761="P134",353,IF(C761="P135",226,IF(C761="P136",604,IF(C761="P137",97,IF(C761="P138",465,IF(C761="P139",637,IF(C761="P140",307,0))))))))))))))))))) -> 637 | E761: =IF(C761="P139",575,IF(C761="P140",402,IF(C761="P141",400,IF(C761="P142",252,IF(C761="P143",800,IF(C761="P144",380,IF(C761="P145",800,IF(C761="P146",822,IF(C761="P147",175,0))))))))) -> 575 | F761: 4 | G761: =Sales_Table!$E761*F761 -> 2300 | H761: Debit | I761: =G761-(D761*F761) -> -248 | J761: =YEAR(Table16[[#This Row],[Date]]) -> 2023 | K761: =TEXT(Table16[[#This Row],[Date]],"MMMM") -> November
A762: 03/12/2023 | B762: O2761 | C762: P139 | D762: =IF(C762="P122",183,IF(C762="P123",371,IF(C762="P124",415,IF(C762="P125",508,IF(C762="P126",358,IF(C762="P127",712,IF(C762="P128",126,IF(C762="P129",280,IF(C762="P130",695,IF(C762="P131",216,IF(C762="P132",540,IF(C762="P133",181,IF(C762="P134",353,IF(C762="P135",226,IF(C762="P136",604,IF(C762="P137",97,IF(C762="P138",465,IF(C762="P139",637,IF(C762="P140",307,0))))))))))))))))))) -> 637 | E762: =IF(C762="P139",575,IF(C762="P140",402,IF(C762="P141",400,IF(C762="P142",252,IF(C762="P143",800,IF(C762="P144",380,IF(C762="P145",800,IF(C762="P146",822,IF(C762="P147",175,0))))))))) -> 575 | F762: 1 | G762: =Sales_Table!$E762*F762 -> 575 | H762: Debit | I762: =G762-(D762*F762) -> -62 | J762: =YEAR(Table16[[#This Row],[Date]]) -> 2023 | K762: =TEXT(Table16[[#This Row],[Date]],"MMMM") -> December
A763: 26/05/2020 | B763: O2762 | C763: P139 | D763: =IF(C763="P122",183,IF(C763="P123",371,IF(C763="P124",415,IF(C763="P125",508,IF(C763="P126",358,IF(C763="P127",712,IF(C763="P128",126,IF(C763="P129",280,IF(C763="P130",695,IF(C763="P131",216,IF(C763="P132",540,IF(C763="P133",181,IF(C763="P134",353,IF(C763="P135",226,IF(C763="P136",604,IF(C763="P137",97,IF(C763="P138",465,IF(C763="P139",637,IF(C763="P140",307,0))))))))))))))))))) -> 637 | E763: =IF(C763="P139",575,IF(C763="P140",402,IF(C763="P141",400,IF(C763="P142",252,IF(C763="P143",800,IF(C763="P144",380,IF(C763="P145",800,IF(C763="P146",822,IF(C763="P147",175,0))))))))) -> 575 | F763: 8 | G763: =Sales_Table!$E763*F763 -> 4600 | H763: EMI | I763: =G763-(D763*F763) -> -496 | J763: =YEAR(Table16[[#This Row],[Date]]) -> 2020 | K763: =TEXT(Table16[[#This Row],[Date]],"MMMM") -> May
A764: 16/07/2022 | B764: O2763 | C764: P139 | D764: =IF(C764="P122",183,IF(C764="P123",371,IF(C764="P124",415,IF(C764="P125",508,IF(C764="P126",358,IF(C764="P127",712,IF(C764="P128",126,IF(C764="P129",280,IF(C764="P130",695,IF(C764="P131",216,IF(C764="P132",540,IF(C764="P133",181,IF(C764="P134",353,IF(C764="P135",226,IF(C764="P136",604,IF(C764="P137",97,IF(C764="P138",465,IF(C764="P139",637,IF(C764="P140",307,0))))))))))))))))))) -> 637 | E764: =IF(C764="P139",575,IF(C764="P140",402,IF(C764="P141",400,IF(C764="P142",252,IF(C764="P143",800,IF(C764="P144",380,IF(C764="P145",800,IF(C764="P146",822,IF(C764="P147",175,0))))))))) -> 575 | F764: 1 | G764: =Sales_Table!$E764*F764 -> 575 | H764: EMI | I764: =G764-(D764*F764) -> -62 | J764: =YEAR(Table16[[#This Row],[Date]]) -> 2022 | K764: =TEXT(Table16[[#This Row],[Date]],"MMMM") -> July
A765: 02/04/2021 | B765: O2764 | C765: P139 | D765: =IF(C765="P122",183,IF(C765="P123",371,IF(C765="P124",415,IF(C765="P125",508,IF(C765="P126",358,IF(C765="P127",712,IF(C765="P128",126,IF(C765="P129",280,IF(C765="P130",695,IF(C765="P131",216,IF(C765="P132",540,IF(C765="P133",181,IF(C765="P134",353,IF(C765="P135",226,IF(C765="P136",604,IF(C765="P137",97,IF(C765="P138",465,IF(C765="P139",637,IF(C765="P140",307,0))))))))))))))))))) -> 637 | E765: =IF(C765="P139",575,IF(C765="P140",402,IF(C765="P141",400,IF(C765="P142",252,IF(C765="P143",800,IF(C765="P144",380,IF(C765="P145",800,IF(C765="P146",822,IF(C765="P147",175,0))))))))) -> 575 | F765: 3 | G765: =Sales_Table!$E765*F765 -> 1725 | H765: EMI | I765: =G765-(D765*F765) -> -186 | J765: =YEAR(Table16[[#This Row],[Date]]) -> 2021 | K765: =TEXT(Table16[[#This Row],[Date]],"MMMM") -> April
A766: 02/09/2020 | B766: O2765 | C766: P139 | D766: =IF(C766="P122",183,IF(C766="P123",371,IF(C766="P124",415,IF(C766="P125",508,IF(C766="P126",358,IF(C766="P127",712,IF(C766="P128",126,IF(C766="P129",280,IF(C766="P130",695,IF(C766="P131",216,IF(C766="P132",540,IF(C766="P133",181,IF(C766="P134",353,IF(C766="P135",226,IF(C766="P136",604,IF(C766="P137",97,IF(C766="P138",465,IF(C766="P139",637,IF(C766="P140",307,0))))))))))))))))))) -> 637 | E766: =IF(C766="P139",575,IF(C766="P140",402,IF(C766="P141",400,IF(C766="P142",252,IF(C766="P143",800,IF(C766="P144",380,IF(C766="P145",800,IF(C766="P146",822,IF(C766="P147",175,0))))))))) -> 575 | F766: 2 | G766: =Sales_Table!$E766*F766 -> 1150 | H766: EMI | I766: =G766-(D766*F766) -> -124 | J766: =YEAR(Table16[[#This Row],[Date]]) -> 2020 | K766: =TEXT(Table16[[#This Row],[Date]],"MMMM") -> September
... A787: 25/10/2021 | B787: O2786 | C787: P140 | D787: =IF(C787="P122",183,IF(C787="P123",371,IF(C787="P124",415,IF(C787="P125",508,IF(C787="P126",358,IF(C787="P127",712,IF(C787="P128",126,IF(C787="P129",280,IF(C787="P130",695,IF(C787="P131",216,IF(C787="P132",540,IF(C787="P133",181,IF(C787="P134",353,IF(C787="P135",226,IF(C787="P136",604,IF(C787="P137",97,IF(C787="P138",465,IF(C787="P139",637,IF(C787="P140",307,0))))))))))))))))))) -> 307 | E787: =IF(C787="P139",575,IF(C787="P140",402,IF(C787="P141",400,IF(C787="P142",252,IF(C787="P143",800,IF(C787="P144",380,IF(C787="P145",800,IF(C787="P146",822,IF(C787="P147",175,0))))))))) -> 402 | F787: 6 | G787: =Sales_Table!$E787*F787 -> 2412 | H787: Debit | I787: =G787-(D787*F787) -> 570 | J787: =YEAR(Table16[[#This Row],[Date]]) -> 2021 | K787: =TEXT(Table16[[#This Row],[Date]],"MMMM") -> October
A788: 25/05/2021 | B788: O2787 | C788: P141 | D788: =IF(C788="P141",435,IF(C788="P142",223,IF(C788="P143",648,IF(C788="P144",633,IF(C788="P145",176,IF(C788="P146",495,IF(C788="P147",123,IF(C788="P148",457,IF(C788="P149",668,IF(C788="P150",265,0)))))))))) -> 435 | E788: =IF(C788="P139",575,IF(C788="P140",402,IF(C788="P141",400,IF(C788="P142",252,IF(C788="P143",800,IF(C788="P144",380,IF(C788="P145",800,IF(C788="P146",822,IF(C788="P147",175,0))))))))) -> 400 | F788: 8 | G788: =Sales_Table!$E788*F788 -> 3200 | H788: Debit | I788: =G788-(D788*F788) -> -280 | J788: =YEAR(Table16[[#This Row],[Date]]) -> 2021 | K788: =TEXT(Table16[[#This Row],[Date]],"MMMM") -> May
A789: 03/05/2022 | B789: O2788 | C789: P141 | D789: =IF(C789="P141",435,IF(C789="P142",223,IF(C789="P143",648,IF(C789="P144",633,IF(C789="P145",176,IF(C789="P146",495,IF(C789="P147",123,IF(C789="P148",457,IF(C789="P149",668,IF(C789="P150",265,0)))))))))) -> 435 | E789: =IF(C789="P139",575,IF(C789="P140",402,IF(C789="P141",400,IF(C789="P142",252,IF(C789="P143",800,IF(C789="P144",380,IF(C789="P145",800,IF(C789="P146",822,IF(C789="P147",175,0))))))))) -> 400 | F789: 1 | G789: =Sales_Table!$E789*F789 -> 400 | H789: Credit | I789: =G789-(D789*F789) -> -35 | J789: =YEAR(Table16[[#This Row],[Date]]) -> 2022 | K789: =TEXT(Table16[[#This Row],[Date]],"MMMM") -> May
A790: 11/05/2024 | B790: O2789 | C790: P141 | D790: =IF(C790="P141",435,IF(C790="P142",223,IF(C790="P143",648,IF(C790="P144",633,IF(C790="P145",176,IF(C790="P146",495,IF(C790="P147",123,IF(C790="P148",457,IF(C790="P149",668,IF(C790="P150",265,0)))))))))) -> 435 | E790: =IF(C790="P139",575,IF(C790="P140",402,IF(C790="P141",400,IF(C790="P142",252,IF(C790="P143",800,IF(C790="P144",380,IF(C790="P145",800,IF(C790="P146",822,IF(C790="P147",175,0))))))))) -> 400 | F790: 2 | G790: =Sales_Table!$E790*F790 -> 800 | H790: EMI | I790: =G790-(D790*F790) -> -70 | J790: =YEAR(Table16[[#This Row],[Date]]) -> 2024 | K790: =TEXT(Table16[[#This Row],[Date]],"MMMM") -> May
A791: 03/04/2024 | B791: O2790 | C791: P141 | D791: =IF(C791="P141",435,IF(C791="P142",223,IF(C791="P143",648,IF(C791="P144",633,IF(C791="P145",176,IF(C791="P146",495,IF(C791="P147",123,IF(C791="P148",457,IF(C791="P149",668,IF(C791="P150",265,0)))))))))) -> 435 | E791: =IF(C791="P139",575,IF(C791="P140",402,IF(C791="P141",400,IF(C791="P142",252,IF(C791="P143",800,IF(C791="P144",380,IF(C791="P145",800,IF(C791="P146",822,IF(C791="P147",175,0))))))))) -> 400 | F791: 6 | G791: =Sales_Table!$E791*F791 -> 2400 | H791: Debit | I791: =G791-(D791*F791) -> -210 | J791: =YEAR(Table16[[#This Row],[Date]]) -> 2024 | K791: =TEXT(Table16[[#This Row],[Date]],"MMMM") -> April
A792: 12/11/2023 | B792: O2791 | C792: P141 | D792: =IF(C792="P141",435,IF(C792="P142",223,IF(C792="P143",648,IF(C792="P144",633,IF(C792="P145",176,IF(C792="P146",495,IF(C792="P147",123,IF(C792="P148",457,IF(C792="P149",668,IF(C792="P150",265,0)))))))))) -> 435 | E792: =IF(C792="P139",575,IF(C792="P140",402,IF(C792="P141",400,IF(C792="P142",252,IF(C792="P143",800,IF(C792="P144",380,IF(C792="P145",800,IF(C792="P146",822,IF(C792="P147",175,0))))))))) -> 400 | F792: 1 | G792: =Sales_Table!$E792*F792 -> 400 | H792: EMI | I792: =G792-(D792*F792) -> -35 | J792: =YEAR(Table16[[#This Row],[Date]]) -> 2023 | K792: =TEXT(Table16[[#This Row],[Date]],"MMMM") -> November
A793: 14/03/2023 | B793: O2792 | C793: P141 | D793: =IF(C793="P141",435,IF(C793="P142",223,IF(C793="P143",648,IF(C793="P144",633,IF(C793="P145",176,IF(C793="P146",495,IF(C793="P147",123,IF(C793="P148",457,IF(C793="P149",668,IF(C793="P150",265,0)))))))))) -> 435 | E793: =IF(C793="P139",575,IF(C793="P140",402,IF(C793="P141",400,IF(C793="P142",252,IF(C793="P143",800,IF(C793="P144",380,IF(C793="P145",800,IF(C793="P146",822,IF(C793="P147",175,0))))))))) -> 400 | F793: 1 | G793: =Sales_Table!$E793*F793 -> 400 | H793: Credit | I793: =G793-(D793*F793) -> -35 | J793: =YEAR(Table16[[#This Row],[Date]]) -> 2023 | K793: =TEXT(Table16[[#This Row],[Date]],"MMMM") -> March
A794: 10/12/2023 | B794: O2793 | C794: P141 | D794: =IF(C794="P141",435,IF(C794="P142",223,IF(C794="P143",648,IF(C794="P144",633,IF(C794="P145",176,IF(C794="P146",495,IF(C794="P147",123,IF(C794="P148",457,IF(C794="P149",668,IF(C794="P150",265,0)))))))))) -> 435 | E794: =IF(C794="P139",575,IF(C794="P140",402,IF(C794="P141",400,IF(C794="P142",252,IF(C794="P143",800,IF(C794="P144",380,IF(C794="P145",800,IF(C794="P146",822,IF(C794="P147",175,0))))))))) -> 400 | F794: 2 | G794: =Sales_Table!$E794*F794 -> 800 | H794: Credit | I794: =G794-(D794*F794) -> -70 | J794: =YEAR(Table16[[#This Row],[Date]]) -> 2023 | K794: =TEXT(Table16[[#This Row],[Date]],"MMMM") -> December
A795: 09/01/2021 | B795: O2794 | C795: P141 | D795: =IF(C795="P141",435,IF(C795="P142",223,IF(C795="P143",648,IF(C795="P144",633,IF(C795="P145",176,IF(C795="P146",495,IF(C795="P147",123,IF(C795="P148",457,IF(C795="P149",668,IF(C795="P150",265,0)))))))))) -> 435 | E795: =IF(C795="P139",575,IF(C795="P140",402,IF(C795="P141",400,IF(C795="P142",252,IF(C795="P143",800,IF(C795="P144",380,IF(C795="P145",800,IF(C795="P146",822,IF(C795="P147",175,0))))))))) -> 400 | F795: 4 | G795: =Sales_Table!$E795*F795 -> 1600 | H795: Debit | I795: =G795-(D795*F795) -> -140 | J795: =YEAR(Table16[[#This Row],[Date]]) -> 2021 | K795: =TEXT(Table16[[#This Row],[Date]],"MMMM") -> January
A796: 24/05/2022 | B796: O2795 | C796: P141 | D796: =IF(C796="P141",435,IF(C796="P142",223,IF(C796="P143",648,IF(C796="P144",633,IF(C796="P145",176,IF(C796="P146",495,IF(C796="P147",123,IF(C796="P148",457,IF(C796="P149",668,IF(C796="P150",265,0)))))))))) -> 435 | E796: =IF(C796="P139",575,IF(C796="P140",402,IF(C796="P141",400,IF(C796="P142",252,IF(C796="P143",800,IF(C796="P144",380,IF(C796="P145",800,IF(C796="P146",822,IF(C796="P147",175,0))))))))) -> 400 | F796: 8 | G796: =Sales_Table!$E796*F796 -> 3200 | H796: EMI | I796: =G796-(D796*F796) -> -280 | J796: =YEAR(Table16[[#This Row],[Date]]) -> 2022 | K796: =TEXT(Table16[[#This Row],[Date]],"MMMM") -> May
A797: 03/05/2021 | B797: O2796 | C797: P141 | D797: =IF(C797="P141",435,IF(C797="P142",223,IF(C797="P143",648,IF(C797="P144",633,IF(C797="P145",176,IF(C797="P146",495,IF(C797="P147",123,IF(C797="P148",457,IF(C797="P149",668,IF(C797="P150",265,0)))))))))) -> 435 | E797: =IF(C797="P139",575,IF(C797="P140",402,IF(C797="P141",400,IF(C797="P142",252,IF(C797="P143",800,IF(C797="P144",380,IF(C797="P145",800,IF(C797="P146",822,IF(C797="P147",175,0))))))))) -> 400 | F797: 2 | G797: =Sales_Table!$E797*F797 -> 800 | H797: COD | I797: =G797-(D797*F797) -> -70 | J797: =YEAR(Table16[[#This Row],[Date]]) -> 2021 | K797: =TEXT(Table16[[#This Row],[Date]],"MMMM") -> May
A798: 29/01/2025 | B798: O2797 | C798: P141 | D798: =IF(C798="P141",435,IF(C798="P142",223,IF(C798="P143",648,IF(C798="P144",633,IF(C798="P145",176,IF(C798="P146",495,IF(C798="P147",123,IF(C798="P148",457,IF(C798="P149",668,IF(C798="P150",265,0)))))))))) -> 435 | E798: =IF(C798="P139",575,IF(C798="P140",402,IF(C798="P141",400,IF(C798="P142",252,IF(C798="P143",800,IF(C798="P144",380,IF(C798="P145",800,IF(C798="P146",822,IF(C798="P147",175,0))))))))) -> 400 | F798: 6 | G798: =Sales_Table!$E798*F798 -> 2400 | H798: EMI | I798: =G798-(D798*F798) -> -210 | J798: =YEAR(Table16[[#This Row],[Date]]) -> 2025 | K798: =TEXT(Table16[[#This Row],[Date]],"MMMM") -> January
A799: 26/09/2024 | B799: O2798 | C799: P141 | D799: =IF(C799="P141",435,IF(C799="P142",223,IF(C799="P143",648,IF(C799="P144",633,IF(C799="P145",176,IF(C799="P146",495,IF(C799="P147",123,IF(C799="P148",457,IF(C799="P149",668,IF(C799="P150",265,0)))))))))) -> 435 | E799: =IF(C799="P139",575,IF(C799="P140",402,IF(C799="P141",400,IF(C799="P142",252,IF(C799="P143",800,IF(C799="P144",380,IF(C799="P145",800,IF(C799="P146",822,IF(C799="P147",175,0))))))))) -> 400 | F799: 10 | G799: =Sales_Table!$E799*F799 -> 4000 | H799: EMI | I799: =G799-(D799*F799) -> -350 | J799: =YEAR(Table16[[#This Row],[Date]]) -> 2024 | K799: =TEXT(Table16[[#This Row],[Date]],"MMMM") -> September
... A925: 28/09/2022 | B925: O2924 | C925: P147 | D925: =IF(C925="P141",435,IF(C925="P142",223,IF(C925="P143",648,IF(C925="P144",633,IF(C925="P145",176,IF(C925="P146",495,IF(C925="P147",123,IF(C925="P148",457,IF(C925="P149",668,IF(C925="P150",265,0)))))))))) -> 123 | E925: =IF(C925="P139",575,IF(C925="P140",402,IF(C925="P141",400,IF(C925="P142",252,IF(C925="P143",800,IF(C925="P144",380,IF(C925="P145",800,IF(C925="P146",822,IF(C925="P147",175,0))))))))) -> 175 | F925: 2 | G925: =Sales_Table!$E925*F925 -> 350 | H925: Debit | I925: =G925-(D925*F925) -> 104 | J925: =YEAR(Table16[[#This Row],[Date]]) -> 2022 | K925: =TEXT(Table16[[#This Row],[Date]],"MMMM") -> September
A926: 26/05/2025 | B926: O2925 | C926: P148 | D926: =IF(C926="P141",435,IF(C926="P142",223,IF(C926="P143",648,IF(C926="P144",633,IF(C926="P145",176,IF(C926="P146",495,IF(C926="P147",123,IF(C926="P148",457,IF(C926="P149",668,IF(C926="P150",265,0)))))))))) -> 457 | E926: 700 | F926: 9 | G926: =Sales_Table!$E926*F926 -> 6300 | H926: COD | I926: =G926-(D926*F926) -> 2187 | J926: =YEAR(Table16[[#This Row],[Date]]) -> 2025 | K926: =TEXT(Table16[[#This Row],[Date]],"MMMM") -> May
A927: 25/02/2023 | B927: O2926 | C927: P148 | D927: =IF(C927="P141",435,IF(C927="P142",223,IF(C927="P143",648,IF(C927="P144",633,IF(C927="P145",176,IF(C927="P146",495,IF(C927="P147",123,IF(C927="P148",457,IF(C927="P149",668,IF(C927="P150",265,0)))))))))) -> 457 | E927: 700 | F927: 5 | G927: =Sales_Table!$E927*F927 -> 3500 | H927: Credit | I927: =G927-(D927*F927) -> 1215 | J927: =YEAR(Table16[[#This Row],[Date]]) -> 2023 | K927: =TEXT(Table16[[#This Row],[Date]],"MMMM") -> February
A928: 20/10/2023 | B928: O2927 | C928: P148 | D928: =IF(C928="P141",435,IF(C928="P142",223,IF(C928="P143",648,IF(C928="P144",633,IF(C928="P145",176,IF(C928="P146",495,IF(C928="P147",123,IF(C928="P148",457,IF(C928="P149",668,IF(C928="P150",265,0)))))))))) -> 457 | E928: 700 | F928: 5 | G928: =Sales_Table!$E928*F928 -> 3500 | H928: COD | I928: =G928-(D928*F928) -> 1215 | J928: =YEAR(Table16[[#This Row],[Date]]) -> 2023 | K928: =TEXT(Table16[[#This Row],[Date]],"MMMM") -> October
A929: 28/02/2021 | B929: O2928 | C929: P148 | D929: =IF(C929="P141",435,IF(C929="P142",223,IF(C929="P143",648,IF(C929="P144",633,IF(C929="P145",176,IF(C929="P146",495,IF(C929="P147",123,IF(C929="P148",457,IF(C929="P149",668,IF(C929="P150",265,0)))))))))) -> 457 | E929: 700 | F929: 10 | G929: =Sales_Table!$E929*F929 -> 7000 | H929: Credit | I929: =G929-(D929*F929) -> 2430 | J929: =YEAR(Table16[[#This Row],[Date]]) -> 2021 | K929: =TEXT(Table16[[#This Row],[Date]],"MMMM") -> February
A930: 19/04/2022 | B930: O2929 | C930: P148 | D930: =IF(C930="P141",435,IF(C930="P142",223,IF(C930="P143",648,IF(C930="P144",633,IF(C930="P145",176,IF(C930="P146",495,IF(C930="P147",123,IF(C930="P148",457,IF(C930="P149",668,IF(C930="P150",265,0)))))))))) -> 457 | E930: 700 | F930: 8 | G930: =Sales_Table!$E930*F930 -> 5600 | H930: COD | I930: =G930-(D930*F930) -> 1944 | J930: =YEAR(Table16[[#This Row],[Date]]) -> 2022 | K930: =TEXT(Table16[[#This Row],[Date]],"MMMM") -> April
A931: 12/01/2024 | B931: O2930 | C931: P148 | D931: =IF(C931="P141",435,IF(C931="P142",223,IF(C931="P143",648,IF(C931="P144",633,IF(C931="P145",176,IF(C931="P146",495,IF(C931="P147",123,IF(C931="P148",457,IF(C931="P149",668,IF(C931="P150",265,0)))))))))) -> 457 | E931: 700 | F931: 1 | G931: =Sales_Table!$E931*F931 -> 700 | H931: EMI | I931: =G931-(D931*F931) -> 243 | J931: =YEAR(Table16[[#This Row],[Date]]) -> 2024 | K931: =TEXT(Table16[[#This Row],[Date]],"MMMM") -> January
A932: 18/03/2020 | B932: O2931 | C932: P148 | D932: =IF(C932="P141",435,IF(C932="P142",223,IF(C932="P143",648,IF(C932="P144",633,IF(C932="P145",176,IF(C932="P146",495,IF(C932="P147",123,IF(C932="P148",457,IF(C932="P149",668,IF(C932="P150",265,0)))))))))) -> 457 | E932: 700 | F932: 4 | G932: =Sales_Table!$E932*F932 -> 2800 | H932: Credit | I932: =G932-(D932*F932) -> 972 | J932: =YEAR(Table16[[#This Row],[Date]]) -> 2020 | K932: =TEXT(Table16[[#This Row],[Date]],"MMMM") -> March
A933: 19/04/2024 | B933: O2932 | C933: P148 | D933: =IF(C933="P141",435,IF(C933="P142",223,IF(C933="P143",648,IF(C933="P144",633,IF(C933="P145",176,IF(C933="P146",495,IF(C933="P147",123,IF(C933="P148",457,IF(C933="P149",668,IF(C933="P150",265,0)))))))))) -> 457 | E933: 700 | F933: 8 | G933: =Sales_Table!$E933*F933 -> 5600 | H933: COD | I933: =G933-(D933*F933) -> 1944 | J933: =YEAR(Table16[[#This Row],[Date]]) -> 2024 | K933: =TEXT(Table16[[#This Row],[Date]],"MMMM") -> April
A934: 25/03/2024 | B934: O2933 | C934: P148 | D934: =IF(C934="P141",435,IF(C934="P142",223,IF(C934="P143",648,IF(C934="P144",633,IF(C934="P145",176,IF(C934="P146",495,IF(C934="P147",123,IF(C934="P148",457,IF(C934="P149",668,IF(C934="P150",265,0)))))))))) -> 457 | E934: 700 | F934: 7 | G934: =Sales_Table!$E934*F934 -> 4900 | H934: COD | I934: =G934-(D934*F934) -> 1701 | J934: =YEAR(Table16[[#This Row],[Date]]) -> 2024 | K934: =TEXT(Table16[[#This Row],[Date]],"MMMM") -> March
A935: 17/02/2020 | B935: O2934 | C935: P148 | D935: =IF(C935="P141",435,IF(C935="P142",223,IF(C935="P143",648,IF(C935="P144",633,IF(C935="P145",176,IF(C935="P146",495,IF(C935="P147",123,IF(C935="P148",457,IF(C935="P149",668,IF(C935="P150",265,0)))))))))) -> 457 | E935: 700 | F935: 5 | G935: =Sales_Table!$E935*F935 -> 3500 | H935: COD | I935: =G935-(D935*F935) -> 1215 | J935: =YEAR(Table16[[#This Row],[Date]]) -> 2020 | K935: =TEXT(Table16[[#This Row],[Date]],"MMMM") -> February
A936: 15/01/2022 | B936: O2935 | C936: P148 | D936: =IF(C936="P141",435,IF(C936="P142",223,IF(C936="P143",648,IF(C936="P144",633,IF(C936="P145",176,IF(C936="P146",495,IF(C936="P147",123,IF(C936="P148",457,IF(C936="P149",668,IF(C936="P150",265,0)))))))))) -> 457 | E936: 700 | F936: 6 | G936: =Sales_Table!$E936*F936 -> 4200 | H936: Credit | I936: =G936-(D936*F936) -> 1458 | J936: =YEAR(Table16[[#This Row],[Date]]) -> 2022 | K936: =TEXT(Table16[[#This Row],[Date]],"MMMM") -> January
A937: 08/06/2022 | B937: O2936 | C937: P148 | D937: =IF(C937="P141",435,IF(C937="P142",223,IF(C937="P143",648,IF(C937="P144",633,IF(C937="P145",176,IF(C937="P146",495,IF(C937="P147",123,IF(C937="P148",457,IF(C937="P149",668,IF(C937="P150",265,0)))))))))) -> 457 | E937: 700 | F937: 4 | G937: =Sales_Table!$E937*F937 -> 2800 | H937: COD | I937: =G937-(D937*F937) -> 972 | J937: =YEAR(Table16[[#This Row],[Date]]) -> 2022 | K937: =TEXT(Table16[[#This Row],[Date]],"MMMM") -> June
... A1001: 15/12/2024 | B1001: O3000 | C1001: P150 | D1001: =IF(C1001="P141",435,IF(C1001="P142",223,IF(C1001="P143",648,IF(C1001="P144",633,IF(C1001="P145",176,IF(C1001="P146",495,IF(C1001="P147",123,IF(C1001="P148",457,IF(C1001="P149",668,IF(C1001="P150",265,0)))))))))) -> 265 | E1001: 212 | F1001: 9 | G1001: =Sales_Table!$E1001*F1001 -> 1908 | H1001: Credit | I1001: =G1001-(D1001*F1001) -> -477 | J1001: =YEAR(Table16[[#This Row],[Date]]) -> 2024 | K1001: =TEXT(Table16[[#This Row],[Date]],"MMMM") -> December

Sheet Inventory_Table
A1: Product_id | B1: Category | C1: Product_name | D1: Stock In | E1: Stock Out | F1: Current Stock
A2: P101 | B2: Toys & Games | C2: =IF(B2="Electronics", CHOOSE(RANDBETWEEN(1,5), "Smartphone", "Laptop", "Smartwatch", "Bluetooth Speaker", "Wireless Earbuds"), IF(B2="Clothing", CHOOSE(RANDBETWEEN(1,5), "T-shirt", "Jeans", "Jacket", "Hoodie", "Shorts"), IF(B2="Books", CHOOSE(RANDBETWEEN(1,5), "Novel", "Biography", "Comics", "Cookbook", "Textbook"), IF(B2="Footwear", CHOOSE(RANDBETWEEN(1,5), "Sneakers", "Sandals", "Boots", "Loafers", "Flip-flops"), IF(B2="Furniture", CHOOSE(RANDBETWEEN(1,5), "Chair", "Table", "Sofa", "Wardrobe", "Bed"), IF(B2="Home Appliances", CHOOSE(RANDBETWEEN(1,5), "Refrigerator", "Microwave", "Washing Machine", "Air Conditioner", "Vacuum Cleaner"), IF(B2="Beauty & Personal Care", CHOOSE(RANDBETWEEN(1,5), "Lipstick", "Moisturizer", "Perfume", "Shampoo", "Sunscreen"), IF(B2="Stationery", CHOOSE(RANDBETWEEN(1,5), "Pen", "Notebook", "Marker", "Stapler", "Eraser"), IF(B2="Toys & Games", CHOOSE(RANDBETWEEN(1,5), "Puzzle", "Action Figure", "Board Game", "Doll", "Remote Car"), IF(B2="Sports & Fitness", CHOOSE(RANDBETWEEN(1,5), "Treadmill", "Dumbbells", "Yoga Mat", "Bicycle", "Skipping Rope"), "Unknown")))))))))) -> Action Figure | D2: 190 | E2: =RANDBETWEEN(150, D2 - 1) -> 174 | F2: =D2-E2 -> 16
A3: P102 | B3: Footwear | C3: =IF(B3="Electronics", CHOOSE(RANDBETWEEN(1,5), "Smartphone", "Laptop", "Smartwatch", "Bluetooth Speaker", "Wireless Earbuds"), IF(B3="Clothing", CHOOSE(RANDBETWEEN(1,5), "T-shirt", "Jeans", "Jacket", "Hoodie", "Shorts"), IF(B3="Books", CHOOSE(RANDBETWEEN(1,5), "Novel", "Biography", "Comics", "Cookbook", "Textbook"), IF(B3="Footwear", CHOOSE(RANDBETWEEN(1,5), "Sneakers", "Sandals", "Boots", "Loafers", "Flip-flops"), IF(B3="Furniture", CHOOSE(RANDBETWEEN(1,5), "Chair", "Table", "Sofa", "Wardrobe", "Bed"), IF(B3="Home Appliances", CHOOSE(RANDBETWEEN(1,5), "Refrigerator", "Microwave", "Washing Machine", "Air Conditioner", "Vacuum Cleaner"), IF(B3="Beauty & Personal Care", CHOOSE(RANDBETWEEN(1,5), "Lipstick", "Moisturizer", "Perfume", "Shampoo", "Sunscreen"), IF(B3="Stationery", CHOOSE(RANDBETWEEN(1,5), "Pen", "Notebook", "Marker", "Stapler", "Eraser"), IF(B3="Toys & Games", CHOOSE(RANDBETWEEN(1,5), "Puzzle", "Action Figure", "Board Game", "Doll", "Remote Car"), IF(B3="Sports & Fitness", CHOOSE(RANDBETWEEN(1,5), "Treadmill", "Dumbbells", "Yoga Mat", "Bicycle", "Skipping Rope"), "Unknown")))))))))) -> Loafers | D3: 411 | E3: =RANDBETWEEN(150, D3 - 1) -> 216 | F3: =D3-E3 -> 195
A4: P103 | B4: Electronics | C4: =IF(B4="Electronics", CHOOSE(RANDBETWEEN(1,5), "Smartphone", "Laptop", "Smartwatch", "Bluetooth Speaker", "Wireless Earbuds"), IF(B4="Clothing", CHOOSE(RANDBETWEEN(1,5), "T-shirt", "Jeans", "Jacket", "Hoodie", "Shorts"), IF(B4="Books", CHOOSE(RANDBETWEEN(1,5), "Novel", "Biography", "Comics", "Cookbook", "Textbook"), IF(B4="Footwear", CHOOSE(RANDBETWEEN(1,5), "Sneakers", "Sandals", "Boots", "Loafers", "Flip-flops"), IF(B4="Furniture", CHOOSE(RANDBETWEEN(1,5), "Chair", "Table", "Sofa", "Wardrobe", "Bed"), IF(B4="Home Appliances", CHOOSE(RANDBETWEEN(1,5), "Refrigerator", "Microwave", "Washing Machine", "Air Conditioner", "Vacuum Cleaner"), IF(B4="Beauty & Personal Care", CHOOSE(RANDBETWEEN(1,5), "Lipstick", "Moisturizer", "Perfume", "Shampoo", "Sunscreen"), IF(B4="Stationery", CHOOSE(RANDBETWEEN(1,5), "Pen", "Notebook", "Marker", "Stapler", "Eraser"), IF(B4="Toys & Games", CHOOSE(RANDBETWEEN(1,5), "Puzzle", "Action Figure", "Board Game", "Doll", "Remote Car"), IF(B4="Sports & Fitness", CHOOSE(RANDBETWEEN(1,5), "Treadmill", "Dumbbells", "Yoga Mat", "Bicycle", "Skipping Rope"), "Unknown")))))))))) -> Wireless Earbuds | D4: 446 | E4: =RANDBETWEEN(150, D4 - 1) -> 373 | F4: =D4-E4 -> 73
A5: P104 | B5: Sports & Fitness | C5: =IF(B5="Electronics", CHOOSE(RANDBETWEEN(1,5), "Smartphone", "Laptop", "Smartwatch", "Bluetooth Speaker", "Wireless Earbuds"), IF(B5="Clothing", CHOOSE(RANDBETWEEN(1,5), "T-shirt", "Jeans", "Jacket", "Hoodie", "Shorts"), IF(B5="Books", CHOOSE(RANDBETWEEN(1,5), "Novel", "Biography", "Comics", "Cookbook", "Textbook"), IF(B5="Footwear", CHOOSE(RANDBETWEEN(1,5), "Sneakers", "Sandals", "Boots", "Loafers", "Flip-flops"), IF(B5="Furniture", CHOOSE(RANDBETWEEN(1,5), "Chair", "Table", "Sofa", "Wardrobe", "Bed"), IF(B5="Home Appliances", CHOOSE(RANDBETWEEN(1,5), "Refrigerator", "Microwave", "Washing Machine", "Air Conditioner", "Vacuum Cleaner"), IF(B5="Beauty & Personal Care", CHOOSE(RANDBETWEEN(1,5), "Lipstick", "Moisturizer", "Perfume", "Shampoo", "Sunscreen"), IF(B5="Stationery", CHOOSE(RANDBETWEEN(1,5), "Pen", "Notebook", "Marker", "Stapler", "Eraser"), IF(B5="Toys & Games", CHOOSE(RANDBETWEEN(1,5), "Puzzle", "Action Figure", "Board Game", "Doll", "Remote Car"), IF(B5="Sports & Fitness", CHOOSE(RANDBETWEEN(1,5), "Treadmill", "Dumbbells", "Yoga Mat", "Bicycle", "Skipping Rope"), "Unknown")))))))))) -> Treadmill | D5: 322 | E5: =RANDBETWEEN(150, D5 - 1) -> 316 | F5: =D5-E5 -> 6
A6: P105 | B6: Footwear | C6: =IF(B6="Electronics", CHOOSE(RANDBETWEEN(1,5), "Smartphone", "Laptop", "Smartwatch", "Bluetooth Speaker", "Wireless Earbuds"), IF(B6="Clothing", CHOOSE(RANDBETWEEN(1,5), "T-shirt", "Jeans", "Jacket", "Hoodie", "Shorts"), IF(B6="Books", CHOOSE(RANDBETWEEN(1,5), "Novel", "Biography", "Comics", "Cookbook", "Textbook"), IF(B6="Footwear", CHOOSE(RANDBETWEEN(1,5), "Sneakers", "Sandals", "Boots", "Loafers", "Flip-flops"), IF(B6="Furniture", CHOOSE(RANDBETWEEN(1,5), "Chair", "Table", "Sofa", "Wardrobe", "Bed"), IF(B6="Home Appliances", CHOOSE(RANDBETWEEN(1,5), "Refrigerator", "Microwave", "Washing Machine", "Air Conditioner", "Vacuum Cleaner"), IF(B6="Beauty & Personal Care", CHOOSE(RANDBETWEEN(1,5), "Lipstick", "Moisturizer", "Perfume", "Shampoo", "Sunscreen"), IF(B6="Stationery", CHOOSE(RANDBETWEEN(1,5), "Pen", "Notebook", "Marker", "Stapler", "Eraser"), IF(B6="Toys & Games", CHOOSE(RANDBETWEEN(1,5), "Puzzle", "Action Figure", "Board Game", "Doll", "Remote Car"), IF(B6="Sports & Fitness", CHOOSE(RANDBETWEEN(1,5), "Treadmill", "Dumbbells", "Yoga Mat", "Bicycle", "Skipping Rope"), "Unknown")))))))))) -> Sandals | D6: 269 | E6: =RANDBETWEEN(150, D6 - 1) -> 222 | F6: =D6-E6 -> 47
A7: P106 | B7: Stationery | C7: =IF(B7="Electronics", CHOOSE(RANDBETWEEN(1,5), "Smartphone", "Laptop", "Smartwatch", "Bluetooth Speaker", "Wireless Earbuds"), IF(B7="Clothing", CHOOSE(RANDBETWEEN(1,5), "T-shirt", "Jeans", "Jacket", "Hoodie", "Shorts"), IF(B7="Books", CHOOSE(RANDBETWEEN(1,5), "Novel", "Biography", "Comics", "Cookbook", "Textbook"), IF(B7="Footwear", CHOOSE(RANDBETWEEN(1,5), "Sneakers", "Sandals", "Boots", "Loafers", "Flip-flops"), IF(B7="Furniture", CHOOSE(RANDBETWEEN(1,5), "Chair", "Table", "Sofa", "Wardrobe", "Bed"), IF(B7="Home Appliances", CHOOSE(RANDBETWEEN(1,5), "Refrigerator", "Microwave", "Washing Machine", "Air Conditioner", "Vacuum Cleaner"), IF(B7="Beauty & Personal Care", CHOOSE(RANDBETWEEN(1,5), "Lipstick", "Moisturizer", "Perfume", "Shampoo", "Sunscreen"), IF(B7="Stationery", CHOOSE(RANDBETWEEN(1,5), "Pen", "Notebook", "Marker", "Stapler", "Eraser"), IF(B7="Toys & Games", CHOOSE(RANDBETWEEN(1,5), "Puzzle", "Action Figure", "Board Game", "Doll", "Remote Car"), IF(B7="Sports & Fitness", CHOOSE(RANDBETWEEN(1,5), "Treadmill", "Dumbbells", "Yoga Mat", "Bicycle", "Skipping Rope"), "Unknown")))))))))) -> Marker | D7: 432 | E7: =RANDBETWEEN(150, D7 - 1) -> 175 | F7: =D7-E7 -> 257
A8: P107 | B8: Beauty & Personal Care | C8: =IF(B8="Electronics", CHOOSE(RANDBETWEEN(1,5), "Smartphone", "Laptop", "Smartwatch", "Bluetooth Speaker", "Wireless Earbuds"), IF(B8="Clothing", CHOOSE(RANDBETWEEN(1,5), "T-shirt", "Jeans", "Jacket", "Hoodie", "Shorts"), IF(B8="Books", CHOOSE(RANDBETWEEN(1,5), "Novel", "Biography", "Comics", "Cookbook", "Textbook"), IF(B8="Footwear", CHOOSE(RANDBETWEEN(1,5), "Sneakers", "Sandals", "Boots", "Loafers", "Flip-flops"), IF(B8="Furniture", CHOOSE(RANDBETWEEN(1,5), "Chair", "Table", "Sofa", "Wardrobe", "Bed"), IF(B8="Home Appliances", CHOOSE(RANDBETWEEN(1,5), "Refrigerator", "Microwave", "Washing Machine", "Air Conditioner", "Vacuum Cleaner"), IF(B8="Beauty & Personal Care", CHOOSE(RANDBETWEEN(1,5), "Lipstick", "Moisturizer", "Perfume", "Shampoo", "Sunscreen"), IF(B8="Stationery", CHOOSE(RANDBETWEEN(1,5), "Pen", "Notebook", "Marker", "Stapler", "Eraser"), IF(B8="Toys & Games", CHOOSE(RANDBETWEEN(1,5), "Puzzle", "Action Figure", "Board Game", "Doll", "Remote Car"), IF(B8="Sports & Fitness", CHOOSE(RANDBETWEEN(1,5), "Treadmill", "Dumbbells", "Yoga Mat", "Bicycle", "Skipping Rope"), "Unknown")))))))))) -> Shampoo | D8: 232 | E8: =RANDBETWEEN(150, D8 - 1) -> 162 | F8: =D8-E8 -> 70
A9: P108 | B9: Sports & Fitness | C9: =IF(B9="Electronics", CHOOSE(RANDBETWEEN(1,5), "Smartphone", "Laptop", "Smartwatch", "Bluetooth Speaker", "Wireless Earbuds"), IF(B9="Clothing", CHOOSE(RANDBETWEEN(1,5), "T-shirt", "Jeans", "Jacket", "Hoodie", "Shorts"), IF(B9="Books", CHOOSE(RANDBETWEEN(1,5), "Novel", "Biography", "Comics", "Cookbook", "Textbook"), IF(B9="Footwear", CHOOSE(RANDBETWEEN(1,5), "Sneakers", "Sandals", "Boots", "Loafers", "Flip-flops"), IF(B9="Furniture", CHOOSE(RANDBETWEEN(1,5), "Chair", "Table", "Sofa", "Wardrobe", "Bed"), IF(B9="Home Appliances", CHOOSE(RANDBETWEEN(1,5), "Refrigerator", "Microwave", "Washing Machine", "Air Conditioner", "Vacuum Cleaner"), IF(B9="Beauty & Personal Care", CHOOSE(RANDBETWEEN(1,5), "Lipstick", "Moisturizer", "Perfume", "Shampoo", "Sunscreen"), IF(B9="Stationery", CHOOSE(RANDBETWEEN(1,5), "Pen", "Notebook", "Marker", "Stapler", "Eraser"), IF(B9="Toys & Games", CHOOSE(RANDBETWEEN(1,5), "Puzzle", "Action Figure", "Board Game", "Doll", "Remote Car"), IF(B9="Sports & Fitness", CHOOSE(RANDBETWEEN(1,5), "Treadmill", "Dumbbells", "Yoga Mat", "Bicycle", "Skipping Rope"), "Unknown")))))))))) -> Skipping Rope | D9: 311 | E9: =RANDBETWEEN(150, D9 - 1) -> 172 | F9: =D9-E9 -> 139
A10: P109 | B10: Toys & Games | C10: =IF(B10="Electronics", CHOOSE(RANDBETWEEN(1,5), "Smartphone", "Laptop", "Smartwatch", "Bluetooth Speaker", "Wireless Earbuds"), IF(B10="Clothing", CHOOSE(RANDBETWEEN(1,5), "T-shirt", "Jeans", "Jacket", "Hoodie", "Shorts"), IF(B10="Books", CHOOSE(RANDBETWEEN(1,5), "Novel", "Biography", "Comics", "Cookbook", "Textbook"), IF(B10="Footwear", CHOOSE(RANDBETWEEN(1,5), "Sneakers", "Sandals", "Boots", "Loafers", "Flip-flops"), IF(B10="Furniture", CHOOSE(RANDBETWEEN(1,5), "Chair", "Table", "Sofa", "Wardrobe", "Bed"), IF(B10="Home Appliances", CHOOSE(RANDBETWEEN(1,5), "Refrigerator", "Microwave", "Washing Machine", "Air Conditioner", "Vacuum Cleaner"), IF(B10="Beauty & Personal Care", CHOOSE(RANDBETWEEN(1,5), "Lipstick", "Moisturizer", "Perfume", "Shampoo", "Sunscreen"), IF(B10="Stationery", CHOOSE(RANDBETWEEN(1,5), "Pen", "Notebook", "Marker", "Stapler", "Eraser"), IF(B10="Toys & Games", CHOOSE(RANDBETWEEN(1,5), "Puzzle", "Action Figure", "Board Game", "Doll", "Remote Car"), IF(B10="Sports & Fitness", CHOOSE(RANDBETWEEN(1,5), "Treadmill", "Dumbbells", "Yoga Mat", "Bicycle", "Skipping Rope"), "Unknown")))))))))) -> Action Figure | D10: 324 | E10: =RANDBETWEEN(150, D10 - 1) -> 294 | F10: =D10-E10 -> 30
A11: P110 | B11: Home Appliances | C11: =IF(B11="Electronics", CHOOSE(RANDBETWEEN(1,5), "Smartphone", "Laptop", "Smartwatch", "Bluetooth Speaker", "Wireless Earbuds"), IF(B11="Clothing", CHOOSE(RANDBETWEEN(1,5), "T-shirt", "Jeans", "Jacket", "Hoodie", "Shorts"), IF(B11="Books", CHOOSE(RANDBETWEEN(1,5), "Novel", "Biography", "Comics", "Cookbook", "Textbook"), IF(B11="Footwear", CHOOSE(RANDBETWEEN(1,5), "Sneakers", "Sandals", "Boots", "Loafers", "Flip-flops"), IF(B11="Furniture", CHOOSE(RANDBETWEEN(1,5), "Chair", "Table", "Sofa", "Wardrobe", "Bed"), IF(B11="Home Appliances", CHOOSE(RANDBETWEEN(1,5), "Refrigerator", "Microwave", "Washing Machine", "Air Conditioner", "Vacuum Cleaner"), IF(B11="Beauty & Personal Care", CHOOSE(RANDBETWEEN(1,5), "Lipstick", "Moisturizer", "Perfume", "Shampoo", "Sunscreen"), IF(B11="Stationery", CHOOSE(RANDBETWEEN(1,5), "Pen", "Notebook", "Marker", "Stapler", "Eraser"), IF(B11="Toys & Games", CHOOSE(RANDBETWEEN(1,5), "Puzzle", "Action Figure", "Board Game", "Doll", "Remote Car"), IF(B11="Sports & Fitness", CHOOSE(RANDBETWEEN(1,5), "Treadmill", "Dumbbells", "Yoga Mat", "Bicycle", "Skipping Rope"), "Unknown")))))))))) -> Air Conditioner | D11: 448 | E11: =RANDBETWEEN(150, D11 - 1) -> 298 | F11: =D11-E11 -> 150
A12: P111 | B12: Home Appliances | C12: =IF(B12="Electronics", CHOOSE(RANDBETWEEN(1,5), "Smartphone", "Laptop", "Smartwatch", "Bluetooth Speaker", "Wireless Earbuds"), IF(B12="Clothing", CHOOSE(RANDBETWEEN(1,5), "T-shirt", "Jeans", "Jacket", "Hoodie", "Shorts"), IF(B12="Books", CHOOSE(RANDBETWEEN(1,5), "Novel", "Biography", "Comics", "Cookbook", "Textbook"), IF(B12="Footwear", CHOOSE(RANDBETWEEN(1,5), "Sneakers", "Sandals", "Boots", "Loafers", "Flip-flops"), IF(B12="Furniture", CHOOSE(RANDBETWEEN(1,5), "Chair", "Table", "Sofa", "Wardrobe", "Bed"), IF(B12="Home Appliances", CHOOSE(RANDBETWEEN(1,5), "Refrigerator", "Microwave", "Washing Machine", "Air Conditioner", "Vacuum Cleaner"), IF(B12="Beauty & Personal Care", CHOOSE(RANDBETWEEN(1,5), "Lipstick", "Moisturizer", "Perfume", "Shampoo", "Sunscreen"), IF(B12="Stationery", CHOOSE(RANDBETWEEN(1,5), "Pen", "Notebook", "Marker", "Stapler", "Eraser"), IF(B12="Toys & Games", CHOOSE(RANDBETWEEN(1,5), "Puzzle", "Action Figure", "Board Game", "Doll", "Remote Car"), IF(B12="Sports & Fitness", CHOOSE(RANDBETWEEN(1,5), "Treadmill", "Dumbbells", "Yoga Mat", "Bicycle", "Skipping Rope"), "Unknown")))))))))) -> Microwave | D12: 301 | E12: =RANDBETWEEN(150, D12 - 1) -> 255 | F12: =D12-E12 -> 46
A13: P112 | B13: Clothing | C13: =IF(B13="Electronics", CHOOSE(RANDBETWEEN(1,5), "Smartphone", "Laptop", "Smartwatch", "Bluetooth Speaker", "Wireless Earbuds"), IF(B13="Clothing", CHOOSE(RANDBETWEEN(1,5), "T-shirt", "Jeans", "Jacket", "Hoodie", "Shorts"), IF(B13="Books", CHOOSE(RANDBETWEEN(1,5), "Novel", "Biography", "Comics", "Cookbook", "Textbook"), IF(B13="Footwear", CHOOSE(RANDBETWEEN(1,5), "Sneakers", "Sandals", "Boots", "Loafers", "Flip-flops"), IF(B13="Furniture", CHOOSE(RANDBETWEEN(1,5), "Chair", "Table", "Sofa", "Wardrobe", "Bed"), IF(B13="Home Appliances", CHOOSE(RANDBETWEEN(1,5), "Refrigerator", "Microwave", "Washing Machine", "Air Conditioner", "Vacuum Cleaner"), IF(B13="Beauty & Personal Care", CHOOSE(RANDBETWEEN(1,5), "Lipstick", "Moisturizer", "Perfume", "Shampoo", "Sunscreen"), IF(B13="Stationery", CHOOSE(RANDBETWEEN(1,5), "Pen", "Notebook", "Marker", "Stapler", "Eraser"), IF(B13="Toys & Games", CHOOSE(RANDBETWEEN(1,5), "Puzzle", "Action Figure", "Board Game", "Doll", "Remote Car"), IF(B13="Sports & Fitness", CHOOSE(RANDBETWEEN(1,5), "Treadmill", "Dumbbells", "Yoga Mat", "Bicycle", "Skipping Rope"), "Unknown")))))))))) -> Jeans | D13: 302 | E13: =RANDBETWEEN(150, D13 - 1) -> 251 | F13: =D13-E13 -> 51
... A51: P150 | B51: Toys & Games | C51: =IF(B51="Electronics", CHOOSE(RANDBETWEEN(1,5), "Smartphone", "Laptop", "Smartwatch", "Bluetooth Speaker", "Wireless Earbuds"), IF(B51="Clothing", CHOOSE(RANDBETWEEN(1,5), "T-shirt", "Jeans", "Jacket", "Hoodie", "Shorts"), IF(B51="Books", CHOOSE(RANDBETWEEN(1,5), "Novel", "Biography", "Comics", "Cookbook", "Textbook"), IF(B51="Footwear", CHOOSE(RANDBETWEEN(1,5), "Sneakers", "Sandals", "Boots", "Loafers", "Flip-flops"), IF(B51="Furniture", CHOOSE(RANDBETWEEN(1,5), "Chair", "Table", "Sofa", "Wardrobe", "Bed"), IF(B51="Home Appliances", CHOOSE(RANDBETWEEN(1,5), "Refrigerator", "Microwave", "Washing Machine", "Air Conditioner", "Vacuum Cleaner"), IF(B51="Beauty & Personal Care", CHOOSE(RANDBETWEEN(1,5), "Lipstick", "Moisturizer", "Perfume", "Shampoo", "Sunscreen"), IF(B51="Stationery", CHOOSE(RANDBETWEEN(1,5), "Pen", "Notebook", "Marker", "Stapler", "Eraser"), IF(B51="Toys & Games", CHOOSE(RANDBETWEEN(1,5), "Puzzle", "Action Figure", "Board Game", "Doll", "Remote Car"), IF(B51="Sports & Fitness", CHOOSE(RANDBETWEEN(1,5), "Treadmill", "Dumbbells", "Yoga Mat", "Bicycle", "Skipping Rope"), "Unknown")))))))))) -> Action Figure | D51: 289 | E51: =RANDBETWEEN(150, D51 - 1) -> 179 | F51: =D51-E51 -> 110

Sheet Product_Table
A1: Product_id | B1: Category | C1: Product_name | D1: Cost | E1: Supplier
A2: P101 | B2: Toys & Games | C2: =IF(B2="Electronics", CHOOSE(RANDBETWEEN(1,5), "Smartphone", "Laptop", "Smartwatch", "Bluetooth Speaker", "Wireless Earbuds"), IF(B2="Clothing", CHOOSE(RANDBETWEEN(1,5), "T-shirt", "Jeans", "Jacket", "Hoodie", "Shorts"), IF(B2="Books", CHOOSE(RANDBETWEEN(1,5), "Novel", "Biography", "Comics", "Cookbook", "Textbook"), IF(B2="Footwear", CHOOSE(RANDBETWEEN(1,5), "Sneakers", "Sandals", "Boots", "Loafers", "Flip-flops"), IF(B2="Furniture", CHOOSE(RANDBETWEEN(1,5), "Chair", "Table", "Sofa", "Wardrobe", "Bed"), IF(B2="Home Appliances", CHOOSE(RANDBETWEEN(1,5), "Refrigerator", "Microwave", "Washing Machine", "Air Conditioner", "Vacuum Cleaner"), IF(B2="Beauty & Personal Care", CHOOSE(RANDBETWEEN(1,5), "Lipstick", "Moisturizer", "Perfume", "Shampoo", "Sunscreen"), IF(B2="Stationery", CHOOSE(RANDBETWEEN(1,5), "Pen", "Notebook", "Marker", "Stapler", "Eraser"), IF(B2="Toys & Games", CHOOSE(RANDBETWEEN(1,5), "Puzzle", "Action Figure", "Board Game", "Doll", "Remote Car"), IF(B2="Sports & Fitness", CHOOSE(RANDBETWEEN(1,5), "Treadmill", "Dumbbells", "Yoga Mat", "Bicycle", "Skipping Rope"), "Unknown")))))))))) -> Action Figure | D2: 271 | E2: ShopPro Distributors
A3: P102 | B3: Footwear | C3: =IF(B3="Electronics", CHOOSE(RANDBETWEEN(1,5), "Smartphone", "Laptop", "Smartwatch", "Bluetooth Speaker", "Wireless Earbuds"), IF(B3="Clothing", CHOOSE(RANDBETWEEN(1,5), "T-shirt", "Jeans", "Jacket", "Hoodie", "Shorts"), IF(B3="Books", CHOOSE(RANDBETWEEN(1,5), "Novel", "Biography", "Comics", "Cookbook", "Textbook"), IF(B3="Footwear", CHOOSE(RANDBETWEEN(1,5), "Sneakers", "Sandals", "Boots", "Loafers", "Flip-flops"), IF(B3="Furniture", CHOOSE(RANDBETWEEN(1,5), "Chair", "Table", "Sofa", "Wardrobe", "Bed"), IF(B3="Home Appliances", CHOOSE(RANDBETWEEN(1,5), "Refrigerator", "Microwave", "Washing Machine", "Air Conditioner", "Vacuum Cleaner"), IF(B3="Beauty & Personal Care", CHOOSE(RANDBETWEEN(1,5), "Lipstick", "Moisturizer", "Perfume", "Shampoo", "Sunscreen"), IF(B3="Stationery", CHOOSE(RANDBETWEEN(1,5), "Pen", "Notebook", "Marker", "Stapler", "Eraser"), IF(B3="Toys & Games", CHOOSE(RANDBETWEEN(1,5), "Puzzle", "Action Figure", "Board Game", "Doll", "Remote Car"), IF(B3="Sports & Fitness", CHOOSE(RANDBETWEEN(1,5), "Treadmill", "Dumbbells", "Yoga Mat", "Bicycle", "Skipping Rope"), "Unknown")))))))))) -> Loafers | D3: 408 | E3: SwiftMart Distributors
A4: P103 | B4: Electronics | C4: =IF(B4="Electronics", CHOOSE(RANDBETWEEN(1,5), "Smartphone", "Laptop", "Smartwatch", "Bluetooth Speaker", "Wireless Earbuds"), IF(B4="Clothing", CHOOSE(RANDBETWEEN(1,5), "T-shirt", "Jeans", "Jacket", "Hoodie", "Shorts"), IF(B4="Books", CHOOSE(RANDBETWEEN(1,5), "Novel", "Biography", "Comics", "Cookbook", "Textbook"), IF(B4="Footwear", CHOOSE(RANDBETWEEN(1,5), "Sneakers", "Sandals", "Boots", "Loafers", "Flip-flops"), IF(B4="Furniture", CHOOSE(RANDBETWEEN(1,5), "Chair", "Table", "Sofa", "Wardrobe", "Bed"), IF(B4="Home Appliances", CHOOSE(RANDBETWEEN(1,5), "Refrigerator", "Microwave", "Washing Machine", "Air Conditioner", "Vacuum Cleaner"), IF(B4="Beauty & Personal Care", CHOOSE(RANDBETWEEN(1,5), "Lipstick", "Moisturizer", "Perfume", "Shampoo", "Sunscreen"), IF(B4="Stationery", CHOOSE(RANDBETWEEN(1,5), "Pen", "Notebook", "Marker", "Stapler", "Eraser"), IF(B4="Toys & Games", CHOOSE(RANDBETWEEN(1,5), "Puzzle", "Action Figure", "Board Game", "Doll", "Remote Car"), IF(B4="Sports & Fitness", CHOOSE(RANDBETWEEN(1,5), "Treadmill", "Dumbbells", "Yoga Mat", "Bicycle", "Skipping Rope"), "Unknown")))))))))) -> Wireless Earbuds | D4: 735 | E4: Bazaar World Importers
A5: P104 | B5: Sports & Fitness | C5: =IF(B5="Electronics", CHOOSE(RANDBETWEEN(1,5), "Smartphone", "Laptop", "Smartwatch", "Bluetooth Speaker", "Wireless Earbuds"), IF(B5="Clothing", CHOOSE(RANDBETWEEN(1,5), "T-shirt", "Jeans", "Jacket", "Hoodie", "Shorts"), IF(B5="Books", CHOOSE(RANDBETWEEN(1,5), "Novel", "Biography", "Comics", "Cookbook", "Textbook"), IF(B5="Footwear", CHOOSE(RANDBETWEEN(1,5), "Sneakers", "Sandals", "Boots", "Loafers", "Flip-flops"), IF(B5="Furniture", CHOOSE(RANDBETWEEN(1,5), "Chair", "Table", "Sofa", "Wardrobe", "Bed"), IF(B5="Home Appliances", CHOOSE(RANDBETWEEN(1,5), "Refrigerator", "Microwave", "Washing Machine", "Air Conditioner", "Vacuum Cleaner"), IF(B5="Beauty & Personal Care", CHOOSE(RANDBETWEEN(1,5), "Lipstick", "Moisturizer", "Perfume", "Shampoo", "Sunscreen"), IF(B5="Stationery", CHOOSE(RANDBETWEEN(1,5), "Pen", "Notebook", "Marker", "Stapler", "Eraser"), IF(B5="Toys & Games", CHOOSE(RANDBETWEEN(1,5), "Puzzle", "Action Figure", "Board Game", "Doll", "Remote Car"), IF(B5="Sports & Fitness", CHOOSE(RANDBETWEEN(1,5), "Treadmill", "Dumbbells", "Yoga Mat", "Bicycle", "Skipping Rope"), "Unknown")))))))))) -> Dumbbells | D5: 749 | E5: ProGear Supply Co.
A6: P105 | B6: Footwear | C6: =IF(B6="Electronics", CHOOSE(RANDBETWEEN(1,5), "Smartphone", "Laptop", "Smartwatch", "Bluetooth Speaker", "Wireless Earbuds"), IF(B6="Clothing", CHOOSE(RANDBETWEEN(1,5), "T-shirt", "Jeans", "Jacket", "Hoodie", "Shorts"), IF(B6="Books", CHOOSE(RANDBETWEEN(1,5), "Novel", "Biography", "Comics", "Cookbook", "Textbook"), IF(B6="Footwear", CHOOSE(RANDBETWEEN(1,5), "Sneakers", "Sandals", "Boots", "Loafers", "Flip-flops"), IF(B6="Furniture", CHOOSE(RANDBETWEEN(1,5), "Chair", "Table", "Sofa", "Wardrobe", "Bed"), IF(B6="Home Appliances", CHOOSE(RANDBETWEEN(1,5), "Refrigerator", "Microwave", "Washing Machine", "Air Conditioner", "Vacuum Cleaner"), IF(B6="Beauty & Personal Care", CHOOSE(RANDBETWEEN(1,5), "Lipstick", "Moisturizer", "Perfume", "Shampoo", "Sunscreen"), IF(B6="Stationery", CHOOSE(RANDBETWEEN(1,5), "Pen", "Notebook", "Marker", "Stapler", "Eraser"), IF(B6="Toys & Games", CHOOSE(RANDBETWEEN(1,5), "Puzzle", "Action Figure", "Board Game", "Doll", "Remote Car"), IF(B6="Sports & Fitness", CHOOSE(RANDBETWEEN(1,5), "Treadmill", "Dumbbells", "Yoga Mat", "Bicycle", "Skipping Rope"), "Unknown")))))))))) -> Sneakers | D6: 807 | E6: Velocity Retailers
A7: P106 | B7: Stationery | C7: =IF(B7="Electronics", CHOOSE(RANDBETWEEN(1,5), "Smartphone", "Laptop", "Smartwatch", "Bluetooth Speaker", "Wireless Earbuds"), IF(B7="Clothing", CHOOSE(RANDBETWEEN(1,5), "T-shirt", "Jeans", "Jacket", "Hoodie", "Shorts"), IF(B7="Books", CHOOSE(RANDBETWEEN(1,5), "Novel", "Biography", "Comics", "Cookbook", "Textbook"), IF(B7="Footwear", CHOOSE(RANDBETWEEN(1,5), "Sneakers", "Sandals", "Boots", "Loafers", "Flip-flops"), IF(B7="Furniture", CHOOSE(RANDBETWEEN(1,5), "Chair", "Table", "Sofa", "Wardrobe", "Bed"), IF(B7="Home Appliances", CHOOSE(RANDBETWEEN(1,5), "Refrigerator", "Microwave", "Washing Machine", "Air Conditioner", "Vacuum Cleaner"), IF(B7="Beauty & Personal Care", CHOOSE(RANDBETWEEN(1,5), "Lipstick", "Moisturizer", "Perfume", "Shampoo", "Sunscreen"), IF(B7="Stationery", CHOOSE(RANDBETWEEN(1,5), "Pen", "Notebook", "Marker", "Stapler", "Eraser"), IF(B7="Toys & Games", CHOOSE(RANDBETWEEN(1,5), "Puzzle", "Action Figure", "Board Game", "Doll", "Remote Car"), IF(B7="Sports & Fitness", CHOOSE(RANDBETWEEN(1,5), "Treadmill", "Dumbbells", "Yoga Mat", "Bicycle", "Skipping Rope"), "Unknown")))))))))) -> Stapler | D7: 365 | E7: Trendy Hub Ltd.
A8: P107 | B8: Beauty & Personal Care | C8: =IF(B8="Electronics", CHOOSE(RANDBETWEEN(1,5), "Smartphone", "Laptop", "Smartwatch", "Bluetooth Speaker", "Wireless Earbuds"), IF(B8="Clothing", CHOOSE(RANDBETWEEN(1,5), "T-shirt", "Jeans", "Jacket", "Hoodie", "Shorts"), IF(B8="Books", CHOOSE(RANDBETWEEN(1,5), "Novel", "Biography", "Comics", "Cookbook", "Textbook"), IF(B8="Footwear", CHOOSE(RANDBETWEEN(1,5), "Sneakers", "Sandals", "Boots", "Loafers", "Flip-flops"), IF(B8="Furniture", CHOOSE(RANDBETWEEN(1,5), "Chair", "Table", "Sofa", "Wardrobe", "Bed"), IF(B8="Home Appliances", CHOOSE(RANDBETWEEN(1,5), "Refrigerator", "Microwave", "Washing Machine", "Air Conditioner", "Vacuum Cleaner"), IF(B8="Beauty & Personal Care", CHOOSE(RANDBETWEEN(1,5), "Lipstick", "Moisturizer", "Perfume", "Shampoo", "Sunscreen"), IF(B8="Stationery", CHOOSE(RANDBETWEEN(1,5), "Pen", "Notebook", "Marker", "Stapler", "Eraser"), IF(B8="Toys & Games", CHOOSE(RANDBETWEEN(1,5), "Puzzle", "Action Figure", "Board Game", "Doll", "Remote Car"), IF(B8="Sports & Fitness", CHOOSE(RANDBETWEEN(1,5), "Treadmill", "Dumbbells", "Yoga Mat", "Bicycle", "Skipping Rope"), "Unknown")))))))))) -> Moisturizer | D8: 213 | E8: Velocity Retailers
A9: P108 | B9: Sports & Fitness | C9: =IF(B9="Electronics", CHOOSE(RANDBETWEEN(1,5), "Smartphone", "Laptop", "Smartwatch", "Bluetooth Speaker", "Wireless Earbuds"), IF(B9="Clothing", CHOOSE(RANDBETWEEN(1,5), "T-shirt", "Jeans", "Jacket", "Hoodie", "Shorts"), IF(B9="Books", CHOOSE(RANDBETWEEN(1,5), "Novel", "Biography", "Comics", "Cookbook", "Textbook"), IF(B9="Footwear", CHOOSE(RANDBETWEEN(1,5), "Sneakers", "Sandals", "Boots", "Loafers", "Flip-flops"), IF(B9="Furniture", CHOOSE(RANDBETWEEN(1,5), "Chair", "Table", "Sofa", "Wardrobe", "Bed"), IF(B9="Home Appliances", CHOOSE(RANDBETWEEN(1,5), "Refrigerator", "Microwave", "Washing Machine", "Air Conditioner", "Vacuum Cleaner"), IF(B9="Beauty & Personal Care", CHOOSE(RANDBETWEEN(1,5), "Lipstick", "Moisturizer", "Perfume", "Shampoo", "Sunscreen"), IF(B9="Stationery", CHOOSE(RANDBETWEEN(1,5), "Pen", "Notebook", "Marker", "Stapler", "Eraser"), IF(B9="Toys & Games", CHOOSE(RANDBETWEEN(1,5), "Puzzle", "Action Figure", "Board Game", "Doll", "Remote Car"), IF(B9="Sports & Fitness", CHOOSE(RANDBETWEEN(1,5), "Treadmill", "Dumbbells", "Yoga Mat", "Bicycle", "Skipping Rope"), "Unknown")))))))))) -> Bicycle | D9: 117 | E9: SmartBazaar Pvt. Ltd.
A10: P109 | B10: Books | C10: Fiction Novel | D10: 399 | E10: MegaMart Traders
A11: P110 | B11: Home Appliances | C11: =IF(B11="Electronics", CHOOSE(RANDBETWEEN(1,5), "Smartphone", "Laptop", "Smartwatch", "Bluetooth Speaker", "Wireless Earbuds"), IF(B11="Clothing", CHOOSE(RANDBETWEEN(1,5), "T-shirt", "Jeans", "Jacket", "Hoodie", "Shorts"), IF(B11="Books", CHOOSE(RANDBETWEEN(1,5), "Novel", "Biography", "Comics", "Cookbook", "Textbook"), IF(B11="Footwear", CHOOSE(RANDBETWEEN(1,5), "Sneakers", "Sandals", "Boots", "Loafers", "Flip-flops"), IF(B11="Furniture", CHOOSE(RANDBETWEEN(1,5), "Chair", "Table", "Sofa", "Wardrobe", "Bed"), IF(B11="Home Appliances", CHOOSE(RANDBETWEEN(1,5), "Refrigerator", "Microwave", "Washing Machine", "Air Conditioner", "Vacuum Cleaner"), IF(B11="Beauty & Personal Care", CHOOSE(RANDBETWEEN(1,5), "Lipstick", "Moisturizer", "Perfume", "Shampoo", "Sunscreen"), IF(B11="Stationery", CHOOSE(RANDBETWEEN(1,5), "Pen", "Notebook", "Marker", "Stapler", "Eraser"), IF(B11="Toys & Games", CHOOSE(RANDBETWEEN(1,5), "Puzzle", "Action Figure", "Board Game", "Doll", "Remote Car"), IF(B11="Sports & Fitness", CHOOSE(RANDBETWEEN(1,5), "Treadmill", "Dumbbells", "Yoga Mat", "Bicycle", "Skipping Rope"), "Unknown")))))))))) -> Air Conditioner | D11: 520 | E11: Orion Home Supplies
A12: P111 | B12: Home Appliances | C12: =IF(B12="Electronics", CHOOSE(RANDBETWEEN(1,5), "Smartphone", "Laptop", "Smartwatch", "Bluetooth Speaker", "Wireless Earbuds"), IF(B12="Clothing", CHOOSE(RANDBETWEEN(1,5), "T-shirt", "Jeans", "Jacket", "Hoodie", "Shorts"), IF(B12="Books", CHOOSE(RANDBETWEEN(1,5), "Novel", "Biography", "Comics", "Cookbook", "Textbook"), IF(B12="Footwear", CHOOSE(RANDBETWEEN(1,5), "Sneakers", "Sandals", "Boots", "Loafers", "Flip-flops"), IF(B12="Furniture", CHOOSE(RANDBETWEEN(1,5), "Chair", "Table", "Sofa", "Wardrobe", "Bed"), IF(B12="Home Appliances", CHOOSE(RANDBETWEEN(1,5), "Refrigerator", "Microwave", "Washing Machine", "Air Conditioner", "Vacuum Cleaner"), IF(B12="Beauty & Personal Care", CHOOSE(RANDBETWEEN(1,5), "Lipstick", "Moisturizer", "Perfume", "Shampoo", "Sunscreen"), IF(B12="Stationery", CHOOSE(RANDBETWEEN(1,5), "Pen", "Notebook", "Marker", "Stapler", "Eraser"), IF(B12="Toys & Games", CHOOSE(RANDBETWEEN(1,5), "Puzzle", "Action Figure", "Board Game", "Doll", "Remote Car"), IF(B12="Sports & Fitness", CHOOSE(RANDBETWEEN(1,5), "Treadmill", "Dumbbells", "Yoga Mat", "Bicycle", "Skipping Rope"), "Unknown")))))))))) -> Vacuum Cleaner | D12: 505 | E12: ValueMax Traders
A13: P112 | B13: Clothing | C13: =IF(B13="Electronics", CHOOSE(RANDBETWEEN(1,5), "Smartphone", "Laptop", "Smartwatch", "Bluetooth Speaker", "Wireless Earbuds"), IF(B13="Clothing", CHOOSE(RANDBETWEEN(1,5), "T-shirt", "Jeans", "Jacket", "Hoodie", "Shorts"), IF(B13="Books", CHOOSE(RANDBETWEEN(1,5), "Novel", "Biography", "Comics", "Cookbook", "Textbook"), IF(B13="Footwear", CHOOSE(RANDBETWEEN(1,5), "Sneakers", "Sandals", "Boots", "Loafers", "Flip-flops"), IF(B13="Furniture", CHOOSE(RANDBETWEEN(1,5), "Chair", "Table", "Sofa", "Wardrobe", "Bed"), IF(B13="Home Appliances", CHOOSE(RANDBETWEEN(1,5), "Refrigerator", "Microwave", "Washing Machine", "Air Conditioner", "Vacuum Cleaner"), IF(B13="Beauty & Personal Care", CHOOSE(RANDBETWEEN(1,5), "Lipstick", "Moisturizer", "Perfume", "Shampoo", "Sunscreen"), IF(B13="Stationery", CHOOSE(RANDBETWEEN(1,5), "Pen", "Notebook", "Marker", "Stapler", "Eraser"), IF(B13="Toys & Games", CHOOSE(RANDBETWEEN(1,5), "Puzzle", "Action Figure", "Board Game", "Doll", "Remote Car"), IF(B13="Sports & Fitness", CHOOSE(RANDBETWEEN(1,5), "Treadmill", "Dumbbells", "Yoga Mat", "Bicycle", "Skipping Rope"), "Unknown")))))))))) -> Jeans | D13: 380 | E13: Velocity Retailers
A14: P113 | B14: Clothing | C14: =IF(B14="Electronics", CHOOSE(RANDBETWEEN(1,5), "Smartphone", "Laptop", "Smartwatch", "Bluetooth Speaker", "Wireless Earbuds"), IF(B14="Clothing", CHOOSE(RANDBETWEEN(1,5), "T-shirt", "Jeans", "Jacket", "Hoodie", "Shorts"), IF(B14="Books", CHOOSE(RANDBETWEEN(1,5), "Novel", "Biography", "Comics", "Cookbook", "Textbook"), IF(B14="Footwear", CHOOSE(RANDBETWEEN(1,5), "Sneakers", "Sandals", "Boots", "Loafers", "Flip-flops"), IF(B14="Furniture", CHOOSE(RANDBETWEEN(1,5), "Chair", "Table", "Sofa", "Wardrobe", "Bed"), IF(B14="Home Appliances", CHOOSE(RANDBETWEEN(1,5), "Refrigerator", "Microwave", "Washing Machine", "Air Conditioner", "Vacuum Cleaner"), IF(B14="Beauty & Personal Care", CHOOSE(RANDBETWEEN(1,5), "Lipstick", "Moisturizer", "Perfume", "Shampoo", "Sunscreen"), IF(B14="Stationery", CHOOSE(RANDBETWEEN(1,5), "Pen", "Notebook", "Marker", "Stapler", "Eraser"), IF(B14="Toys & Games", CHOOSE(RANDBETWEEN(1,5), "Puzzle", "Action Figure", "Board Game", "Doll", "Remote Car"), IF(B14="Sports & Fitness", CHOOSE(RANDBETWEEN(1,5), "Treadmill", "Dumbbells", "Yoga Mat", "Bicycle", "Skipping Rope"), "Unknown")))))))))) -> T-shirt | D14: 392 | E14: Visionary Retailers
A15: P114 | B15: Beauty & Personal Care | C15: Shampoo | D15: 164 | E15: CraftNova Supplies
A16: P115 | B16: Sports & Fitness | C16: =IF(B16="Electronics", CHOOSE(RANDBETWEEN(1,5), "Smartphone", "Laptop", "Smartwatch", "Bluetooth Speaker", "Wireless Earbuds"), IF(B16="Clothing", CHOOSE(RANDBETWEEN(1,5), "T-shirt", "Jeans", "Jacket", "Hoodie", "Shorts"), IF(B16="Books", CHOOSE(RANDBETWEEN(1,5), "Novel", "Biography", "Comics", "Cookbook", "Textbook"), IF(B16="Footwear", CHOOSE(RANDBETWEEN(1,5), "Sneakers", "Sandals", "Boots", "Loafers", "Flip-flops"), IF(B16="Furniture", CHOOSE(RANDBETWEEN(1,5), "Chair", "Table", "Sofa", "Wardrobe", "Bed"), IF(B16="Home Appliances", CHOOSE(RANDBETWEEN(1,5), "Refrigerator", "Microwave", "Washing Machine", "Air Conditioner", "Vacuum Cleaner"), IF(B16="Beauty & Personal Care", CHOOSE(RANDBETWEEN(1,5), "Lipstick", "Moisturizer", "Perfume", "Shampoo", "Sunscreen"), IF(B16="Stationery", CHOOSE(RANDBETWEEN(1,5), "Pen", "Notebook", "Marker", "Stapler", "Eraser"), IF(B16="Toys & Games", CHOOSE(RANDBETWEEN(1,5), "Puzzle", "Action Figure", "Board Game", "Doll", "Remote Car"), IF(B16="Sports & Fitness", CHOOSE(RANDBETWEEN(1,5), "Treadmill", "Dumbbells", "Yoga Mat", "Bicycle", "Skipping Rope"), "Unknown")))))))))) -> Treadmill | D16: 282 | E16: ProGear Supply Co.
A17: P116 | B17: Footwear | C17: =IF(B17="Electronics", CHOOSE(RANDBETWEEN(1,5), "Smartphone", "Laptop", "Smartwatch", "Bluetooth Speaker", "Wireless Earbuds"), IF(B17="Clothing", CHOOSE(RANDBETWEEN(1,5), "T-shirt", "Jeans", "Jacket", "Hoodie", "Shorts"), IF(B17="Books", CHOOSE(RANDBETWEEN(1,5), "Novel", "Biography", "Comics", "Cookbook", "Textbook"), IF(B17="Footwear", CHOOSE(RANDBETWEEN(1,5), "Sneakers", "Sandals", "Boots", "Loafers", "Flip-flops"), IF(B17="Furniture", CHOOSE(RANDBETWEEN(1,5), "Chair", "Table", "Sofa", "Wardrobe", "Bed"), IF(B17="Home Appliances", CHOOSE(RANDBETWEEN(1,5), "Refrigerator", "Microwave", "Washing Machine", "Air Conditioner", "Vacuum Cleaner"), IF(B17="Beauty & Personal Care", CHOOSE(RANDBETWEEN(1,5), "Lipstick", "Moisturizer", "Perfume", "Shampoo", "Sunscreen"), IF(B17="Stationery", CHOOSE(RANDBETWEEN(1,5), "Pen", "Notebook", "Marker", "Stapler", "Eraser"), IF(B17="Toys & Games", CHOOSE(RANDBETWEEN(1,5), "Puzzle", "Action Figure", "Board Game", "Doll", "Remote Car"), IF(B17="Sports & Fitness", CHOOSE(RANDBETWEEN(1,5), "Treadmill", "Dumbbells", "Yoga Mat", "Bicycle", "Skipping Rope"), "Unknown")))))))))) -> Sneakers | D17: 386 | E17: OmniMart Vendors
A18: P117 | B18: Footwear | C18: Heels | D18: 217 | E18: Velocity Retailers
A19: P118 | B19: Furniture | C19: =IF(B19="Electronics", CHOOSE(RANDBETWEEN(1,5), "Smartphone", "Laptop", "Smartwatch", "Bluetooth Speaker", "Wireless Earbuds"), IF(B19="Clothing", CHOOSE(RANDBETWEEN(1,5), "T-shirt", "Jeans", "Jacket", "Hoodie", "Shorts"), IF(B19="Books", CHOOSE(RANDBETWEEN(1,5), "Novel", "Biography", "Comics", "Cookbook", "Textbook"), IF(B19="Footwear", CHOOSE(RANDBETWEEN(1,5), "Sneakers", "Sandals", "Boots", "Loafers", "Flip-flops"), IF(B19="Furniture", CHOOSE(RANDBETWEEN(1,5), "Chair", "Table", "Sofa", "Wardrobe", "Bed"), IF(B19="Home Appliances", CHOOSE(RANDBETWEEN(1,5), "Refrigerator", "Microwave", "Washing Machine", "Air Conditioner", "Vacuum Cleaner"), IF(B19="Beauty & Personal Care", CHOOSE(RANDBETWEEN(1,5), "Lipstick", "Moisturizer", "Perfume", "Shampoo", "Sunscreen"), IF(B19="Stationery", CHOOSE(RANDBETWEEN(1,5), "Pen", "Notebook", "Marker", "Stapler", "Eraser"), IF(B19="Toys & Games", CHOOSE(RANDBETWEEN(1,5), "Puzzle", "Action Figure", "Board Game", "Doll", "Remote Car"), IF(B19="Sports & Fitness", CHOOSE(RANDBETWEEN(1,5), "Treadmill", "Dumbbells", "Yoga Mat", "Bicycle", "Skipping Rope"), "Unknown")))))))))) -> Wardrobe | D19: 518 | E19: Prime Essentials
A20: P119 | B20: Electronics | C20: =IF(B20="Electronics", CHOOSE(RANDBETWEEN(1,5), "Smartphone", "Laptop", "Smartwatch", "Bluetooth Speaker", "Wireless Earbuds"), IF(B20="Clothing", CHOOSE(RANDBETWEEN(1,5), "T-shirt", "Jeans", "Jacket", "Hoodie", "Shorts"), IF(B20="Books", CHOOSE(RANDBETWEEN(1,5), "Novel", "Biography", "Comics", "Cookbook", "Textbook"), IF(B20="Footwear", CHOOSE(RANDBETWEEN(1,5), "Sneakers", "Sandals", "Boots", "Loafers", "Flip-flops"), IF(B20="Furniture", CHOOSE(RANDBETWEEN(1,5), "Chair", "Table", "Sofa", "Wardrobe", "Bed"), IF(B20="Home Appliances", CHOOSE(RANDBETWEEN(1,5), "Refrigerator", "Microwave", "Washing Machine", "Air Conditioner", "Vacuum Cleaner"), IF(B20="Beauty & Personal Care", CHOOSE(RANDBETWEEN(1,5), "Lipstick", "Moisturizer", "Perfume", "Shampoo", "Sunscreen"), IF(B20="Stationery", CHOOSE(RANDBETWEEN(1,5), "Pen", "Notebook", "Marker", "Stapler", "Eraser"), IF(B20="Toys & Games", CHOOSE(RANDBETWEEN(1,5), "Puzzle", "Action Figure", "Board Game", "Doll", "Remote Car"), IF(B20="Sports & Fitness", CHOOSE(RANDBETWEEN(1,5), "Treadmill", "Dumbbells", "Yoga Mat", "Bicycle", "Skipping Rope"), "Unknown")))))))))) -> Bluetooth Speaker | D20: 321 | E20: TrendNest Co.
A21: P120 | B21: Furniture | C21: =IF(B21="Electronics", CHOOSE(RANDBETWEEN(1,5), "Smartphone", "Laptop", "Smartwatch", "Bluetooth Speaker", "Wireless Earbuds"), IF(B21="Clothing", CHOOSE(RANDBETWEEN(1,5), "T-shirt", "Jeans", "Jacket", "Hoodie", "Shorts"), IF(B21="Books", CHOOSE(RANDBETWEEN(1,5), "Novel", "Biography", "Comics", "Cookbook", "Textbook"), IF(B21="Footwear", CHOOSE(RANDBETWEEN(1,5), "Sneakers", "Sandals", "Boots", "Loafers", "Flip-flops"), IF(B21="Furniture", CHOOSE(RANDBETWEEN(1,5), "Chair", "Table", "Sofa", "Wardrobe", "Bed"), IF(B21="Home Appliances", CHOOSE(RANDBETWEEN(1,5), "Refrigerator", "Microwave", "Washing Machine", "Air Conditioner", "Vacuum Cleaner"), IF(B21="Beauty & Personal Care", CHOOSE(RANDBETWEEN(1,5), "Lipstick", "Moisturizer", "Perfume", "Shampoo", "Sunscreen"), IF(B21="Stationery", CHOOSE(RANDBETWEEN(1,5), "Pen", "Notebook", "Marker", "Stapler", "Eraser"), IF(B21="Toys & Games", CHOOSE(RANDBETWEEN(1,5), "Puzzle", "Action Figure", "Board Game", "Doll", "Remote Car"), IF(B21="Sports & Fitness", CHOOSE(RANDBETWEEN(1,5), "Treadmill", "Dumbbells", "Yoga Mat", "Bicycle", "Skipping Rope"), "Unknown")))))))))) -> Chair | D21: 593 | E21: Elite Traders Pvt. Ltd.
A22: P121 | B22: Toys & Games | C22: =IF(B22="Electronics", CHOOSE(RANDBETWEEN(1,5), "Smartphone", "Laptop", "Smartwatch", "Bluetooth Speaker", "Wireless Earbuds"), IF(B22="Clothing", CHOOSE(RANDBETWEEN(1,5), "T-shirt", "Jeans", "Jacket", "Hoodie", "Shorts"), IF(B22="Books", CHOOSE(RANDBETWEEN(1,5), "Novel", "Biography", "Comics", "Cookbook", "Textbook"), IF(B22="Footwear", CHOOSE(RANDBETWEEN(1,5), "Sneakers", "Sandals", "Boots", "Loafers", "Flip-flops"), IF(B22="Furniture", CHOOSE(RANDBETWEEN(1,5), "Chair", "Table", "Sofa", "Wardrobe", "Bed"), IF(B22="Home Appliances", CHOOSE(RANDBETWEEN(1,5), "Refrigerator", "Microwave", "Washing Machine", "Air Conditioner", "Vacuum Cleaner"), IF(B22="Beauty & Personal Care", CHOOSE(RANDBETWEEN(1,5), "Lipstick", "Moisturizer", "Perfume", "Shampoo", "Sunscreen"), IF(B22="Stationery", CHOOSE(RANDBETWEEN(1,5), "Pen", "Notebook", "Marker", "Stapler", "Eraser"), IF(B22="Toys & Games", CHOOSE(RANDBETWEEN(1,5), "Puzzle", "Action Figure", "Board Game", "Doll", "Remote Car"), IF(B22="Sports & Fitness", CHOOSE(RANDBETWEEN(1,5), "Treadmill", "Dumbbells", "Yoga Mat", "Bicycle", "Skipping Rope"), "Unknown")))))))))) -> Puzzle | D22: 104 | E22: Horizon Goods Co.
A23: P122 | B23: Home Appliances | C23: =IF(B23="Electronics", CHOOSE(RANDBETWEEN(1,5), "Smartphone", "Laptop", "Smartwatch", "Bluetooth Speaker", "Wireless Earbuds"), IF(B23="Clothing", CHOOSE(RANDBETWEEN(1,5), "T-shirt", "Jeans", "Jacket", "Hoodie", "Shorts"), IF(B23="Books", CHOOSE(RANDBETWEEN(1,5), "Novel", "Biography", "Comics", "Cookbook", "Textbook"), IF(B23="Footwear", CHOOSE(RANDBETWEEN(1,5), "Sneakers", "Sandals", "Boots", "Loafers", "Flip-flops"), IF(B23="Furniture", CHOOSE(RANDBETWEEN(1,5), "Chair", "Table", "Sofa", "Wardrobe", "Bed"), IF(B23="Home Appliances", CHOOSE(RANDBETWEEN(1,5), "Refrigerator", "Microwave", "Washing Machine", "Air Conditioner", "Vacuum Cleaner"), IF(B23="Beauty & Personal Care", CHOOSE(RANDBETWEEN(1,5), "Lipstick", "Moisturizer", "Perfume", "Shampoo", "Sunscreen"), IF(B23="Stationery", CHOOSE(RANDBETWEEN(1,5), "Pen", "Notebook", "Marker", "Stapler", "Eraser"), IF(B23="Toys & Games", CHOOSE(RANDBETWEEN(1,5), "Puzzle", "Action Figure", "Board Game", "Doll", "Remote Car"), IF(B23="Sports & Fitness", CHOOSE(RANDBETWEEN(1,5), "Treadmill", "Dumbbells", "Yoga Mat", "Bicycle", "Skipping Rope"), "Unknown")))))))))) -> Vacuum Cleaner | D23: 183 | E23: Trendy Hub Ltd.
A24: P123 | B24: Stationery | C24: Pencil | D24: 371 | E24: UrbanCraft Importers
A25: P124 | B25: Footwear | C25: Shoe | D25: 415 | E25: Prestige World Traders
A26: P125 | B26: Stationery | C26: Pen | D26: 508 | E26: UrbanCraft Importers
A27: P126 | B27: Books | C27: Biography | D27: 358 | E27: GoodValue Wholesale
A28: P127 | B28: Electronics | C28: =IF(B28="Electronics", CHOOSE(RANDBETWEEN(1,5), "Smartphone", "Laptop", "Smartwatch", "Bluetooth Speaker", "Wireless Earbuds"), IF(B28="Clothing", CHOOSE(RANDBETWEEN(1,5), "T-shirt", "Jeans", "Jacket", "Hoodie", "Shorts"), IF(B28="Books", CHOOSE(RANDBETWEEN(1,5), "Novel", "Biography", "Comics", "Cookbook", "Textbook"), IF(B28="Footwear", CHOOSE(RANDBETWEEN(1,5), "Sneakers", "Sandals", "Boots", "Loafers", "Flip-flops"), IF(B28="Furniture", CHOOSE(RANDBETWEEN(1,5), "Chair", "Table", "Sofa", "Wardrobe", "Bed"), IF(B28="Home Appliances", CHOOSE(RANDBETWEEN(1,5), "Refrigerator", "Microwave", "Washing Machine", "Air Conditioner", "Vacuum Cleaner"), IF(B28="Beauty & Personal Care", CHOOSE(RANDBETWEEN(1,5), "Lipstick", "Moisturizer", "Perfume", "Shampoo", "Sunscreen"), IF(B28="Stationery", CHOOSE(RANDBETWEEN(1,5), "Pen", "Notebook", "Marker", "Stapler", "Eraser"), IF(B28="Toys & Games", CHOOSE(RANDBETWEEN(1,5), "Puzzle", "Action Figure", "Board Game", "Doll", "Remote Car"), IF(B28="Sports & Fitness", CHOOSE(RANDBETWEEN(1,5), "Treadmill", "Dumbbells", "Yoga Mat", "Bicycle", "Skipping Rope"), "Unknown")))))))))) -> Wireless Earbuds | D28: 712 | E28: LinkLine Wholesale
A29: P128 | B29: Books | C29: =IF(B29="Electronics", CHOOSE(RANDBETWEEN(1,5), "Smartphone", "Laptop", "Smartwatch", "Bluetooth Speaker", "Wireless Earbuds"), IF(B29="Clothing", CHOOSE(RANDBETWEEN(1,5), "T-shirt", "Jeans", "Jacket", "Hoodie", "Shorts"), IF(B29="Books", CHOOSE(RANDBETWEEN(1,5), "Novel", "Biography", "Comics", "Cookbook", "Textbook"), IF(B29="Footwear", CHOOSE(RANDBETWEEN(1,5), "Sneakers", "Sandals", "Boots", "Loafers", "Flip-flops"), IF(B29="Furniture", CHOOSE(RANDBETWEEN(1,5), "Chair", "Table", "Sofa", "Wardrobe", "Bed"), IF(B29="Home Appliances", CHOOSE(RANDBETWEEN(1,5), "Refrigerator", "Microwave", "Washing Machine", "Air Conditioner", "Vacuum Cleaner"), IF(B29="Beauty & Personal Care", CHOOSE(RANDBETWEEN(1,5), "Lipstick", "Moisturizer", "Perfume", "Shampoo", "Sunscreen"), IF(B29="Stationery", CHOOSE(RANDBETWEEN(1,5), "Pen", "Notebook", "Marker", "Stapler", "Eraser"), IF(B29="Toys & Games", CHOOSE(RANDBETWEEN(1,5), "Puzzle", "Action Figure", "Board Game", "Doll", "Remote Car"), IF(B29="Sports & Fitness", CHOOSE(RANDBETWEEN(1,5), "Treadmill", "Dumbbells", "Yoga Mat", "Bicycle", "Skipping Rope"), "Unknown")))))))))) -> Biography | D29: 126 | E29: Bright Line Traders
A30: P129 | B30: Toys & Games | C30: =IF(B30="Electronics", CHOOSE(RANDBETWEEN(1,5), "Smartphone", "Laptop", "Smartwatch", "Bluetooth Speaker", "Wireless Earbuds"), IF(B30="Clothing", CHOOSE(RANDBETWEEN(1,5), "T-shirt", "Jeans", "Jacket", "Hoodie", "Shorts"), IF(B30="Books", CHOOSE(RANDBETWEEN(1,5), "Novel", "Biography", "Comics", "Cookbook", "Textbook"), IF(B30="Footwear", CHOOSE(RANDBETWEEN(1,5), "Sneakers", "Sandals", "Boots", "Loafers", "Flip-flops"), IF(B30="Furniture", CHOOSE(RANDBETWEEN(1,5), "Chair", "Table", "Sofa", "Wardrobe", "Bed"), IF(B30="Home Appliances", CHOOSE(RANDBETWEEN(1,5), "Refrigerator", "Microwave", "Washing Machine", "Air Conditioner", "Vacuum Cleaner"), IF(B30="Beauty & Personal Care", CHOOSE(RANDBETWEEN(1,5), "Lipstick", "Moisturizer", "Perfume", "Shampoo", "Sunscreen"), IF(B30="Stationery", CHOOSE(RANDBETWEEN(1,5), "Pen", "Notebook", "Marker", "Stapler", "Eraser"), IF(B30="Toys & Games", CHOOSE(RANDBETWEEN(1,5), "Puzzle", "Action Figure", "Board Game", "Doll", "Remote Car"), IF(B30="Sports & Fitness", CHOOSE(RANDBETWEEN(1,5), "Treadmill", "Dumbbells", "Yoga Mat", "Bicycle", "Skipping Rope"), "Unknown")))))))))) -> Board Game | D30: 280 | E30: Daily Deals Distributors
A31: P130 | B31: Beauty & Personal Care | C31: Lipstick | D31: 695 | E31: NextGen Supply Co.
A32: P131 | B32: Toys & Games | C32: =IF(B32="Electronics", CHOOSE(RANDBETWEEN(1,5), "Smartphone", "Laptop", "Smartwatch", "Bluetooth Speaker", "Wireless Earbuds"), IF(B32="Clothing", CHOOSE(RANDBETWEEN(1,5), "T-shirt", "Jeans", "Jacket", "Hoodie", "Shorts"), IF(B32="Books", CHOOSE(RANDBETWEEN(1,5), "Novel", "Biography", "Comics", "Cookbook", "Textbook"), IF(B32="Footwear", CHOOSE(RANDBETWEEN(1,5), "Sneakers", "Sandals", "Boots", "Loafers", "Flip-flops"), IF(B32="Furniture", CHOOSE(RANDBETWEEN(1,5), "Chair", "Table", "Sofa", "Wardrobe", "Bed"), IF(B32="Home Appliances", CHOOSE(RANDBETWEEN(1,5), "Refrigerator", "Microwave", "Washing Machine", "Air Conditioner", "Vacuum Cleaner"), IF(B32="Beauty & Personal Care", CHOOSE(RANDBETWEEN(1,5), "Lipstick", "Moisturizer", "Perfume", "Shampoo", "Sunscreen"), IF(B32="Stationery", CHOOSE(RANDBETWEEN(1,5), "Pen", "Notebook", "Marker", "Stapler", "Eraser"), IF(B32="Toys & Games", CHOOSE(RANDBETWEEN(1,5), "Puzzle", "Action Figure", "Board Game", "Doll", "Remote Car"), IF(B32="Sports & Fitness", CHOOSE(RANDBETWEEN(1,5), "Treadmill", "Dumbbells", "Yoga Mat", "Bicycle", "Skipping Rope"), "Unknown")))))))))) -> Board Game | D32: 216 | E32: OmniMart Vendors
A33: P132 | B33: Electronics | C33: Laptop | D33: 540 | E33: NextGen Supply Co.
A34: P133 | B34: Electronics | C34: Bluetooth Speaker | D34: 181 | E34: Alpha Wholesalers
A35: P134 | B35: Sports & Fitness | C35: Treadmill | D35: 353 | E35: OmniMart Vendors
A36: P135 | B36: Clothing | C36: Men's Formal Shirt | D36: 226 | E36: CraftNova Supplies
A37: P136 | B37: Stationery | C37: Geometry Box | D37: 604 | E37: WareZone Retail
A38: P137 | B38: Beauty & Personal Care | C38: Body Lotion | D38: 97 | E38: Elite Traders Pvt. Ltd.
A39: P138 | B39: Furniture | C39: =IF(B39="Electronics", CHOOSE(RANDBETWEEN(1,5), "Smartphone", "Laptop", "Smartwatch", "Bluetooth Speaker", "Wireless Earbuds"), IF(B39="Clothing", CHOOSE(RANDBETWEEN(1,5), "T-shirt", "Jeans", "Jacket", "Hoodie", "Shorts"), IF(B39="Books", CHOOSE(RANDBETWEEN(1,5), "Novel", "Biography", "Comics", "Cookbook", "Textbook"), IF(B39="Footwear", CHOOSE(RANDBETWEEN(1,5), "Sneakers", "Sandals", "Boots", "Loafers", "Flip-flops"), IF(B39="Furniture", CHOOSE(RANDBETWEEN(1,5), "Chair", "Table", "Sofa", "Wardrobe", "Bed"), IF(B39="Home Appliances", CHOOSE(RANDBETWEEN(1,5), "Refrigerator", "Microwave", "Washing Machine", "Air Conditioner", "Vacuum Cleaner"), IF(B39="Beauty & Personal Care", CHOOSE(RANDBETWEEN(1,5), "Lipstick", "Moisturizer", "Perfume", "Shampoo", "Sunscreen"), IF(B39="Stationery", CHOOSE(RANDBETWEEN(1,5), "Pen", "Notebook", "Marker", "Stapler", "Eraser"), IF(B39="Toys & Games", CHOOSE(RANDBETWEEN(1,5), "Puzzle", "Action Figure", "Board Game", "Doll", "Remote Car"), IF(B39="Sports & Fitness", CHOOSE(RANDBETWEEN(1,5), "Treadmill", "Dumbbells", "Yoga Mat", "Bicycle", "Skipping Rope"), "Unknown")))))))))) -> Bed | D39: 465 | E39: Orion Home Supplies
A40: P139 | B40: Books | C40: Self-Help Book | D40: 637 | E40: EverFresh Supply Chain
A41: P140 | B41: Clothing | C41: =IF(B41="Electronics", CHOOSE(RANDBETWEEN(1,5), "Smartphone", "Laptop", "Smartwatch", "Bluetooth Speaker", "Wireless Earbuds"), IF(B41="Clothing", CHOOSE(RANDBETWEEN(1,5), "T-shirt", "Jeans", "Jacket", "Hoodie", "Shorts"), IF(B41="Books", CHOOSE(RANDBETWEEN(1,5), "Novel", "Biography", "Comics", "Cookbook", "Textbook"), IF(B41="Footwear", CHOOSE(RANDBETWEEN(1,5), "Sneakers", "Sandals", "Boots", "Loafers", "Flip-flops"), IF(B41="Furniture", CHOOSE(RANDBETWEEN(1,5), "Chair", "Table", "Sofa", "Wardrobe", "Bed"), IF(B41="Home Appliances", CHOOSE(RANDBETWEEN(1,5), "Refrigerator", "Microwave", "Washing Machine", "Air Conditioner", "Vacuum Cleaner"), IF(B41="Beauty & Personal Care", CHOOSE(RANDBETWEEN(1,5), "Lipstick", "Moisturizer", "Perfume", "Shampoo", "Sunscreen"), IF(B41="Stationery", CHOOSE(RANDBETWEEN(1,5), "Pen", "Notebook", "Marker", "Stapler", "Eraser"), IF(B41="Toys & Games", CHOOSE(RANDBETWEEN(1,5), "Puzzle", "Action Figure", "Board Game", "Doll", "Remote Car"), IF(B41="Sports & Fitness", CHOOSE(RANDBETWEEN(1,5), "Treadmill", "Dumbbells", "Yoga Mat", "Bicycle", "Skipping Rope"), "Unknown")))))))))) -> T-shirt | D41: 307 | E41: SmartChoice Suppliers
A42: P141 | B42: Beauty & Personal Care | C42: Face Wash | D42: 435 | E42: Nova Distributors
A43: P142 | B43: Stationery | C43: =IF(B43="Electronics", CHOOSE(RANDBETWEEN(1,5), "Smartphone", "Laptop", "Smartwatch", "Bluetooth Speaker", "Wireless Earbuds"), IF(B43="Clothing", CHOOSE(RANDBETWEEN(1,5), "T-shirt", "Jeans", "Jacket", "Hoodie", "Shorts"), IF(B43="Books", CHOOSE(RANDBETWEEN(1,5), "Novel", "Biography", "Comics", "Cookbook", "Textbook"), IF(B43="Footwear", CHOOSE(RANDBETWEEN(1,5), "Sneakers", "Sandals", "Boots", "Loafers", "Flip-flops"), IF(B43="Furniture", CHOOSE(RANDBETWEEN(1,5), "Chair", "Table", "Sofa", "Wardrobe", "Bed"), IF(B43="Home Appliances", CHOOSE(RANDBETWEEN(1,5), "Refrigerator", "Microwave", "Washing Machine", "Air Conditioner", "Vacuum Cleaner"), IF(B43="Beauty & Personal Care", CHOOSE(RANDBETWEEN(1,5), "Lipstick", "Moisturizer", "Perfume", "Shampoo", "Sunscreen"), IF(B43="Stationery", CHOOSE(RANDBETWEEN(1,5), "Pen", "Notebook", "Marker", "Stapler", "Eraser"), IF(B43="Toys & Games", CHOOSE(RANDBETWEEN(1,5), "Puzzle", "Action Figure", "Board Game", "Doll", "Remote Car"), IF(B43="Sports & Fitness", CHOOSE(RANDBETWEEN(1,5), "Treadmill", "Dumbbells", "Yoga Mat", "Bicycle", "Skipping Rope"), "Unknown")))))))))) -> Notebook | D43: 223 | E43: LinkLine Wholesale
A44: P143 | B44: Home Appliances | C44: =IF(B44="Electronics", CHOOSE(RANDBETWEEN(1,5), "Smartphone", "Laptop", "Smartwatch", "Bluetooth Speaker", "Wireless Earbuds"), IF(B44="Clothing", CHOOSE(RANDBETWEEN(1,5), "T-shirt", "Jeans", "Jacket", "Hoodie", "Shorts"), IF(B44="Books", CHOOSE(RANDBETWEEN(1,5), "Novel", "Biography", "Comics", "Cookbook", "Textbook"), IF(B44="Footwear", CHOOSE(RANDBETWEEN(1,5), "Sneakers", "Sandals", "Boots", "Loafers", "Flip-flops"), IF(B44="Furniture", CHOOSE(RANDBETWEEN(1,5), "Chair", "Table", "Sofa", "Wardrobe", "Bed"), IF(B44="Home Appliances", CHOOSE(RANDBETWEEN(1,5), "Refrigerator", "Microwave", "Washing Machine", "Air Conditioner", "Vacuum Cleaner"), IF(B44="Beauty & Personal Care", CHOOSE(RANDBETWEEN(1,5), "Lipstick", "Moisturizer", "Perfume", "Shampoo", "Sunscreen"), IF(B44="Stationery", CHOOSE(RANDBETWEEN(1,5), "Pen", "Notebook", "Marker", "Stapler", "Eraser"), IF(B44="Toys & Games", CHOOSE(RANDBETWEEN(1,5), "Puzzle", "Action Figure", "Board Game", "Doll", "Remote Car"), IF(B44="Sports & Fitness", CHOOSE(RANDBETWEEN(1,5), "Treadmill", "Dumbbells", "Yoga Mat", "Bicycle", "Skipping Rope"), "Unknown")))))))))) -> Air Conditioner | D44: 648 | E44: ProGear Supply Co.
A45: P144 | B45: Clothing | C45: =IF(B45="Electronics", CHOOSE(RANDBETWEEN(1,5), "Smartphone", "Laptop", "Smartwatch", "Bluetooth Speaker", "Wireless Earbuds"), IF(B45="Clothing", CHOOSE(RANDBETWEEN(1,5), "T-shirt", "Jeans", "Jacket", "Hoodie", "Shorts"), IF(B45="Books", CHOOSE(RANDBETWEEN(1,5), "Novel", "Biography", "Comics", "Cookbook", "Textbook"), IF(B45="Footwear", CHOOSE(RANDBETWEEN(1,5), "Sneakers", "Sandals", "Boots", "Loafers", "Flip-flops"), IF(B45="Furniture", CHOOSE(RANDBETWEEN(1,5), "Chair", "Table", "Sofa", "Wardrobe", "Bed"), IF(B45="Home Appliances", CHOOSE(RANDBETWEEN(1,5), "Refrigerator", "Microwave", "Washing Machine", "Air Conditioner", "Vacuum Cleaner"), IF(B45="Beauty & Personal Care", CHOOSE(RANDBETWEEN(1,5), "Lipstick", "Moisturizer", "Perfume", "Shampoo", "Sunscreen"), IF(B45="Stationery", CHOOSE(RANDBETWEEN(1,5), "Pen", "Notebook", "Marker", "Stapler", "Eraser"), IF(B45="Toys & Games", CHOOSE(RANDBETWEEN(1,5), "Puzzle", "Action Figure", "Board Game", "Doll", "Remote Car"), IF(B45="Sports & Fitness", CHOOSE(RANDBETWEEN(1,5), "Treadmill", "Dumbbells", "Yoga Mat", "Bicycle", "Skipping Rope"), "Unknown")))))))))) -> Hoodie | D45: 633 | E45: Spark Digital Distributors
A46: P145 | B46: Sports & Fitness | C46: =IF(B46="Electronics", CHOOSE(RANDBETWEEN(1,5), "Smartphone", "Laptop", "Smartwatch", "Bluetooth Speaker", "Wireless Earbuds"), IF(B46="Clothing", CHOOSE(RANDBETWEEN(1,5), "T-shirt", "Jeans", "Jacket", "Hoodie", "Shorts"), IF(B46="Books", CHOOSE(RANDBETWEEN(1,5), "Novel", "Biography", "Comics", "Cookbook", "Textbook"), IF(B46="Footwear", CHOOSE(RANDBETWEEN(1,5), "Sneakers", "Sandals", "Boots", "Loafers", "Flip-flops"), IF(B46="Furniture", CHOOSE(RANDBETWEEN(1,5), "Chair", "Table", "Sofa", "Wardrobe", "Bed"), IF(B46="Home Appliances", CHOOSE(RANDBETWEEN(1,5), "Refrigerator", "Microwave", "Washing Machine", "Air Conditioner", "Vacuum Cleaner"), IF(B46="Beauty & Personal Care", CHOOSE(RANDBETWEEN(1,5), "Lipstick", "Moisturizer", "Perfume", "Shampoo", "Sunscreen"), IF(B46="Stationery", CHOOSE(RANDBETWEEN(1,5), "Pen", "Notebook", "Marker", "Stapler", "Eraser"), IF(B46="Toys & Games", CHOOSE(RANDBETWEEN(1,5), "Puzzle", "Action Figure", "Board Game", "Doll", "Remote Car"), IF(B46="Sports & Fitness", CHOOSE(RANDBETWEEN(1,5), "Treadmill", "Dumbbells", "Yoga Mat", "Bicycle", "Skipping Rope"), "Unknown")))))))))) -> Treadmill | D46: 176 | E46: Horizon Goods Co.
A47: P146 | B47: Home Appliances | C47: =IF(B47="Electronics", CHOOSE(RANDBETWEEN(1,5), "Smartphone", "Laptop", "Smartwatch", "Bluetooth Speaker", "Wireless Earbuds"), IF(B47="Clothing", CHOOSE(RANDBETWEEN(1,5), "T-shirt", "Jeans", "Jacket", "Hoodie", "Shorts"), IF(B47="Books", CHOOSE(RANDBETWEEN(1,5), "Novel", "Biography", "Comics", "Cookbook", "Textbook"), IF(B47="Footwear", CHOOSE(RANDBETWEEN(1,5), "Sneakers", "Sandals", "Boots", "Loafers", "Flip-flops"), IF(B47="Furniture", CHOOSE(RANDBETWEEN(1,5), "Chair", "Table", "Sofa", "Wardrobe", "Bed"), IF(B47="Home Appliances", CHOOSE(RANDBETWEEN(1,5), "Refrigerator", "Microwave", "Washing Machine", "Air Conditioner", "Vacuum Cleaner"), IF(B47="Beauty & Personal Care", CHOOSE(RANDBETWEEN(1,5), "Lipstick", "Moisturizer", "Perfume", "Shampoo", "Sunscreen"), IF(B47="Stationery", CHOOSE(RANDBETWEEN(1,5), "Pen", "Notebook", "Marker", "Stapler", "Eraser"), IF(B47="Toys & Games", CHOOSE(RANDBETWEEN(1,5), "Puzzle", "Action Figure", "Board Game", "Doll", "Remote Car"), IF(B47="Sports & Fitness", CHOOSE(RANDBETWEEN(1,5), "Treadmill", "Dumbbells", "Yoga Mat", "Bicycle", "Skipping Rope"), "Unknown")))))))))) -> Microwave | D47: 495 | E47: MegaMart Traders
A48: P147 | B48: Toys & Games | C48: =IF(B48="Electronics", CHOOSE(RANDBETWEEN(1,5), "Smartphone", "Laptop", "Smartwatch", "Bluetooth Speaker", "Wireless Earbuds"), IF(B48="Clothing", CHOOSE(RANDBETWEEN(1,5), "T-shirt", "Jeans", "Jacket", "Hoodie", "Shorts"), IF(B48="Books", CHOOSE(RANDBETWEEN(1,5), "Novel", "Biography", "Comics", "Cookbook", "Textbook"), IF(B48="Footwear", CHOOSE(RANDBETWEEN(1,5), "Sneakers", "Sandals", "Boots", "Loafers", "Flip-flops"), IF(B48="Furniture", CHOOSE(RANDBETWEEN(1,5), "Chair", "Table", "Sofa", "Wardrobe", "Bed"), IF(B48="Home Appliances", CHOOSE(RANDBETWEEN(1,5), "Refrigerator", "Microwave", "Washing Machine", "Air Conditioner", "Vacuum Cleaner"), IF(B48="Beauty & Personal Care", CHOOSE(RANDBETWEEN(1,5), "Lipstick", "Moisturizer", "Perfume", "Shampoo", "Sunscreen"), IF(B48="Stationery", CHOOSE(RANDBETWEEN(1,5), "Pen", "Notebook", "Marker", "Stapler", "Eraser"), IF(B48="Toys & Games", CHOOSE(RANDBETWEEN(1,5), "Puzzle", "Action Figure", "Board Game", "Doll", "Remote Car"), IF(B48="Sports & Fitness", CHOOSE(RANDBETWEEN(1,5), "Treadmill", "Dumbbells", "Yoga Mat", "Bicycle", "Skipping Rope"), "Unknown")))))))))) -> Puzzle | D48: 123 | E48: MegaMart Traders
A49: P148 | B49: Furniture | C49: Study Table | D49: 457 | E49: QuickKart Distributors
A50: P149 | B50: Furniture | C50: =IF(B50="Electronics", CHOOSE(RANDBETWEEN(1,5), "Smartphone", "Laptop", "Smartwatch", "Bluetooth Speaker", "Wireless Earbuds"), IF(B50="Clothing", CHOOSE(RANDBETWEEN(1,5), "T-shirt", "Jeans", "Jacket", "Hoodie", "Shorts"), IF(B50="Books", CHOOSE(RANDBETWEEN(1,5), "Novel", "Biography", "Comics", "Cookbook", "Textbook"), IF(B50="Footwear", CHOOSE(RANDBETWEEN(1,5), "Sneakers", "Sandals", "Boots", "Loafers", "Flip-flops"), IF(B50="Furniture", CHOOSE(RANDBETWEEN(1,5), "Chair", "Table", "Sofa", "Wardrobe", "Bed"), IF(B50="Home Appliances", CHOOSE(RANDBETWEEN(1,5), "Refrigerator", "Microwave", "Washing Machine", "Air Conditioner", "Vacuum Cleaner"), IF(B50="Beauty & Personal Care", CHOOSE(RANDBETWEEN(1,5), "Lipstick", "Moisturizer", "Perfume", "Shampoo", "Sunscreen"), IF(B50="Stationery", CHOOSE(RANDBETWEEN(1,5), "Pen", "Notebook", "Marker", "Stapler", "Eraser"), IF(B50="Toys & Games", CHOOSE(RANDBETWEEN(1,5), "Puzzle", "Action Figure", "Board Game", "Doll", "Remote Car"), IF(B50="Sports & Fitness", CHOOSE(RANDBETWEEN(1,5), "Treadmill", "Dumbbells", "Yoga Mat", "Bicycle", "Skipping Rope"), "Unknown")))))))))) -> Chair | D50: 668 | E50: NextGen Supply Co.
A51: P150 | B51: Books | C51: Children's Storybook | D51: 265 | E51: HexaMart Supplies

Sheet Customer_Clean_Table
A1: Customer ID | B1: Name | C1: Gender | D1: Location | E1: Email | F1: Rating | G1: Attribute | H1: Order_id
A2: C001 | B2: Flo Masser | C2: Female | D2: Visakhapatnam | E2: raj.rao@example.com | F2: 8.9 | G2: Purchase History 1 | H2: O2970
A3: C002 | B3: Tarra Sey | C3: Female | D3: Coimbatore | E3: nikhil.nair@example.com | F3: 8.5 | G3: Purchase History 1 | H3: O2732
A4: C002 | B4: Tarra Sey | C4: Female | D4: Coimbatore | E4: nikhil.nair@example.com | F4: 8.5 | G4: Purchase History 2 | H4: O2451
A5: C002 | B5: Tarra Sey | C5: Female | D5: Coimbatore | E5: nikhil.nair@example.com | F5: 8.5 | G5: Purchase History 3 | H5: O2843
A6: C003 | B6: Lynnette Dinesen | C6: Female | D6: Bhopal | E6: tara.menon@example.com | F6: 9.5 | G6: Purchase History 1 | H6: O2124
A7: C004 | B7: Lucais Poulney | C7: Male | D7: Bhopal | E7: aadhya.reddy@example.com | F7: 6.1 | G7: Purchase History 1 | H7: O2268
A8: C004 | B8: Lucais Poulney | C8: Male | D8: Bhopal | E8: aadhya.reddy@example.com | F8: 6.1 | G8: Purchase History 2 | H8: O2472
A9: C005 | B9: Nealy Redborn | C9: Male | D9: Lucknow | E9: diya.iyer@example.com | F9: 6.5 | G9: Purchase History 1 | H9: O2748
A10: C005 | B10: Nealy Redborn | C10: Male | D10: Lucknow | E10: diya.iyer@example.com | F10: 6.5 | G10: Purchase History 2 | H10: O2799 | K10: Gender | L10: COD | M10: EMI | N10: Debit | O10: Credit | P10: Total
A11: C006 | B11: Justis Antoni | C11: Male | D11: Hyderabad | E11: myra.kumar@example.com | F11: 8.2 | G11: Purchase History 1 | H11: O2683 | K11: Male | L11: =COUNTIFS(C:C,"Male",Sales_Table!H:H,"COD") -> 131 | M11: =COUNTIFS(C:C,"Male",Sales_Table!H:H,"EMI") -> 105 | N11: =COUNTIFS(C:C,"Male",Sales_Table!H:H,"Debit") -> 118 | O11: =COUNTIFS(C:C,"Male",Sales_Table!H:H,"Credit") -> 110 | P11: =SUM(L11:O11) -> 464
A12: C006 | B12: Justis Antoni | C12: Male | D12: Hyderabad | E12: myra.kumar@example.com | F12: 8.2 | G12: Purchase History 2 | H12: O2896 | K12: Female | L12: =COUNTIFS(C:C,"Female",Sales_Table!H:H,"COD") -> 153 | M12: =COUNTIFS(C:C,"Female",Sales_Table!H:H,"EMI") -> 140 | N12: =COUNTIFS(C:C,"Female",Sales_Table!H:H,"DEBIT") -> 144 | O12: =COUNTIFS(C:C,"Female",Sales_Table!H:H,"Credit") -> 99 | P12: =SUM(L12:O12) -> 536
A13: C006 | B13: Justis Antoni | C13: Male | D13: Hyderabad | E13: myra.kumar@example.com | F13: 8.2 | G13: Purchase History 3 | H13: O2392
A14: C006 | B14: Justis Antoni | C14: Male | D14: Hyderabad | E14: myra.kumar@example.com | F14: 8.2 | G14: Purchase History 4 | H14: O2246
A15: C007 | B15: Reine Divis | C15: Female | D15: Patna | E15: krishna.joshi@example.com | F15: 8.3 | G15: Purchase History 1 | H15: O2648
A16: C007 | B16: Reine Divis | C16: Female | D16: Patna | E16: krishna.joshi@example.com | F16: 8.3 | G16: Purchase History 2 | H16: O2354
A17: C007 | B17: Reine Divis | C17: Female | D17: Patna | E17: krishna.joshi@example.com | F17: 8.3 | G17: Purchase History 3 | H17: O2009
A18: C008 | B18: Hilary Northedge | C18: Male | D18: Pune | E18: aadhya.reddy@example.com | F18: 8.1 | G18: Purchase History 1 | H18: O2398
A19: C009 | B19: Natividad Damant | C19: Female | D19: Bengaluru | E19: ishaan.kumar@example.com | F19: 5.1 | G19: Purchase History 1 | H19: O2028
A20: C009 | B20: Natividad Damant | C20: Female | D20: Bengaluru | E20: ishaan.kumar@example.com | F20: 5.1 | G20: Purchase History 2 | H20: O2645
A21: C009 | B21: Natividad Damant | C21: Female | D21: Bengaluru | E21: ishaan.kumar@example.com | F21: 5.1 | G21: Purchase History 3 | H21: O2092
A22: C009 | B22: Natividad Damant | C22: Female | D22: Bengaluru | E22: ishaan.kumar@example.com | F22: 5.1 | G22: Purchase History 4 | H22: O2773
A23: C010 | B23: Barry Dysert | C23: Female | D23: Vadodara | E23: vivaan.joshi@example.com | F23: 8.3 | G23: Purchase History 1 | H23: O2737
A24: C011 | B24: Sonia Ferrar | C24: Female | D24: Mumbai | E24: kabir.gupta@example.com | F24: 7.7 | G24: Purchase History 1 | H24: O2619
... A1001: C401 | B1001: Margit Crickmer | C1001: Female | D1001: Delhi | E1001: aadhya.sharma@example.com | F1001: 6.6 | G1001: Purchase History 1 | H1001: O2141

Sheet Customer_Table
A1: Customer ID | B1: Name | C1: Gender | D1: Location | E1: Email | F1: Purchase History 1 | G1: Purchase History 2 | H1: Purchase History 3 | I1: Purchase History 4 | J1: Rating | N1: Order idPu
A2: C001 | B2: Flo Masser | C2: Female | D2: Visakhapatnam | E2: raj.rao@example.com | F2: O2970 | J2: =RANDBETWEEN(55,100)/10 -> 6.9 | N2: O2970
A3: C002 | B3: Tarra Sey | C3: Female | D3: Coimbatore | E3: nikhil.nair@example.com | F3: O2732 | G3: O2451 | H3: O2843 | J3: =RANDBETWEEN(45,100)/10 -> 6.7 | N3: O2732 O2451 O2843
A4: C003 | B4: Lynnette Dinesen | C4: Female | D4: Bhopal | E4: tara.menon@example.com | F4: O2124 | J4: =RANDBETWEEN(45,100)/10 -> 7.2 | N4: O2124
A5: C004 | B5: Lucais Poulney | C5: Male | D5: Bhopal | E5: aadhya.reddy@example.com | F5: O2268 | G5: O2472 | J5: =RANDBETWEEN(45,100)/10 -> 9.4 | N5: O2268 O2472
A6: C005 | B6: Nealy Redborn | C6: Male | D6: Lucknow | E6: diya.iyer@example.com | F6: O2748 | G6: O2799 | J6: =RANDBETWEEN(45,100)/10 -> 5.1 | N6: O2748 O2799
A7: C006 | B7: Justis Antoni | C7: Male | D7: Hyderabad | E7: myra.kumar@example.com | F7: O2683 | G7: O2896 | H7: O2392 | I7: O2246 | J7: =RANDBETWEEN(45,100)/10 -> 8.1 | N7: O2683 O2896 O2392 O2246
A8: C007 | B8: Reine Divis | C8: Female | D8: Patna | E8: krishna.joshi@example.com | F8: O2648 | G8: O2354 | H8: O2009 | J8: =RANDBETWEEN(45,100)/10 -> 7.8 | N8: O2648 O2354 O2009
A9: C008 | B9: Hilary Northedge | C9: Male | D9: Pune | E9: aadhya.reddy@example.com | F9: O2398 | J9: =RANDBETWEEN(45,100)/10 -> 5.6 | N9: O2398
A10: C009 | B10: Natividad Damant | C10: Female | D10: Bengaluru | E10: ishaan.kumar@example.com | F10: O2028 | G10: O2645 | H10: O2092 | I10: O2773 | J10: =RANDBETWEEN(45,100)/10 -> 9.7 | N10: O2028 O2645 O2092 O2773
A11: C010 | B11: Barry Dysert | C11: Female | D11: Vadodara | E11: vivaan.joshi@example.com | F11: O2737 | J11: =RANDBETWEEN(45,100)/10 -> 5.9 | N11: O2737
A12: C011 | B12: Sonia Ferrar | C12: Female | D12: Mumbai | E12: kabir.gupta@example.com | F12: O2619 | G12: O2296 | J12: =RANDBETWEEN(45,100)/10 -> 10 | N12: O2619 O2296
A13: C012 | B13: Ninnette Stoller | C13: Female | D13: Kolkata | E13: riya.chopra@example.com | F13: O2085 | G13: O2833 | H13: O2818 | I13: O2608 | J13: =RANDBETWEEN(45,100)/10 -> 4.5 | N13: O2085 O2833 O2818 O2608
A14: C013 | B14: Dall Hoogendorp | C14: Male | D14: Kolkata | E14: raj.nair@example.com | F14: O2724 | G14: O2993 | H14: O2801 | J14: =RANDBETWEEN(45,100)/10 -> 5.9 | N14: O2724 O2993 O2801
A15: C014 | B15: Xaviera Blacker | C15: Female | D15: Mumbai | E15: aadhya.das@example.com | F15: O2726 | G15: O2980 | H15: O2046 | I15: O2165 | J15: =RANDBETWEEN(45,100)/10 -> 9.4 | N15: O2726 O2980 O2046 O2165
A16: C015 | B16: Lavinie Kimbly | C16: Female | D16: Pune | E16: neha.sharma@example.com | F16: O2001 | G16: O2731 | H16: O2041 | J16: =RANDBETWEEN(45,100)/10 -> 7.4 | N16: O2001 O2731 O2041
A17: C016 | B17: Anderea Ovitts | C17: Female | D17: Pune | E17: ira.reddy@example.com | F17: O2528 | G17: O2512 | J17: =RANDBETWEEN(45,100)/10 -> 7.6 | N17: O2528 O2512
A18: C017 | B18: Amelia Elldred | C18: Female | D18: Visakhapatnam | E18: meera.chopra@example.com | F18: O2949 | G18: O2907 | H18: O2181 | J18: =RANDBETWEEN(45,100)/10 -> 4.5 | N18: O2949 O2907 O2181
A19: C018 | B19: Carey Collyer | C19: Male | D19: Coimbatore | E19: ishaan.patel@example.com | F19: O2207 | J19: =RANDBETWEEN(45,100)/10 -> 9.5 | N19: O2207
A20: C019 | B20: Gratia Hardway | C20: Female | D20: Mumbai | E20: tara.verma@example.com | F20: O2564 | G20: O2395 | H20: O2086 | I20: O2432 | J20: =RANDBETWEEN(45,100)/10 -> 6.2 | N20: O2564 O2395 O2086 O2432
A21: C020 | B21: Dirk Charnick | C21: Male | D21: Coimbatore | E21: nikhil.mishra@example.com | F21: O2210 | J21: =RANDBETWEEN(45,100)/10 -> 8.6 | N21: O2210
A22: C021 | B22: Rayshell Ludford | C22: Female | D22: Visakhapatnam | E22: anaya.malhotra@example.com | F22: O2096 | G22: O2524 | J22: =RANDBETWEEN(45,100)/10 -> 8.7 | N22: O2096 O2524
A23: C022 | B23: Brinn Huggan | C23: Female | D23: Jaipur | E23: kavya.menon@example.com | F23: O2289 | G23: O2563 | J23: =RANDBETWEEN(45,100)/10 -> 8.4 | N23: O2289 O2563
A24: C023 | B24: Leesa Bussey | C24: Female | D24: Vadodara | E24: kabir.malhotra@example.com | F24: O2434 | J24: =RANDBETWEEN(45,100)/10 -> 7.3 | N24: O2434
A25: C024 | B25: Derron Parkes | C25: Male | D25: Kolkata | E25: myra.reddy@example.com | F25: O2387 | G25: O2453 | H25: O2172 | J25: =RANDBETWEEN(45,100)/10 -> 5 | N25: O2387 O2453 O2172
A26: C025 | B26: Camila Blazey | C26: Female | D26: Ludhiana | E26: tara.joshi@example.com | F26: O2323 | G26: O2047 | H26: O2873 | J26: =RANDBETWEEN(45,100)/10 -> 9 | N26: O2323 O2047 O2873
A27: C026 | B27: Marcelo Hedditeh | C27: Male | D27: Mumbai | E27: aditya.kapoor@example.com | F27: O2513 | G27: O2448 | H27: O2554 | I27: O2891 | J27: =RANDBETWEEN(45,100)/10 -> 5.9 | N27: O2513 O2448 O2554 O2891
A28: C027 | B28: Brenden Pauler | C28: Male | D28: Delhi | E28: tara.agarwal@example.com | F28: O2649 | J28: =RANDBETWEEN(45,100)/10 -> 9.5 | N28: O2649
A29: C028 | B29: Jodie Ayscough | C29: Male | D29: Ludhiana | E29: tara.das@example.com | F29: O2902 | G29: O2706 | H29: O2820 | I29: O2539 | J29: =RANDBETWEEN(45,100)/10 -> 4.6 | N29: O2902 O2706 O2820 O2539
A30: C029 | B30: Loella Conachy | C30: Female | D30: Coimbatore | E30: meera.mishra@example.com | F30: O2668 | J30: =RANDBETWEEN(45,100)/10 -> 4.7 | N30: O2668
A31: C030 | B31: Caresa Gresch | C31: Female | D31: Bhopal | E31: aditya.sharma@example.com | F31: O2300 | G31: O2757 | J31: =RANDBETWEEN(45,100)/10 -> 8.5 | N31: O2300 O2757
A32: C031 | B32: Trevor Logsdail | C32: Male | D32: Kolkata | E32: riya.iyer@example.com | F32: O2391 | J32: =RANDBETWEEN(45,100)/10 -> 8.3 | N32: O2391
A33: C032 | B33: Dougy Connew | C33: Male | D33: Nagpur | E33: krishna.kapoor@example.com | F33: O2056 | G33: O2100 | H33: O2462 | I33: O2163 | J33: =RANDBETWEEN(45,100)/10 -> 8.4 | N33: O2056 O2100 O2462 O2163
A34: C033 | B34: Deni Enterlein | C34: Female | D34: Mumbai | E34: nikhil.reddy@example.com | F34: O2461 | G34: O2985 | H34: O2883 | I34: O2267 | J34: =RANDBETWEEN(45,100)/10 -> 4.9 | N34: O2461 O2985 O2883 O2267
A35: C034 | B35: Lonnard Apted | C35: Male | D35: Vadodara | E35: nikhil.singh@example.com | F35: O2879 | G35: O2326 | H35: O2831 | J35: =RANDBETWEEN(45,100)/10 -> 6.8 | N35: O2879 O2326 O2831
A36: C035 | B36: Nicky Evelyn | C36: Female | D36: Ludhiana | E36: anaya.chopra@example.com | F36: O2688 | G36: O2503 | J36: =RANDBETWEEN(45,100)/10 -> 9 | N36: O2688 O2503
A37: C036 | B37: Chevy Ruzek | C37: Male | D37: Ahmedabad | E37: ishaan.bhat@example.com | F37: O2191 | G37: O2646 | H37: O2630 | I37: O2367 | J37: =RANDBETWEEN(45,100)/10 -> 8.3 | N37: O2191 O2646 O2630 O2367
A38: C037 | B38: Bea Treadgall | C38: Female | D38: Nagpur | E38: aarav.singh@example.com | F38: O2017 | G38: O2483 | H38: O2545 | I38: O2742 | J38: =RANDBETWEEN(45,100)/10 -> 7.3 | N38: O2017 O2483 O2545 O2742
A39: C038 | B39: Lila Sparham | C39: Female | D39: Mumbai | E39: saanvi.malhotra@example.com | F39: O2306 | G39: O2624 | H39: O2607 | J39: =RANDBETWEEN(45,100)/10 -> 7 | N39: O2306 O2624 O2607
A40: C039 | B40: Goldina Bowra | C40: Female | D40: Jaipur | E40: aryan.gupta@example.com | F40: O2940 | G40: O2759 | H40: O2081 | J40: =RANDBETWEEN(45,100)/10 -> 5.8 | N40: O2940 O2759 O2081
A41: C040 | B41: Stephanie Arrol | C41: Female | D41: Pune | E41: tara.das@example.com | F41: O2575 | G41: O2479 | H41: O2599 | J41: =RANDBETWEEN(45,100)/10 -> 7.7 | N41: O2575 O2479 O2599
A42: C041 | B42: Cobb Vanezis | C42: Male | D42: Nagpur | E42: myra.singh@example.com | F42: O2852 | G42: O2373 | H42: O2890 | J42: =RANDBETWEEN(45,100)/10 -> 6 | N42: O2852 O2373 O2890
A43: C042 | B43: Stefan Ponsford | C43: Male | D43: Kanpur | E43: saanvi.mishra@example.com | F43: O2854 | G43: O2988 | H43: O2211 | J43: =RANDBETWEEN(45,100)/10 -> 5.2 | N43: O2854 O2988 O2211
A44: C043 | B44: Wilmette Chillingworth | C44: Female | D44: Ahmedabad | E44: raj.verma@example.com | F44: O2355 | J44: =RANDBETWEEN(45,100)/10 -> 7.2 | N44: O2355
A45: C044 | B45: Shawn Ziehms | C45: Male | D45: Kolkata | E45: riya.joshi@example.com | F45: O2860 | G45: O2673 | H45: O2586 | I45: O2161 | J45: =RANDBETWEEN(45,100)/10 -> 10 | N45: O2860 O2673 O2586 O2161
A46: C045 | B46: Melissa Marklow | C46: Female | D46: Kolkata | E46: kabir.patel@example.com | F46: O2661 | G46: O2826 | J46: =RANDBETWEEN(45,100)/10 -> 10 | N46: O2661 O2826
A47: C046 | B47: Thatcher Jurgenson | C47: Male | D47: Jaipur | E47: anaya.iyer@example.com | F47: O2827 | G47: O2042 | J47: =RANDBETWEEN(45,100)/10 -> 8.9 | N47: O2827 O2042
A48: C047 | B48: Heidie Denholm | C48: Female | D48: Hyderabad | E48: saanvi.iyer@example.com | F48: O2158 | G48: O2715 | H48: O2782 | J48: =RANDBETWEEN(45,100)/10 -> 9.2 | N48: O2158 O2715 O2782
A49: C048 | B49: Madelene Bedinn | C49: Female | D49: Kanpur | E49: diya.menon@example.com | F49: O2245 | J49: =RANDBETWEEN(45,100)/10 -> 6.6 | N49: O2245
A50: C049 | B50: Lisette Wrist | C50: Female | D50: Bhopal | E50: kavya.agarwal@example.com | F50: O2968 | G50: O2260 | J50: =RANDBETWEEN(45,100)/10 -> 5.3 | N50: O2968 O2260
A51: C050 | B51: Archaimbaud Reaney | C51: Male | D51: Chennai | E51: kabir.menon@example.com | F51: O2348 | G51: O2235 | J51: =RANDBETWEEN(45,100)/10 -> 4.6 | N51: O2348 O2235
A52: C051 | B52: Shoshana Pettie | C52: Female | D52: Nagpur | E52: diya.sharma@example.com | F52: O2928 | G52: O2370 | H52: O2871 | I52: O2596 | J52: =RANDBETWEEN(45,100)/10 -> 5 | N52: O2928 O2370 O2871 O2596
A53: C052 | B53: Raymund Fronsek | C53: Male | D53: Visakhapatnam | E53: anaya.gupta@example.com | F53: O2116 | G53: O2438 | H53: O2230 | J53: =RANDBETWEEN(45,100)/10 -> 7.7 | N53: O2116 O2438 O2230
A54: C053 | B54: Elisabet Glendenning | C54: Female | D54: Mumbai | E54: saanvi.reddy@example.com | F54: O2816 | G54: O2663 | H54: O2814 | J54: =RANDBETWEEN(45,100)/10 -> 9.3 | N54: O2816 O2663 O2814
A55: C054 | B55: Zebadiah Doley | C55: Male | D55: Visakhapatnam | E55: aditya.menon@example.com | F55: O2450 | G55: O2974 | H55: O2029 | J55: =RANDBETWEEN(45,100)/10 -> 6 | N55: O2450 O2974 O2029
A56: C055 | B56: Tallulah Gadsby | C56: Female | D56: Ahmedabad | E56: vivaan.menon@example.com | F56: O2189 | G56: O2904 | J56: =RANDBETWEEN(45,100)/10 -> 7.8 | N56: O2189 O2904
A57: C056 | B57: Teddi Anfusso | C57: Female | D57: Patna | E57: aryan.rao@example.com | F57: O2102 | J57: =RANDBETWEEN(45,100)/10 -> 9.1 | N57: O2102
A58: C057 | B58: Hinda Boother | C58: Female | D58: Ludhiana | E58: myra.menon@example.com | F58: O2798 | G58: O2791 | J58: =RANDBETWEEN(45,100)/10 -> 6.4 | N58: O2798 O2791
A59: C058 | B59: Reinald Kynan | C59: Male | D59: Pune | E59: tara.chopra@example.com | F59: O2540 | G59: O2735 | H59: O2913 | J59: =RANDBETWEEN(45,100)/10 -> 7.2 | N59: O2540 O2735 O2913
A60: C059 | B60: Car Trelease | C60: Male | D60: Bengaluru | E60: aadhya.singh@example.com | F60: O2825 | G60: O2180 | J60: =RANDBETWEEN(45,100)/10 -> 8.5 | N60: O2825 O2180
A61: C060 | B61: Giselbert Havard | C61: Male | D61: Visakhapatnam | E61: neha.iyer@example.com | F61: O2795 | G61: O2021 | J61: =RANDBETWEEN(45,100)/10 -> 7.5 | N61: O2795 O2021
A62: C061 | B62: Kathe Alessandrucci | C62: Female | D62: Kanpur | E62: raj.malhotra@example.com | F62: O2989 | G62: O2802 | J62: =RANDBETWEEN(45,100)/10 -> 8.1 | N62: O2989 O2802
A63: C062 | B63: Reidar Gaine | C63: Male | D63: Coimbatore | E63: aarav.bhat@example.com | F63: O2692 | G63: O2316 | H63: O2084 | J63: =RANDBETWEEN(45,100)/10 -> 6.6 | N63: O2692 O2316 O2084
A64: C063 | B64: Modesty Kimmings | C64: Female | D64: Visakhapatnam | E64: saanvi.kumar@example.com | F64: O2889 | G64: O2772 | H64: O2059 | J64: =RANDBETWEEN(45,100)/10 -> 8.1 | N64: O2889 O2772 O2059
A65: C064 | B65: Abagael Barnsdall | C65: Female | D65: Patna | E65: nikhil.chopra@example.com | F65: O2285 | G65: O2241 | H65: O2711 | I65: O2437 | J65: =RANDBETWEEN(45,100)/10 -> 4.6 | N65: O2285 O2241 O2711 O2437
A66: C065 | B66: Lilli Cortese | C66: Female | D66: Jaipur | E66: kavya.patel@example.com | F66: O2061 | G66: O2131 | J66: =RANDBETWEEN(45,100)/10 -> 5.1 | N66: O2061 O2131
A67: C066 | B67: Barbee Pessolt | C67: Female | D67: Patna | E67: meera.chopra@example.com | F67: O2755 | J67: =RANDBETWEEN(45,100)/10 -> 4.9 | N67: O2755
A68: C067 | B68: Jan Wren | C68: Male | D68: Coimbatore | E68: riya.sharma@example.com | F68: O2231 | G68: O2171 | H68: O2357 | J68: =RANDBETWEEN(45,100)/10 -> 7.8 | N68: O2231 O2171 O2357
A69: C068 | B69: Carie Ottawell | C69: Female | D69: Bengaluru | E69: raj.kapoor@example.com | F69: O2468 | G69: O2546 | H69: O2359 | I69: O2111 | J69: =RANDBETWEEN(45,100)/10 -> 8.8 | N69: O2468 O2546 O2359 O2111
A70: C069 | B70: Collete Fedorski | C70: Female | D70: Kolkata | E70: krishna.singh@example.com | F70: O2651 | G70: O2848 | H70: O2271 | I70: O2331 | J70: =RANDBETWEEN(45,100)/10 -> 8.2 | N70: O2651 O2848 O2271 O2331
A71: C070 | B71: Kevyn Woodham | C71: Female | D71: Surat | E71: krishna.nair@example.com | F71: O2849 | G71: O2167 | H71: O2166 | J71: =RANDBETWEEN(45,100)/10 -> 7.6 | N71: O2849 O2167 O2166
A72: C071 | B72: Jermain Kittman | C72: Male | D72: Lucknow | E72: nikhil.bhat@example.com | F72: O2666 | G72: O2014 | J72: =RANDBETWEEN(45,100)/10 -> 8.1 | N72: O2666 O2014
A73: C072 | B73: Andy Kerswill | C73: Female | D73: Hyderabad | E73: ishaan.reddy@example.com | F73: O2681 | G73: O2942 | H73: O2811 | I73: O2943 | J73: =RANDBETWEEN(45,100)/10 -> 6.6 | N73: O2681 O2942 O2811 O2943
A74: C073 | B74: Stormie Medgwick | C74: Female | D74: Bhopal | E74: neha.jain@example.com | F74: O2616 | G74: O2224 | H74: O2774 | I74: O2606 | J74: =RANDBETWEEN(45,100)/10 -> 10 | N74: O2616 O2224 O2774 O2606
A75: C074 | B75: Brand Stapells | C75: Male | D75: Coimbatore | E75: meera.kumar@example.com | F75: O2632 | G75: O2179 | H75: O2643 | I75: O2228 | J75: =RANDBETWEEN(45,100)/10 -> 8.7 | N75: O2632 O2179 O2643 O2228
A76: C075 | B76: Florian Speeks | C76: Male | D76: Mumbai | E76: ishaan.das@example.com | F76: O2946 | G76: O2944 | H76: O2386 | I76: O2923 | J76: =RANDBETWEEN(45,100)/10 -> 7.9 | N76: O2946 O2944 O2386 O2923
A77: C076 | B77: Gusti Deely | C77: Female | D77: Coimbatore | E77: saanvi.singh@example.com | F77: O2912 | G77: O2464 | J77: =RANDBETWEEN(45,100)/10 -> 5.8 | N77: O2912 O2464
A78: C077 | B78: Sharia Gomersal | C78: Female | D78: Indore | E78: anaya.jain@example.com | F78: O2071 | G78: O2840 | J78: =RANDBETWEEN(45,100)/10 -> 6.3 | N78: O2071 O2840
A79: C078 | B79: Frieda Adame | C79: Female | D79: Delhi | E79: anaya.malhotra@example.com | F79: O2577 | G79: O2910 | J79: =RANDBETWEEN(45,100)/10 -> 9.2 | N79: O2577 O2910
A80: C079 | B80: Staford Elvin | C80: Male | D80: Surat | E80: aditya.menon@example.com | F80: O2134 | G80: O2809 | J80: =RANDBETWEEN(45,100)/10 -> 7.3 | N80: O2134 O2809
A81: C080 | B81: Chandler Algie | C81: Male | D81: Vadodara | E81: anaya.sharma@example.com | F81: O2595 | J81: =RANDBETWEEN(45,100)/10 -> 9.9 | N81: O2595
A82: C081 | B82: Pippa Spindler | C82: Female | D82: Mumbai | E82: ishaan.kapoor@example.com | F82: O2522 | G82: O2308 | H82: O2703 | J82: =RANDBETWEEN(45,100)/10 -> 9.5 | N82: O2522 O2308 O2703
A83: C082 | B83: Galen Hemmingway | C83: Male | D83: Ahmedabad | E83: krishna.kapoor@example.com | F83: O2493 | G83: O2229 | H83: O2315 | I83: O2589 | J83: =RANDBETWEEN(45,100)/10 -> 6.2 | N83: O2493 O2229 O2315 O2589
A84: C083 | B84: Rebeka Tolussi | C84: Female | D84: Kolkata | E84: kabir.kumar@example.com | F84: O2008 | G84: O2251 | H84: O2227 | I84: O2976 | J84: =RANDBETWEEN(45,100)/10 -> 8.8 | N84: O2008 O2251 O2227 O2976
A85: C084 | B85: Ulrika Jahns | C85: Female | D85: Visakhapatnam | E85: vivaan.nair@example.com | F85: O2729 | J85: =RANDBETWEEN(45,100)/10 -> 9.6 | N85: O2729
A86: C085 | B86: Tyler Dmych | C86: Male | D86: Coimbatore | E86: ishaan.bhat@example.com | F86: O2847 | G86: O2627 | H86: O2785 | J86: =RANDBETWEEN(45,100)/10 -> 5.6 | N86: O2847 O2627 O2785
A87: C086 | B87: Gabbey Brinkman | C87: Female | D87: Indore | E87: neha.jain@example.com | F87: O2702 | J87: =RANDBETWEEN(45,100)/10 -> 5.5 | N87: O2702
A88: C087 | B88: Ardath Mattiazzi | C88: Female | D88: Lucknow | E88: anaya.reddy@example.com | F88: O2828 | G88: O2447 | J88: =RANDBETWEEN(45,100)/10 -> 5 | N88: O2828 O2447
A89: C088 | B89: Padriac Buckell | C89: Male | D89: Delhi | E89: aarav.iyer@example.com | F89: O2456 | G89: O2341 | H89: O2144 | I89: O2829 | J89: =RANDBETWEEN(45,100)/10 -> 8.7 | N89: O2456 O2341 O2144 O2829
A90: C089 | B90: Ettore Grebert | C90: Male | D90: Kanpur | E90: ishaan.bhat@example.com | F90: O2662 | J90: =RANDBETWEEN(45,100)/10 -> 7.2 | N90: O2662
A91: C090 | B91: Margy Spehr | C91: Female | D91: Surat | E91: meera.das@example.com | F91: O2040 | G91: O2567 | H91: O2900 | J91: =RANDBETWEEN(45,100)/10 -> 6.9 | N91: O2040 O2567 O2900
A92: C091 | B92: Ulrica Laurie | C92: Female | D92: Indore | E92: meera.mishra@example.com | F92: O2402 | G92: O2374 | J92: =RANDBETWEEN(45,100)/10 -> 6.8 | N92: O2402 O2374
A93: C092 | B93: Silas Kigelman | C93: Male | D93: Coimbatore | E93: riya.gupta@example.com | F93: O2206 | G93: O2389 | H93: O2558 | J93: =RANDBETWEEN(45,100)/10 -> 8.9 | N93: O2206 O2389 O2558
A94: C093 | B94: Flin Strond | C94: Male | D94: Indore | E94: riya.verma@example.com | F94: O2264 | G94: O2789 | H94: O2079 | I94: O2063 | J94: =RANDBETWEEN(45,100)/10 -> 8.2 | N94: O2264 O2789 O2079 O2063
A95: C094 | B95: Harriot Shireff | C95: Female | D95: Surat | E95: tara.iyer@example.com | F95: O2427 | J95: =RANDBETWEEN(45,100)/10 -> 4.8 | N95: O2427
A96: C095 | B96: Rayshell Klawi | C96: Female | D96: Chennai | E96: saanvi.iyer@example.com | F96: O2885 | G96: O2444 | H96: O2118 | I96: O2003 | J96: =RANDBETWEEN(45,100)/10 -> 5.4 | N96: O2885 O2444 O2118 O2003
A97: C096 | B97: Rosco Crinion | C97: Male | D97: Lucknow | E97: diya.menon@example.com | F97: O2147 | G97: O2052 | J97: =RANDBETWEEN(45,100)/10 -> 8.8 | N97: O2147 O2052
A98: C097 | B98: Lars Harrinson | C98: Male | D98: Pune | E98: anaya.chopra@example.com | F98: O2685 | G98: O2857 | H98: O2394 | J98: =RANDBETWEEN(45,100)/10 -> 6 | N98: O2685 O2857 O2394
A99: C098 | B99: Karleen Borrott | C99: Female | D99: Pune | E99: aryan.sharma@example.com | F99: O2099 | G99: O2765 | J99: =RANDBETWEEN(45,100)/10 -> 7.5 | N99: O2099 O2765
A100: C099 | B100: Feodora Echlin | C100: Female | D100: Ludhiana | E100: myra.bhat@example.com | F100: O2570 | G100: O2745 | H100: O2866 | J100: =RANDBETWEEN(45,100)/10 -> 5.4 | N100: O2570 O2745 O2866
...

Sheet Pivot_Table
B3: Sum of Total_Sale | D3: Sum of Quantity_Sold | F3: Sum of Profit | H3: Average of Rating
B4: 2490673 | D4: 5595 | F4: 287330 | H4: 7.2438903
B7: Row Labels | C7: Average of Rating
B8: Female | C8: 7.2191589 | F8: Row Labels | G8: Sum of Total_Sale
B9: Male | C9: 7.2721925 | F9: COD | G9: 739523
B10: Grand Total | C10: 7.2438903 | F10: Credit | G10: 468103
F11: Debit | G11: 661245
F12: EMI | G12: 621802
C13: Row Labels | D13: Sum of Total_Sale | F13: Grand Total | G13: 2490673
C14: 2020 | D14: 440628
C15: 2021 | D15: 467992
C16: 2022 | D16: 476140 | F16: Row Labels | G16: Sum of Total_Sale
B17: Sum of Total_Sale | C17: 2023 | D17: 470110 | F17: Beauty & Personal Care | G17: 231375
B18: 2490673 | C18: 2024 | D18: 476558 | F18: Books | G18: 186782
C19: 2025 | D19: 159245 | F19: Clothing | G19: 184206
C20: Grand Total | D20: 2490673 | F20: Electronics | G20: 304451
F21: Footwear | G21: 236332
F22: Furniture | G22: 402280
F23: Home Appliances | G23: 358771
F24: Sports & Fitness | G24: 179550
A25: Row Labels | B25: Count of Order_id | F25: Stationery | G25: 269456
A26: Male | B26: 464 | F26: Toys & Games | G26: 137470
A27: Female | B27: 536 | F27: Grand Total | G27: 2490673
A28: Grand Total | B28: 1000
D38: Sum of Profit | E38: Column Labels
D39: Row Labels | E39: 2020 | F39: 2021 | G39: 2022 | H39: 2023 | I39: 2024 | J39: 2025 | K39: Grand Total
D40: January | E40: 1646 | F40: 10921 | G40: 3294 | H40: 8828 | I40: 5390 | J40: -660 | K40: 29419
D41: February | E41: 7316 | F41: 8856 | G41: 1682 | H41: 3771 | I41: 6714 | J41: 1936 | K41: 30275
D42: March | E42: 3211 | F42: -1471 | G42: 3629 | H42: 4117 | I42: 15351 | J42: -220 | K42: 24617
D43: April | E43: 6391 | F43: 4381 | G43: 3105 | H43: 3950 | I43: 3657 | J43: 1276 | K43: 22760
D44: May | E44: 3972 | F44: 2795 | G44: 2272 | H44: 2521 | I44: 3955 | J44: 4767 | K44: 20282
D45: June | E45: 8830 | F45: 4533 | G45: 7207 | H45: 13892 | I45: 6184 | K45: 40646
D46: July | E46: -822 | F46: 11631 | G46: 8024 | H46: 5226 | I46: 6355 | K46: 30414
D47: August | E47: 1199 | F47: 4998 | G47: 5348 | H47: 7838 | I47: -401 | K47: 18982
D48: September | E48: -200 | F48: 2278 | G48: 2965 | H48: 5709 | I48: 2253 | K48: 13005
D49: October | E49: -1069 | F49: 6357 | G49: 1394 | H49: 2304 | I49: 6625 | K49: 15611
D50: November | E50: 8347 | F50: 4868 | G50: 4643 | H50: -605 | I50: -931 | K50: 16322
D51: December | E51: -1695 | F51: 10321 | G51: 9810 | H51: -1864 | I51: 8425 | K51: 24997
D52: Grand Total | E52: 37126 | F52: 70468 | G52: 53373 | H52: 55687 | I52: 63577 | J52: 7099 | K52: 287330
D57: Row Labels | E57: Sum of Profit
D58: Jan | E58: 29419
D59: Feb | E59: 30275
A60: Row Labels | B60: Count of Order_id | D60: Mar | E60: 24617
A61: Female | D61: Apr | E61: 22760
A62: Ahmedabad | B62: 27 | D62: May | E62: 20282
A63: Bengaluru | B63: 28 | D63: Jun | E63: 40646
A64: Bhopal | B64: 20 | D64: Jul | E64: 30414
A65: Chennai | B65: 30 | D65: Aug | E65: 18982
A66: Coimbatore | B66: 28 | D66: Sep | E66: 13005
A67: Delhi | B67: 35 | D67: Oct | E67: 15611
A68: Hyderabad | B68: 29 | D68: Nov | E68: 16322
A69: Indore | B69: 27 | D69: Dec | E69: 24997
A70: Jaipur | B70: 21 | D70: Grand Total | E70: 287330
A71: Kanpur | B71: 18
A72: Kolkata | B72: 29
A73: Lucknow | B73: 16
A74: Ludhiana | B74: 27
A75: Mumbai | B75: 41
A76: Nagpur | B76: 33 | D76: Row Labels | E76: Sum of Total_Sale
A77: Patna | B77: 32 | D77: January | E77: 253083
A78: Pune | B78: 23 | D78: February | E78: 187801
A79: Surat | B79: 24 | D79: March | E79: 274636
A80: Vadodara | B80: 22 | D80: April | E80: 237626
A81: Visakhapatnam | B81: 26 | D81: May | E81: 236208 | P81: Row Labels | Q81: Count of Order_id
A82: Male | D82: June | E82: 205545 | P82: Ahmedabad | Q82: 57 | X82: {=P82:P101} -> Ahmedabad | Y82: {=Q82:Q101} -> 57
A83: Ahmedabad | B83: 30 | D83: July | E83: 213715 | P83: Bengaluru | Q83: 52 | X83: Bengaluru | Y83: 52
A84: Bengaluru | B84: 24 | D84: August | E84: 196531 | P84: Bhopal | Q84: 42 | X84: Bhopal | Y84: 42
A85: Bhopal | B85: 22 | D85: September | E85: 169102 | P85: Chennai | Q85: 46 | X85: Chennai | Y85: 46
A86: Chennai | B86: 16 | D86: October | E86: 141141 | P86: Coimbatore | Q86: 69 | X86: Coimbatore | Y86: 69
A87: Coimbatore | B87: 41 | D87: November | E87: 203982 | P87: Delhi | Q87: 66 | X87: Delhi | Y87: 66
A88: Delhi | B88: 31 | D88: December | E88: 171303 | P88: Hyderabad | Q88: 48 | X88: Hyderabad | Y88: 48
A89: Hyderabad | B89: 19 | D89: Grand Total | E89: 2490673 | P89: Indore | Q89: 50 | X89: Indore | Y89: 50
A90: Indore | B90: 23 | P90: Jaipur | Q90: 43 | X90: Jaipur | Y90: 43
A91: Jaipur | B91: 22 | P91: Kanpur | Q91: 42 | X91: Kanpur | Y91: 42
A92: Kanpur | B92: 24 | P92: Kolkata | Q92: 60 | X92: Kolkata | Y92: 60
A93: Kolkata | B93: 31 | P93: Lucknow | Q93: 35 | X93: Lucknow | Y93: 35
A94: Lucknow | B94: 19 | P94: Ludhiana | Q94: 46 | X94: Ludhiana | Y94: 46
A95: Ludhiana | B95: 19 | P95: Mumbai | Q95: 62 | X95: Mumbai | Y95: 62
A96: Mumbai | B96: 21 | P96: Nagpur | Q96: 59 | X96: Nagpur | Y96: 59
A97: Nagpur | B97: 26 | P97: Patna | Q97: 44 | X97: Patna | Y97: 44
A98: Patna | B98: 12 | P98: Pune | Q98: 43 | X98: Pune | Y98: 43
A99: Pune | B99: 20 | P99: Surat | Q99: 43 | X99: Surat | Y99: 43
A100: Surat | B100: 19 | P100: Vadodara | Q100: 44 | X100: Vadodara | Y100: 44
A101: Vadodara | B101: 22 | P101: Visakhapatnam | Q101: 49 | X101: Visakhapatnam | Y101: 49
A102: Visakhapatnam | B102: 23 | P102: Grand Total | Q102: 1000
A103: Grand Total | B103: 1000
V108: =TRIM(CLEAN(V82))
V109: =TRIM(CLEAN(V83))
V110: =TRIM(CLEAN(V84))
V111: =TRIM(CLEAN(V85))
V112: =TRIM(CLEAN(V86))
V113: =TRIM(CLEAN(V87))
V114: =TRIM(CLEAN(V88))
V115: =TRIM(CLEAN(V89))
V116: =TRIM(CLEAN(V90))
V117: =TRIM(CLEAN(V91))
V118: =TRIM(CLEAN(V92))
V119: =TRIM(CLEAN(V93))
... V129: =TRIM(CLEAN(V103))

Sheet Dashboard
